Workbook

Sheet Disclaimer 
B2: Notes
B8: This report (this “Report”) has been prepared by Eldridge Capital Management, LLC (“ECM”) and the information contained herein may not be reproduced or used, in whole or in part, for any purpose other than discussions with ECM or ECM’s affiliates (together, the “Eldridge Group””), and their officers, directors, employees, partners, and representatives (collectively, the “Representatives”). This Report if provided for informational purposes only and is produced in response to SBL’s request.
B13: Recipients of this Report acknowledge that certain information contained herein comes from third party sources that Eldridge believes to be accurate and current; however the Eldridge Group and the Representatives shall have no liability for any misstatement or omission of fact or any opinion expressed herein. Recipients should not assume that the information in this Report is accurate as of any date other than the date of this Report. Nothing contained herein is, or should relied upon as, a promise or representations as to future performance. Any estimates and projections contained herein involve significant elements of subjective judgement and analysis that may not be correct. The economic valuations contained in this Report are base don current market conditions, which may change significantly over a short period of time. Changes and events occurring after the date hereof may affect the validity of the conclusions of this Report.
B22: Past performance is not indicative of, or a guarantee of, future results, and the information set forth herein should not be viewed as having any bearing on how any fund or account managed by ECM will perform. There are risks inherent in the investments, funds, and accounts managed by ECM, including potential for losses of some or all of an investment. Any performance information included in this Report is unaudited and subject to change.

Sheet Report
B1: SBL CLO ABS Report
B2: Prepared As of: | C2: View As Portfolio:
C3: Choose the desired portfolio in the drop down
B4: 46142 | C4: All Portfolios
B6: Summary Page
B8: Executive Summary | E8: Tranche Rating | K8: Weighted Average Life
B9: Characteristics | C9: Total | E9: Tranche Rating | F9: Current Face (M) | G9: Market Value (M) | H9: Portfolio % CF | I9: Portfolio % MV | K9: WAL | L9: Current Face (M) | M9: Market Value (M) | N9: Portfolio % CF | O9: Portfolio % MV
B10: Face Value | C10: =C54 -> 1.792046e+09 | E10: AAA | F10: =Table13[[#This Row],[Portfolio % CF]]*$C$10/1000000 -> 5.25 | G10: =Table13[[#This Row],[Portfolio % MV]]*$C$11/1000000 -> 5.2668998 | H10: =IFERROR(IF($C$4="All Portfolios", SUMIFS(tbl_rawhold[Current Face],tbl_rawhold[Tranche Rating],Table13[[#This Row],[Tranche Rating]])/$C$10, SUMIFS(tbl_rawhold[Current Face],tbl_rawhold[Tranche Rating],Table13[[#This Row],[Tranche Rating]],tbl_rawhold[Portfolio_Name],$C$4)/$C$10),0) -> 0.0029296124 | I10: =IFERROR(IF($C$4="All Portfolios", SUMIFS(tbl_rawhold[BASEMarket Value],tbl_rawhold[Tranche Rating],Table13[[#This Row],[Tranche Rating]])/$C$11, SUMIFS(tbl_rawhold[BASEMarket Value],tbl_rawhold[Tranche Rating],Table13[[#This Row],[Tranche Rating]],tbl_rawhold[Portfolio_Name],$C$4)/$C$11),0) -> 0.0029797987 | K10: 0<2 | L10: =Table14[[#This Row],[Portfolio % CF]]*$C$10/1000000 -> 181.50253 | M10: =Table14[[#This Row],[Portfolio % MV]]*$C$11/1000000 -> 175.65111 | N10: =IFERROR(IF($C$4="All Portfolios", SUMIFS(Positions!$C$2:$C$644,Positions!$U$2:$U$644,Table14[[#This Row],[WAL]])/$C$10, SUMIFS(Positions!$C$2:$C$644,Positions!$U$2:$U$644,Table14[[#This Row],[WAL]],Positions!$M$2:$M$644,$C$4)/$C$10),0) -> 0.10128229 | O10: =IFERROR(IF($C$4="All Portfolios", SUMIFS(Positions!$D$2:$D$644,Positions!$U$2:$U$644,Table14[[#This Row],[WAL]])/$C$11, SUMIFS(Positions!$D$2:$D$644,Positions!$U$2:$U$644,Table14[[#This Row],[WAL]],Positions!$M$2:$M$644,$C$4)/$C$11),0) -> 0.099376287
B11: Market Value | C11: =D54 -> 1.7675354e+09 | E11: AA | F11: =Table13[[#This Row],[Portfolio % CF]]*$C$10/1000000 -> 120.49796 | G11: =Table13[[#This Row],[Portfolio % MV]]*$C$11/1000000 -> 120.65678 | H11: =IFERROR(IF($C$4="All Portfolios", SUMIFS(tbl_rawhold[Current Face],tbl_rawhold[Tranche Rating],Table13[[#This Row],[Tranche Rating]])/$C$10, SUMIFS(tbl_rawhold[Current Face],tbl_rawhold[Tranche Rating],Table13[[#This Row],[Tranche Rating]],tbl_rawhold[Portfolio_Name],$C$4)/$C$10),0) -> 0.067240442 | I11: =IFERROR(IF($C$4="All Portfolios", SUMIFS(tbl_rawhold[BASEMarket Value],tbl_rawhold[Tranche Rating],Table13[[#This Row],[Tranche Rating]])/$C$11, SUMIFS(tbl_rawhold[BASEMarket Value],tbl_rawhold[Tranche Rating],Table13[[#This Row],[Tranche Rating]],tbl_rawhold[Portfolio_Name],$C$4)/$C$11),0) -> 0.068262724 | K11: 2<4 | L11: =Table14[[#This Row],[Portfolio % CF]]*$C$10/1000000 -> 424.41139 | M11: =Table14[[#This Row],[Portfolio % MV]]*$C$11/1000000 -> 409.8227 | N11: =IFERROR(IF($C$4="All Portfolios", SUMIFS(Positions!$C$2:$C$644,Positions!$U$2:$U$644,Table14[[#This Row],[WAL]])/$C$10, SUMIFS(Positions!$C$2:$C$644,Positions!$U$2:$U$644,Table14[[#This Row],[WAL]],Positions!$M$2:$M$644,$C$4)/$C$10),0) -> 0.23683064 | O11: =IFERROR(IF($C$4="All Portfolios", SUMIFS(Positions!$D$2:$D$644,Positions!$U$2:$U$644,Table14[[#This Row],[WAL]])/$C$11, SUMIFS(Positions!$D$2:$D$644,Positions!$U$2:$U$644,Table14[[#This Row],[WAL]],Positions!$M$2:$M$644,$C$4)/$C$11),0) -> 0.2318611
B12: WA Coupon | C12: {=IFERROR(IF( $C$4 = "All Portfolios", SUMPRODUCT( tbl_rawhold[Current Face] * (tbl_rawhold[Coupon Rate] * 0.01) ) / SUMIFS(tbl_rawhold[Current Face], tbl_rawhold[Coupon Rate],"> 0"), SUMPRODUCT((tbl_rawhold[Portfolio_Name] = $C$4) * tbl_rawhold[Current Face] * (tbl_rawhold[Coupon Rate] * 0.01) ) / SUMIFS(tbl_rawhold[Current Face], tbl_rawhold[Coupon Rate],"> 0",tbl_rawhold[Portfolio_Name], $C$4)),0)} -> 0.071441017 | E12: A | F12: =Table13[[#This Row],[Portfolio % CF]]*$C$10/1000000 -> 441.25372 | G12: =Table13[[#This Row],[Portfolio % MV]]*$C$11/1000000 -> 441.59185 | H12: =IFERROR(IF($C$4="All Portfolios", SUMIFS(tbl_rawhold[Current Face],tbl_rawhold[Tranche Rating],Table13[[#This Row],[Tranche Rating]])/$C$10, SUMIFS(tbl_rawhold[Current Face],tbl_rawhold[Tranche Rating],Table13[[#This Row],[Tranche Rating]],tbl_rawhold[Portfolio_Name],$C$4)/$C$10),0) -> 0.24622902 | I12: =IFERROR(IF($C$4="All Portfolios", SUMIFS(tbl_rawhold[BASEMarket Value],tbl_rawhold[Tranche Rating],Table13[[#This Row],[Tranche Rating]])/$C$11, SUMIFS(tbl_rawhold[BASEMarket Value],tbl_rawhold[Tranche Rating],Table13[[#This Row],[Tranche Rating]],tbl_rawhold[Portfolio_Name],$C$4)/$C$11),0) -> 0.24983479 | K12: 4<6 | L12: =Table14[[#This Row],[Portfolio % CF]]*$C$10/1000000 -> 383.77553 | M12: =Table14[[#This Row],[Portfolio % MV]]*$C$11/1000000 -> 375.77441 | N12: =IFERROR(IF($C$4="All Portfolios", SUMIFS(Positions!$C$2:$C$644,Positions!$U$2:$U$644,Table14[[#This Row],[WAL]])/$C$10, SUMIFS(Positions!$C$2:$C$644,Positions!$U$2:$U$644,Table14[[#This Row],[WAL]],Positions!$M$2:$M$644,$C$4)/$C$10),0) -> 0.21415496 | O12: =IFERROR(IF($C$4="All Portfolios", SUMIFS(Positions!$D$2:$D$644,Positions!$U$2:$U$644,Table14[[#This Row],[WAL]])/$C$11, SUMIFS(Positions!$D$2:$D$644,Positions!$U$2:$U$644,Table14[[#This Row],[WAL]],Positions!$M$2:$M$644,$C$4)/$C$11),0) -> 0.21259795
B13: WA Purchase Price | C13: =IFERROR(IF($C$4="All Portfolios", SUM(tbl_rawhold[BASEOriginal Cost])/C10, SUMIF(tbl_rawhold[Portfolio_Name],$C$4,tbl_rawhold[BASEOriginal Cost])/C10),0) -> 1.7402397 | E13: BBB | F13: =Table13[[#This Row],[Portfolio % CF]]*$C$10/1000000 -> 2310.0751 | G13: =Table13[[#This Row],[Portfolio % MV]]*$C$11/1000000 -> 2302.2705 | H13: =IFERROR(IF($C$4="All Portfolios", SUMIFS(tbl_rawhold[Current Face],tbl_rawhold[Tranche Rating],Table13[[#This Row],[Tranche Rating]])/$C$10, SUMIFS(tbl_rawhold[Current Face],tbl_rawhold[Tranche Rating],Table13[[#This Row],[Tranche Rating]],tbl_rawhold[Portfolio_Name],$C$4)/$C$10),0) -> 1.2890713 | I13: =IFERROR(IF($C$4="All Portfolios", SUMIFS(tbl_rawhold[BASEMarket Value],tbl_rawhold[Tranche Rating],Table13[[#This Row],[Tranche Rating]])/$C$11, SUMIFS(tbl_rawhold[BASEMarket Value],tbl_rawhold[Tranche Rating],Table13[[#This Row],[Tranche Rating]],tbl_rawhold[Portfolio_Name],$C$4)/$C$11),0) -> 1.3025315 | K13: 6<8 | L13: =Table14[[#This Row],[Portfolio % CF]]*$C$10/1000000 -> 638.83394 | M13: =Table14[[#This Row],[Portfolio % MV]]*$C$11/1000000 -> 633.56748 | N13: =IFERROR(IF($C$4="All Portfolios", SUMIFS(Positions!$C$2:$C$644,Positions!$U$2:$U$644,Table14[[#This Row],[WAL]])/$C$10, SUMIFS(Positions!$C$2:$C$644,Positions!$U$2:$U$644,Table14[[#This Row],[WAL]],Positions!$M$2:$M$644,$C$4)/$C$10),0) -> 0.35648301 | O13: =IFERROR(IF($C$4="All Portfolios", SUMIFS(Positions!$D$2:$D$644,Positions!$U$2:$U$644,Table14[[#This Row],[WAL]])/$C$11, SUMIFS(Positions!$D$2:$D$644,Positions!$U$2:$U$644,Table14[[#This Row],[WAL]],Positions!$M$2:$M$644,$C$4)/$C$11),0) -> 0.35844683
B14: WA Market Price | C14: =IFERROR(C11/C10,0) -> 0.9863226 | E14: BB | F14: =Table13[[#This Row],[Portfolio % CF]]*$C$10/1000000 -> 234.07859 | G14: =Table13[[#This Row],[Portfolio % MV]]*$C$11/1000000 -> 214.66818 | H14: =IFERROR(IF($C$4="All Portfolios", SUMIFS(tbl_rawhold[Current Face],tbl_rawhold[Tranche Rating],Table13[[#This Row],[Tranche Rating]])/$C$10, SUMIFS(tbl_rawhold[Current Face],tbl_rawhold[Tranche Rating],Table13[[#This Row],[Tranche Rating]],tbl_rawhold[Portfolio_Name],$C$4)/$C$10),0) -> 0.13062086 | I14: =IFERROR(IF($C$4="All Portfolios", SUMIFS(tbl_rawhold[BASEMarket Value],tbl_rawhold[Tranche Rating],Table13[[#This Row],[Tranche Rating]])/$C$11, SUMIFS(tbl_rawhold[BASEMarket Value],tbl_rawhold[Tranche Rating],Table13[[#This Row],[Tranche Rating]],tbl_rawhold[Portfolio_Name],$C$4)/$C$11),0) -> 0.12145057 | K14: 8<10 | L14: =Table14[[#This Row],[Portfolio % CF]]*$C$10/1000000 -> 1488.9836 | M14: =Table14[[#This Row],[Portfolio % MV]]*$C$11/1000000 -> 1494.9256 | N14: =IFERROR(IF($C$4="All Portfolios", SUMIFS(Positions!$C$2:$C$644,Positions!$U$2:$U$644,Table14[[#This Row],[WAL]])/$C$10, SUMIFS(Positions!$C$2:$C$644,Positions!$U$2:$U$644,Table14[[#This Row],[WAL]],Positions!$M$2:$M$644,$C$4)/$C$10),0) -> 0.83088473 | O14: =IFERROR(IF($C$4="All Portfolios", SUMIFS(Positions!$D$2:$D$644,Positions!$U$2:$U$644,Table14[[#This Row],[WAL]])/$C$11, SUMIFS(Positions!$D$2:$D$644,Positions!$U$2:$U$644,Table14[[#This Row],[WAL]],Positions!$M$2:$M$644,$C$4)/$C$11),0) -> 0.84576837
B15: WA Life | C15: {=IFERROR(IF( $C$4 = "All Portfolios", SUMPRODUCT( tbl_rawhold[Current Face]* tbl_rawhold[WAL] ) / SUMIFS(tbl_rawhold[Current Face], tbl_rawhold[WAL],"> 0"), SUMPRODUCT((tbl_rawhold[Portfolio_Name] = $C$4) * tbl_rawhold[Current Face] * tbl_rawhold[WAL] ) / SUMIFS(tbl_rawhold[Current Face], tbl_rawhold[WAL],"> 0",tbl_rawhold[Portfolio_Name], $C$4)),0)} -> 6.8734366 | E15: B | F15: =Table13[[#This Row],[Portfolio % CF]]*$C$10/1000000 -> 21.376475 | G15: =Table13[[#This Row],[Portfolio % MV]]*$C$11/1000000 -> 20.703746 | H15: =IFERROR(IF($C$4="All Portfolios", SUMIFS(tbl_rawhold[Current Face],tbl_rawhold[Tranche Rating],Table13[[#This Row],[Tranche Rating]])/$C$10, SUMIFS(tbl_rawhold[Current Face],tbl_rawhold[Tranche Rating],Table13[[#This Row],[Tranche Rating]],tbl_rawhold[Portfolio_Name],$C$4)/$C$10),0) -> 0.01192853 | I15: =IFERROR(IF($C$4="All Portfolios", SUMIFS(tbl_rawhold[BASEMarket Value],tbl_rawhold[Tranche Rating],Table13[[#This Row],[Tranche Rating]])/$C$11, SUMIFS(tbl_rawhold[BASEMarket Value],tbl_rawhold[Tranche Rating],Table13[[#This Row],[Tranche Rating]],tbl_rawhold[Portfolio_Name],$C$4)/$C$11),0) -> 0.011713341 | K15: 10+ | L15: =Table14[[#This Row],[Portfolio % CF]]*$C$10/1000000 -> 4.495 | M15: =Table14[[#This Row],[Portfolio % MV]]*$C$11/1000000 -> 4.5736304 | N15: =IFERROR(IF($C$4="All Portfolios", SUMIFS(Positions!$C$2:$C$644,Positions!$U$2:$U$644,Table14[[#This Row],[WAL]])/$C$10, SUMIFS(Positions!$C$2:$C$644,Positions!$U$2:$U$644,Table14[[#This Row],[WAL]],Positions!$M$2:$M$644,$C$4)/$C$10),0) -> 0.0025083062 | O15: =IFERROR(IF($C$4="All Portfolios", SUMIFS(Positions!$D$2:$D$644,Positions!$U$2:$U$644,Table14[[#This Row],[WAL]])/$C$11, SUMIFS(Positions!$D$2:$D$644,Positions!$U$2:$U$644,Table14[[#This Row],[WAL]],Positions!$M$2:$M$644,$C$4)/$C$11),0) -> 0.002587575
B16: WA Spread | C16: {=IFERROR(IF( $C$4 = "All Portfolios", SUMPRODUCT( tbl_rawhold[Current Face]* tbl_rawhold[Spread] ) / SUMIFS(tbl_rawhold[Current Face], tbl_rawhold[Spread],"> 0"), SUMPRODUCT((tbl_rawhold[Portfolio_Name] = $C$4) * tbl_rawhold[Current Face] * tbl_rawhold[Spread] ) / SUMIFS(tbl_rawhold[Current Face], tbl_rawhold[Spread],"> 0",tbl_rawhold[Portfolio_Name], $C$4)),0)} -> 320.4024 | E16: CCC | F16: =Table13[[#This Row],[Portfolio % CF]]*$C$10/1000000 -> 1.203 | G16: =Table13[[#This Row],[Portfolio % MV]]*$C$11/1000000 -> 0.80212672 | H16: =IFERROR(IF($C$4="All Portfolios", SUMIFS(tbl_rawhold[Current Face],tbl_rawhold[Tranche Rating],Table13[[#This Row],[Tranche Rating]])/$C$10, SUMIFS(tbl_rawhold[Current Face],tbl_rawhold[Tranche Rating],Table13[[#This Row],[Tranche Rating]],tbl_rawhold[Portfolio_Name],$C$4)/$C$10),0) -> 0.00067129975 | I16: =IFERROR(IF($C$4="All Portfolios", SUMIFS(tbl_rawhold[BASEMarket Value],tbl_rawhold[Tranche Rating],Table13[[#This Row],[Tranche Rating]])/$C$11, SUMIFS(tbl_rawhold[BASEMarket Value],tbl_rawhold[Tranche Rating],Table13[[#This Row],[Tranche Rating]],tbl_rawhold[Portfolio_Name],$C$4)/$C$11),0) -> 0.00045381083 | K16: unknown | L16: =Table14[[#This Row],[Portfolio % CF]]*$C$10/1000000 -> 11.732833 | M16: =Table14[[#This Row],[Portfolio % MV]]*$C$11/1000000 -> 11.645209 | N16: =IFERROR(IF($C$4="All Portfolios", SUMIFS(Positions!$C$2:$C$644,Positions!$U$2:$U$644,Table14[[#This Row],[WAL]])/$C$10, SUMIFS(Positions!$C$2:$C$644,Positions!$U$2:$U$644,Table14[[#This Row],[WAL]],Positions!$M$2:$M$644,$C$4)/$C$10),0) -> 0.0065471719 | O16: =IFERROR(IF($C$4="All Portfolios", SUMIFS(Positions!$D$2:$D$644,Positions!$U$2:$U$644,Table14[[#This Row],[WAL]])/$C$11, SUMIFS(Positions!$D$2:$D$644,Positions!$U$2:$U$644,Table14[[#This Row],[WAL]],Positions!$M$2:$M$644,$C$4)/$C$11),0) -> 0.0065883878
B17: WA DM | C17: {=IFERROR(IF( $C$4 = "All Portfolios", SUMPRODUCT( tbl_rawhold[Current Face]* tbl_rawhold[Implied DM] ) / SUMIFS(tbl_rawhold[Current Face], tbl_rawhold[Implied DM],"> 0"), SUMPRODUCT((tbl_rawhold[Portfolio_Name] = $C$4) * tbl_rawhold[Current Face] * tbl_rawhold[Implied DM] ) / SUMIFS(tbl_rawhold[Current Face], tbl_rawhold[Implied DM],"> 0",tbl_rawhold[Portfolio_Name], $C$4)),0)} -> 350.95738 | E17: NR | F17: =Table13[[#This Row],[Portfolio % CF]]*$C$10/1000000 -> 0 | G17: =Table13[[#This Row],[Portfolio % MV]]*$C$11/1000000 -> 0 | H17: =IFERROR(IF($C$4="All Portfolios", SUMIFS(tbl_rawhold[Current Face],tbl_rawhold[Tranche Rating],Table13[[#This Row],[Tranche Rating]])/$C$10, SUMIFS(tbl_rawhold[Current Face],tbl_rawhold[Tranche Rating],Table13[[#This Row],[Tranche Rating]],tbl_rawhold[Portfolio_Name],$C$4)/$C$10),0) -> 0 | I17: =IFERROR(IF($C$4="All Portfolios", SUMIFS(tbl_rawhold[BASEMarket Value],tbl_rawhold[Tranche Rating],Table13[[#This Row],[Tranche Rating]])/$C$11, SUMIFS(tbl_rawhold[BASEMarket Value],tbl_rawhold[Tranche Rating],Table13[[#This Row],[Tranche Rating]],tbl_rawhold[Portfolio_Name],$C$4)/$C$11),0) -> 0 | K17: Total | L17: =SUBTOTAL(109,Table14[Current Face (M)]) -> 3133.7348 | M17: =SUBTOTAL(109,Table14[Market Value (M)]) -> 3105.9601 | N17: =SUBTOTAL(109,Table14[Portfolio % CF]) -> 1.7486911 | O17: =SUBTOTAL(109,Table14[Portfolio % MV]) -> 1.7572265
B18: WA Yield | C18: {=IFERROR(IF( $C$4 = "All Portfolios", SUMPRODUCT( tbl_rawhold[Current Face]* tbl_rawhold[Yield] ) / SUMIFS(tbl_rawhold[Current Face], tbl_rawhold[Yield],"> 0"), SUMPRODUCT((tbl_rawhold[Portfolio_Name] = $C$4) * tbl_rawhold[Current Face] * tbl_rawhold[Yield] ) / SUMIFS(tbl_rawhold[Current Face], tbl_rawhold[Yield],"> 0",tbl_rawhold[Portfolio_Name], $C$4)),0)} -> 7.1814735 | E18: Total | F18: =SUBTOTAL(109,Table13[Current Face (M)]) -> 3133.7348 | G18: =SUBTOTAL(109,Table13[Market Value (M)]) -> 3105.9601 | H18: =SUBTOTAL(109,Table13[Portfolio % CF]) -> 1.7486911 | I18: =SUBTOTAL(109,Table13[Portfolio % MV]) -> 1.7572265
B19: Number of Issuers | C19: =G54 -> 37
B20: Number of Managers | C20: =COUNTIFS(tbl_report_manager[Current Face],"<>0") -> 16
B21: Number of Cusips | C21: =H54 -> 226
B25: CLO Debt Coupon | H25: Vintage Year | N25: Collateral Type
B26: Coupon | C26: Current Face (M) | D26: Market Value (M) | E26: Portfolio % CF | F26: Portfolio % MV | H26: Vintage | I26: Current Face (M) | J26: Market Value (M) | K26: Portfolio % CF | L26: Portfolio % MV | N26: Collateral Type | O26: Current Face (M) | P26: Market Value (M) | Q26: Portfolio % CF | R26: Portfolio % MV
B27: 0<3 | C27: =Table15[[#This Row],[Portfolio % CF]]*$C$10/1000000 -> 172.57906 | D27: =Table15[[#This Row],[Portfolio % MV]]*$C$11/1000000 -> 157.63821 | E27: =IFERROR(IF($C$4="All Portfolios", SUMIFS(Positions!$C$2:$C$644,Positions!$V$2:$V$644,Table15[[#This Row],[Coupon]])/$C$10, SUMIFS(Positions!$C$2:$C$644,Positions!$V$2:$V$644,Table15[[#This Row],[Coupon]],Positions!$M$2:$M$644,$C$4)/$C$10),0) -> 0.09630281 | F27: =IFERROR(IF($C$4="All Portfolios", SUMIFS(Positions!$D$2:$D$644,Positions!$V$2:$V$644,Table15[[#This Row],[Coupon]])/$C$11, SUMIFS(Positions!$D$2:$D$644,Positions!$V$2:$V$644,Table15[[#This Row],[Coupon]],Positions!$M$2:$M$644,$C$4)/$C$11),0) -> 0.08918532 | H27: 2017 | I27: =Table20[[#This Row],[Portfolio % CF]]*$C$10/1000000 -> 8.125 | J27: =Table20[[#This Row],[Portfolio % MV]]*$C$11/1000000 -> 8.1479044 | K27: =IFERROR(IF($C$4="All Portfolios", SUMIFS(Positions!$C$2:$C$644,tbl_rawhold[Vintage],Table20[[#This Row],[Vintage]])/$C$10, SUMIFS(Positions!$C$2:$C$644,tbl_rawhold[Vintage],Table20[[#This Row],[Vintage]],Positions!$M$2:$M$644,$C$4)/$C$10),0) -> 0.0045339239 | L27: =IFERROR(IF($C$4="All Portfolios", SUMIFS(Positions!$D$2:$D$644,tbl_rawhold[Vintage],Table20[[#This Row],[Vintage]])/$C$11, SUMIFS(Positions!$D$2:$D$644,tbl_rawhold[Vintage],Table20[[#This Row],[Vintage]],Positions!$M$2:$M$644,$C$4)/$C$11),0) -> 0.0046097545 | N27: Aircraft Portfolio | O27: =Table21[[#This Row],[Portfolio % CF]]*$C$10/1000000 -> 0.04810924 | P27: =Table21[[#This Row],[Portfolio % MV]]*$C$11/1000000 -> 0.0478367 | Q27: =IFERROR(IF($C$4="All Portfolios", SUMIFS(Positions!$C$2:$C$644,tbl_rawhold[Collateral Type],Table21[[#This Row],[Collateral Type]])/$C$10, SUMIFS(Positions!$C$2:$C$644,tbl_rawhold[Collateral Type],Table21[[#This Row],[Collateral Type]],Positions!$M$2:$M$644,$C$4)/$C$10),0) -> 2.6845986e-05 | R27: =IFERROR(IF($C$4="All Portfolios", SUMIFS(Positions!$D$2:$D$644,tbl_rawhold[Collateral Type],Table21[[#This Row],[Collateral Type]])/$C$11, SUMIFS(Positions!$D$2:$D$644,tbl_rawhold[Collateral Type],Table21[[#This Row],[Collateral Type]],Positions!$M$2:$M$644,$C$4)/$C$11),0) -> 2.7064069e-05
B28: 3<4 | C28: =Table15[[#This Row],[Portfolio % CF]]*$C$10/1000000 -> 14.192843 | D28: =Table15[[#This Row],[Portfolio % MV]]*$C$11/1000000 -> 13.527959 | E28: =IFERROR(IF($C$4="All Portfolios", SUMIFS(Positions!$C$2:$C$644,Positions!$V$2:$V$644,Table15[[#This Row],[Coupon]])/$C$10, SUMIFS(Positions!$C$2:$C$644,Positions!$V$2:$V$644,Table15[[#This Row],[Coupon]],Positions!$M$2:$M$644,$C$4)/$C$10),0) -> 0.0079199102 | F28: =IFERROR(IF($C$4="All Portfolios", SUMIFS(Positions!$D$2:$D$644,Positions!$V$2:$V$644,Table15[[#This Row],[Coupon]])/$C$11, SUMIFS(Positions!$D$2:$D$644,Positions!$V$2:$V$644,Table15[[#This Row],[Coupon]],Positions!$M$2:$M$644,$C$4)/$C$11),0) -> 0.0076535714 | H28: 2018 | I28: =Table20[[#This Row],[Portfolio % CF]]*$C$10/1000000 -> 209.57596 | J28: =Table20[[#This Row],[Portfolio % MV]]*$C$11/1000000 -> 209.49104 | K28: =IFERROR(IF($C$4="All Portfolios", SUMIFS(Positions!$C$2:$C$644,tbl_rawhold[Vintage],Table20[[#This Row],[Vintage]])/$C$10, SUMIFS(Positions!$C$2:$C$644,tbl_rawhold[Vintage],Table20[[#This Row],[Vintage]],Positions!$M$2:$M$644,$C$4)/$C$10),0) -> 0.11694787 | L28: =IFERROR(IF($C$4="All Portfolios", SUMIFS(Positions!$D$2:$D$644,tbl_rawhold[Vintage],Table20[[#This Row],[Vintage]])/$C$11, SUMIFS(Positions!$D$2:$D$644,tbl_rawhold[Vintage],Table20[[#This Row],[Vintage]],Positions!$M$2:$M$644,$C$4)/$C$11),0) -> 0.11852155 | N28: Cell Towers | O28: =Table21[[#This Row],[Portfolio % CF]]*$C$10/1000000 -> 8 | P28: =Table21[[#This Row],[Portfolio % MV]]*$C$11/1000000 -> 7.9699829 | Q28: =IFERROR(IF($C$4="All Portfolios", SUMIFS(Positions!$C$2:$C$644,tbl_rawhold[Collateral Type],Table21[[#This Row],[Collateral Type]])/$C$10, SUMIFS(Positions!$C$2:$C$644,tbl_rawhold[Collateral Type],Table21[[#This Row],[Collateral Type]],Positions!$M$2:$M$644,$C$4)/$C$10),0) -> 0.0044641712 | R28: =IFERROR(IF($C$4="All Portfolios", SUMIFS(Positions!$D$2:$D$644,tbl_rawhold[Collateral Type],Table21[[#This Row],[Collateral Type]])/$C$11, SUMIFS(Positions!$D$2:$D$644,tbl_rawhold[Collateral Type],Table21[[#This Row],[Collateral Type]],Positions!$M$2:$M$644,$C$4)/$C$11),0) -> 0.0045090937
B29: 4<5 | C29: =Table15[[#This Row],[Portfolio % CF]]*$C$10/1000000 -> 54.176261 | D29: =Table15[[#This Row],[Portfolio % MV]]*$C$11/1000000 -> 52.133453 | E29: =IFERROR(IF($C$4="All Portfolios", SUMIFS(Positions!$C$2:$C$644,Positions!$V$2:$V$644,Table15[[#This Row],[Coupon]])/$C$10, SUMIFS(Positions!$C$2:$C$644,Positions!$V$2:$V$644,Table15[[#This Row],[Coupon]],Positions!$M$2:$M$644,$C$4)/$C$10),0) -> 0.030231513 | F29: =IFERROR(IF($C$4="All Portfolios", SUMIFS(Positions!$D$2:$D$644,Positions!$V$2:$V$644,Table15[[#This Row],[Coupon]])/$C$11, SUMIFS(Positions!$D$2:$D$644,Positions!$V$2:$V$644,Table15[[#This Row],[Coupon]],Positions!$M$2:$M$644,$C$4)/$C$11),0) -> 0.029494998 | H29: 2019 | I29: =Table20[[#This Row],[Portfolio % CF]]*$C$10/1000000 -> 28.77725 | J29: =Table20[[#This Row],[Portfolio % MV]]*$C$11/1000000 -> 28.817043 | K29: =IFERROR(IF($C$4="All Portfolios", SUMIFS(Positions!$C$2:$C$644,tbl_rawhold[Vintage],Table20[[#This Row],[Vintage]])/$C$10, SUMIFS(Positions!$C$2:$C$644,tbl_rawhold[Vintage],Table20[[#This Row],[Vintage]],Positions!$M$2:$M$644,$C$4)/$C$10),0) -> 0.016058321 | L29: =IFERROR(IF($C$4="All Portfolios", SUMIFS(Positions!$D$2:$D$644,tbl_rawhold[Vintage],Table20[[#This Row],[Vintage]])/$C$11, SUMIFS(Positions!$D$2:$D$644,tbl_rawhold[Vintage],Table20[[#This Row],[Vintage]],Positions!$M$2:$M$644,$C$4)/$C$11),0) -> 0.016303516 | N29: Data Center | O29: =Table21[[#This Row],[Portfolio % CF]]*$C$10/1000000 -> 9.55 | P29: =Table21[[#This Row],[Portfolio % MV]]*$C$11/1000000 -> 9.3323762 | Q29: =IFERROR(IF($C$4="All Portfolios", SUMIFS(Positions!$C$2:$C$644,tbl_rawhold[Collateral Type],Table21[[#This Row],[Collateral Type]])/$C$10, SUMIFS(Positions!$C$2:$C$644,tbl_rawhold[Collateral Type],Table21[[#This Row],[Collateral Type]],Positions!$M$2:$M$644,$C$4)/$C$10),0) -> 0.0053291044 | R29: =IFERROR(IF($C$4="All Portfolios", SUMIFS(Positions!$D$2:$D$644,tbl_rawhold[Collateral Type],Table21[[#This Row],[Collateral Type]])/$C$11, SUMIFS(Positions!$D$2:$D$644,tbl_rawhold[Collateral Type],Table21[[#This Row],[Collateral Type]],Positions!$M$2:$M$644,$C$4)/$C$11),0) -> 0.0052798807
B30: 5<6 | C30: =Table15[[#This Row],[Portfolio % CF]]*$C$10/1000000 -> 124.03283 | D30: =Table15[[#This Row],[Portfolio % MV]]*$C$11/1000000 -> 108.48835 | E30: =IFERROR(IF($C$4="All Portfolios", SUMIFS(Positions!$C$2:$C$644,Positions!$V$2:$V$644,Table15[[#This Row],[Coupon]])/$C$10, SUMIFS(Positions!$C$2:$C$644,Positions!$V$2:$V$644,Table15[[#This Row],[Coupon]],Positions!$M$2:$M$644,$C$4)/$C$10),0) -> 0.069212975 | F30: =IFERROR(IF($C$4="All Portfolios", SUMIFS(Positions!$D$2:$D$644,Positions!$V$2:$V$644,Table15[[#This Row],[Coupon]])/$C$11, SUMIFS(Positions!$D$2:$D$644,Positions!$V$2:$V$644,Table15[[#This Row],[Coupon]],Positions!$M$2:$M$644,$C$4)/$C$11),0) -> 0.061378315 | H30: 2020 | I30: =Table20[[#This Row],[Portfolio % CF]]*$C$10/1000000 -> 134.44791 | J30: =Table20[[#This Row],[Portfolio % MV]]*$C$11/1000000 -> 122.7 | K30: =IFERROR(IF($C$4="All Portfolios", SUMIFS(Positions!$C$2:$C$644,tbl_rawhold[Vintage],Table20[[#This Row],[Vintage]])/$C$10, SUMIFS(Positions!$C$2:$C$644,tbl_rawhold[Vintage],Table20[[#This Row],[Vintage]],Positions!$M$2:$M$644,$C$4)/$C$10),0) -> 0.075024812 | L30: =IFERROR(IF($C$4="All Portfolios", SUMIFS(Positions!$D$2:$D$644,tbl_rawhold[Vintage],Table20[[#This Row],[Vintage]])/$C$11, SUMIFS(Positions!$D$2:$D$644,tbl_rawhold[Vintage],Table20[[#This Row],[Vintage]],Positions!$M$2:$M$644,$C$4)/$C$11),0) -> 0.069418691 | N30: PC Rated Feeder | O30: =Table21[[#This Row],[Portfolio % CF]]*$C$10/1000000 -> 0 | P30: =Table21[[#This Row],[Portfolio % MV]]*$C$11/1000000 -> 0 | Q30: =IFERROR(IF($C$4="All Portfolios", SUMIFS(Positions!$C$2:$C$644,tbl_rawhold[Collateral Type],Table21[[#This Row],[Collateral Type]])/$C$10, SUMIFS(Positions!$C$2:$C$644,tbl_rawhold[Collateral Type],Table21[[#This Row],[Collateral Type]],Positions!$M$2:$M$644,$C$4)/$C$10),0) -> 0 | R30: =IFERROR(IF($C$4="All Portfolios", SUMIFS(Positions!$D$2:$D$644,tbl_rawhold[Collateral Type],Table21[[#This Row],[Collateral Type]])/$C$11, SUMIFS(Positions!$D$2:$D$644,tbl_rawhold[Collateral Type],Table21[[#This Row],[Collateral Type]],Positions!$M$2:$M$644,$C$4)/$C$11),0) -> 0
B31: 6<7 | C31: =Table15[[#This Row],[Portfolio % CF]]*$C$10/1000000 -> 737.01685 | D31: =Table15[[#This Row],[Portfolio % MV]]*$C$11/1000000 -> 738.86286 | E31: =IFERROR(IF($C$4="All Portfolios", SUMIFS(Positions!$C$2:$C$644,Positions!$V$2:$V$644,Table15[[#This Row],[Coupon]])/$C$10, SUMIFS(Positions!$C$2:$C$644,Positions!$V$2:$V$644,Table15[[#This Row],[Coupon]],Positions!$M$2:$M$644,$C$4)/$C$10),0) -> 0.41127118 | F31: =IFERROR(IF($C$4="All Portfolios", SUMIFS(Positions!$D$2:$D$644,Positions!$V$2:$V$644,Table15[[#This Row],[Coupon]])/$C$11, SUMIFS(Positions!$D$2:$D$644,Positions!$V$2:$V$644,Table15[[#This Row],[Coupon]],Positions!$M$2:$M$644,$C$4)/$C$11),0) -> 0.4180187 | H31: 2021 | I31: =Table20[[#This Row],[Portfolio % CF]]*$C$10/1000000 -> 807.27464 | J31: =Table20[[#This Row],[Portfolio % MV]]*$C$11/1000000 -> 787.99579 | K31: =IFERROR(IF($C$4="All Portfolios", SUMIFS(Positions!$C$2:$C$644,tbl_rawhold[Vintage],Table20[[#This Row],[Vintage]])/$C$10, SUMIFS(Positions!$C$2:$C$644,tbl_rawhold[Vintage],Table20[[#This Row],[Vintage]],Positions!$M$2:$M$644,$C$4)/$C$10),0) -> 0.45047653 | L31: =IFERROR(IF($C$4="All Portfolios", SUMIFS(Positions!$D$2:$D$644,tbl_rawhold[Vintage],Table20[[#This Row],[Vintage]])/$C$11, SUMIFS(Positions!$D$2:$D$644,tbl_rawhold[Vintage],Table20[[#This Row],[Vintage]],Positions!$M$2:$M$644,$C$4)/$C$11),0) -> 0.44581612 | N31: Engine Portfolio | O31: =Table21[[#This Row],[Portfolio % CF]]*$C$10/1000000 -> 4.7190396 | P31: =Table21[[#This Row],[Portfolio % MV]]*$C$11/1000000 -> 4.3788523 | Q31: =IFERROR(IF($C$4="All Portfolios", SUMIFS(Positions!$C$2:$C$644,tbl_rawhold[Collateral Type],Table21[[#This Row],[Collateral Type]])/$C$10, SUMIFS(Positions!$C$2:$C$644,tbl_rawhold[Collateral Type],Table21[[#This Row],[Collateral Type]],Positions!$M$2:$M$644,$C$4)/$C$10),0) -> 0.0026333251 | R31: =IFERROR(IF($C$4="All Portfolios", SUMIFS(Positions!$D$2:$D$644,tbl_rawhold[Collateral Type],Table21[[#This Row],[Collateral Type]])/$C$11, SUMIFS(Positions!$D$2:$D$644,tbl_rawhold[Collateral Type],Table21[[#This Row],[Collateral Type]],Positions!$M$2:$M$644,$C$4)/$C$11),0) -> 0.0024773774
B32: 7+ | C32: =Table15[[#This Row],[Portfolio % CF]]*$C$10/1000000 -> 2031.737 | D32: =Table15[[#This Row],[Portfolio % MV]]*$C$11/1000000 -> 2035.3093 | E32: =IFERROR(IF($C$4="All Portfolios", SUMIFS(Positions!$C$2:$C$644,Positions!$V$2:$V$644,Table15[[#This Row],[Coupon]])/$C$10, SUMIFS(Positions!$C$2:$C$644,Positions!$V$2:$V$644,Table15[[#This Row],[Coupon]],Positions!$M$2:$M$644,$C$4)/$C$10),0) -> 1.1337527 | F32: =IFERROR(IF($C$4="All Portfolios", SUMIFS(Positions!$D$2:$D$644,Positions!$V$2:$V$644,Table15[[#This Row],[Coupon]])/$C$11, SUMIFS(Positions!$D$2:$D$644,Positions!$V$2:$V$644,Table15[[#This Row],[Coupon]],Positions!$M$2:$M$644,$C$4)/$C$11),0) -> 1.1514956 | H32: 2022 | I32: =Table20[[#This Row],[Portfolio % CF]]*$C$10/1000000 -> 47.458558 | J32: =Table20[[#This Row],[Portfolio % MV]]*$C$11/1000000 -> 47.150561 | K32: =IFERROR(IF($C$4="All Portfolios", SUMIFS(Positions!$C$2:$C$644,tbl_rawhold[Vintage],Table20[[#This Row],[Vintage]])/$C$10, SUMIFS(Positions!$C$2:$C$644,tbl_rawhold[Vintage],Table20[[#This Row],[Vintage]],Positions!$M$2:$M$644,$C$4)/$C$10),0) -> 0.026482891 | L32: =IFERROR(IF($C$4="All Portfolios", SUMIFS(Positions!$D$2:$D$644,tbl_rawhold[Vintage],Table20[[#This Row],[Vintage]])/$C$11, SUMIFS(Positions!$D$2:$D$644,tbl_rawhold[Vintage],Table20[[#This Row],[Vintage]],Positions!$M$2:$M$644,$C$4)/$C$11),0) -> 0.026675879 | N32: Triple Net Lease | O32: =Table21[[#This Row],[Portfolio % CF]]*$C$10/1000000 -> 40.100505 | P32: =Table21[[#This Row],[Portfolio % MV]]*$C$11/1000000 -> 37.168121 | Q32: =IFERROR(IF($C$4="All Portfolios", SUMIFS(Positions!$C$2:$C$644,tbl_rawhold[Collateral Type],Table21[[#This Row],[Collateral Type]])/$C$10, SUMIFS(Positions!$C$2:$C$644,tbl_rawhold[Collateral Type],Table21[[#This Row],[Collateral Type]],Positions!$M$2:$M$644,$C$4)/$C$10),0) -> 0.02237694 | R32: =IFERROR(IF($C$4="All Portfolios", SUMIFS(Positions!$D$2:$D$644,tbl_rawhold[Collateral Type],Table21[[#This Row],[Collateral Type]])/$C$11, SUMIFS(Positions!$D$2:$D$644,tbl_rawhold[Collateral Type],Table21[[#This Row],[Collateral Type]],Positions!$M$2:$M$644,$C$4)/$C$11),0) -> 0.021028219
B33: Total | C33: =SUBTOTAL(109,Table15[Current Face (M)]) -> 3133.7348 | D33: =SUBTOTAL(109,Table15[Market Value (M)]) -> 3105.9601 | E33: =SUBTOTAL(109,Table15[Portfolio % CF]) -> 1.7486911 | F33: =SUBTOTAL(109,Table15[Portfolio % MV]) -> 1.7572265 | H33: 2023 | I33: =Table20[[#This Row],[Portfolio % CF]]*$C$10/1000000 -> 68.270809 | J33: =Table20[[#This Row],[Portfolio % MV]]*$C$11/1000000 -> 68.656143 | K33: =IFERROR(IF($C$4="All Portfolios", SUMIFS(Positions!$C$2:$C$644,tbl_rawhold[Vintage],Table20[[#This Row],[Vintage]])/$C$10, SUMIFS(Positions!$C$2:$C$644,tbl_rawhold[Vintage],Table20[[#This Row],[Vintage]],Positions!$M$2:$M$644,$C$4)/$C$10),0) -> 0.038096573 | L33: =IFERROR(IF($C$4="All Portfolios", SUMIFS(Positions!$D$2:$D$644,tbl_rawhold[Vintage],Table20[[#This Row],[Vintage]])/$C$11, SUMIFS(Positions!$D$2:$D$644,tbl_rawhold[Vintage],Table20[[#This Row],[Vintage]],Positions!$M$2:$M$644,$C$4)/$C$11),0) -> 0.038842867 | N33: Total | O33: =SUBTOTAL(109,Table21[Current Face (M)]) -> 62.417654 | P33: =SUBTOTAL(109,Table21[Market Value (M)]) -> 58.897169 | Q33: =SUBTOTAL(109,Table21[Portfolio % CF]) -> 0.034830387 | R33: =SUBTOTAL(109,Table21[Portfolio % MV]) -> 0.033321634
H34: 2024 | I34: =Table20[[#This Row],[Portfolio % CF]]*$C$10/1000000 -> 830.65161 | J34: =Table20[[#This Row],[Portfolio % MV]]*$C$11/1000000 -> 834.23876 | K34: =IFERROR(IF($C$4="All Portfolios", SUMIFS(Positions!$C$2:$C$644,tbl_rawhold[Vintage],Table20[[#This Row],[Vintage]])/$C$10, SUMIFS(Positions!$C$2:$C$644,tbl_rawhold[Vintage],Table20[[#This Row],[Vintage]],Positions!$M$2:$M$644,$C$4)/$C$10),0) -> 0.46352138 | L34: =IFERROR(IF($C$4="All Portfolios", SUMIFS(Positions!$D$2:$D$644,tbl_rawhold[Vintage],Table20[[#This Row],[Vintage]])/$C$11, SUMIFS(Positions!$D$2:$D$644,tbl_rawhold[Vintage],Table20[[#This Row],[Vintage]],Positions!$M$2:$M$644,$C$4)/$C$11),0) -> 0.47197852
H35: 2025 | I35: =Table20[[#This Row],[Portfolio % CF]]*$C$10/1000000 -> 935.73545 | J35: =Table20[[#This Row],[Portfolio % MV]]*$C$11/1000000 -> 938.96049 | K35: =IFERROR(IF($C$4="All Portfolios", SUMIFS(Positions!$C$2:$C$644,tbl_rawhold[Vintage],Table20[[#This Row],[Vintage]])/$C$10, SUMIFS(Positions!$C$2:$C$644,tbl_rawhold[Vintage],Table20[[#This Row],[Vintage]],Positions!$M$2:$M$644,$C$4)/$C$10),0) -> 0.52216041 | L35: =IFERROR(IF($C$4="All Portfolios", SUMIFS(Positions!$D$2:$D$644,tbl_rawhold[Vintage],Table20[[#This Row],[Vintage]])/$C$11, SUMIFS(Positions!$D$2:$D$644,tbl_rawhold[Vintage],Table20[[#This Row],[Vintage]],Positions!$M$2:$M$644,$C$4)/$C$11),0) -> 0.53122584
H36: 2026 | I36: =Table20[[#This Row],[Portfolio % CF]]*$C$10/1000000 -> 0 | J36: =Table20[[#This Row],[Portfolio % MV]]*$C$11/1000000 -> 0 | K36: =IFERROR(IF($C$4="All Portfolios", SUMIFS(Positions!$C$2:$C$644,tbl_rawhold[Vintage],Table20[[#This Row],[Vintage]])/$C$10, SUMIFS(Positions!$C$2:$C$644,tbl_rawhold[Vintage],Table20[[#This Row],[Vintage]],Positions!$M$2:$M$644,$C$4)/$C$10),0) -> 0 | L36: =IFERROR(IF($C$4="All Portfolios", SUMIFS(Positions!$D$2:$D$644,tbl_rawhold[Vintage],Table20[[#This Row],[Vintage]])/$C$11, SUMIFS(Positions!$D$2:$D$644,tbl_rawhold[Vintage],Table20[[#This Row],[Vintage]],Positions!$M$2:$M$644,$C$4)/$C$11),0) -> 0
H37: Unknown | I37: =Table20[[#This Row],[Portfolio % CF]]*$C$10/1000000 -> 0 | J37: =Table20[[#This Row],[Portfolio % MV]]*$C$11/1000000 -> 0 | K37: =IFERROR(IF($C$4="All Portfolios", SUMIFS(Positions!$C$2:$C$644,tbl_rawhold[Vintage],Table20[[#This Row],[Vintage]])/$C$10, SUMIFS(Positions!$C$2:$C$644,tbl_rawhold[Vintage],Table20[[#This Row],[Vintage]],Positions!$M$2:$M$644,$C$4)/$C$10),0) -> 0 | L37: =IFERROR(IF($C$4="All Portfolios", SUMIFS(Positions!$D$2:$D$644,tbl_rawhold[Vintage],Table20[[#This Row],[Vintage]])/$C$11, SUMIFS(Positions!$D$2:$D$644,tbl_rawhold[Vintage],Table20[[#This Row],[Vintage]],Positions!$M$2:$M$644,$C$4)/$C$11),0) -> 0
H38: Total | I38: =SUBTOTAL(109,Table20[Current Face (M)]) -> 3070.3172 | J38: =SUBTOTAL(109,Table20[Market Value (M)]) -> 3046.1577 | K38: =SUBTOTAL(109,Table20[Portfolio % CF]) -> 1.7133027 | L38: =SUBTOTAL(109,Table20[Portfolio % MV]) -> 1.7233927
B40: Holdings Summary
B41: Tranche Rating | C41: WA Coupon | D41: WA WAL | E41: Current Face | F41: Market Value | G41: Market Price
B42: CLO/ABS Debt - AAA | C42: =IFERROR(SUMPRODUCT(tbl_hold_aaa[Coupon],tbl_hold_aaa[Current Face])/SUM(tbl_hold_aaa[Current Face]),0) -> 0 | D42: =IFERROR(SUMPRODUCT(tbl_hold_aaa[WAL],tbl_hold_aaa[Current Face])/SUM(tbl_hold_aaa[Current Face]),0) -> 0 | E42: =SUM(tbl_hold_aaa[Current Face]) -> 0 | F42: =SUM(tbl_hold_aaa[Market Value]) -> 0 | G42: =IFERROR(Report!$F42/Report!$E42,0) -> 0
B43: CLO/ABS Debt - AA | C43: =IFERROR(SUMPRODUCT(tbl_hold_aa[Coupon],tbl_hold_aa[Current Face])/SUM(tbl_hold_aa[Current Face]),0) -> 0 | D43: =IFERROR(SUMPRODUCT(tbl_hold_aa[WAL],tbl_hold_aa[Current Face])/SUM(tbl_hold_aa[Current Face]),0) -> 0 | E43: =SUM(tbl_hold_aa[Current Face]) -> 0 | F43: =SUM(tbl_hold_aa[Market Value]) -> 0 | G43: =IFERROR(Report!$F43/Report!$E43,0) -> 0
B44: CLO/ABS Debt - A | C44: =IFERROR(SUMPRODUCT(tbl_hold_a[Coupon],tbl_hold_a[Current Face])/SUM(tbl_hold_a[Current Face]),0) -> 0 | D44: =IFERROR(SUMPRODUCT(tbl_hold_a[WAL],tbl_hold_a[Current Face])/SUM(tbl_hold_a[Current Face]),0) -> 0 | E44: =SUM(tbl_hold_a[Current Face]) -> 0 | F44: =SUM(tbl_hold_a[Market Value]) -> 0 | G44: =IFERROR(Report!$F44/Report!$E44,0) -> 0
B45: CLO/ABS Debt - BBB | C45: =IFERROR(SUMPRODUCT(tbl_hold_bbb[Coupon],tbl_hold_bbb[Current Face])/SUM(tbl_hold_bbb[Current Face]),0) -> 0 | D45: =IFERROR(SUMPRODUCT(tbl_hold_bbb[WAL],tbl_hold_bbb[Current Face])/SUM(tbl_hold_bbb[Current Face]),0) -> 0 | E45: =SUM(tbl_hold_bbb[Current Face]) -> 0 | F45: =SUM(tbl_hold_bbb[Market Value]) -> 0 | G45: =IFERROR(Report!$F45/Report!$E45,0) -> 0
B46: CLO/ABS Debt - BB | C46: =IFERROR(SUMPRODUCT(tbl_hold_bb[Coupon],tbl_hold_bb[Current Face])/SUM(tbl_hold_bb[Current Face]),0) -> 0 | D46: =IFERROR(SUMPRODUCT(tbl_hold_bb[WAL],tbl_hold_bb[Current Face])/SUM(tbl_hold_bb[Current Face]),0) -> 0 | E46: =SUM(tbl_hold_bb[Current Face]) -> 0 | F46: =SUM(tbl_hold_bb[Market Value]) -> 0 | G46: =IFERROR(Report!$F46/Report!$E46,0) -> 0
B47: CLO/ABS Debt - B | C47: =IFERROR(SUMPRODUCT(tbl_hold_b[Coupon],tbl_hold_b[Current Face])/SUM(tbl_hold_b[Current Face]),0) -> 0 | D47: =IFERROR(SUMPRODUCT(tbl_hold_b[WAL],tbl_hold_b[Current Face])/SUM(tbl_hold_b[Current Face]),0) -> 0 | E47: =SUM(tbl_hold_b[Current Face]) -> 0 | F47: =SUM(tbl_hold_b[Market Value]) -> 0 | G47: =IFERROR(Report!$F47/Report!$E47,0) -> 0
B48: CLO/ABS Debt - CCC | C48: =IFERROR(SUMPRODUCT(tbl_hold_ccc[Coupon],tbl_hold_ccc[Current Face])/SUM(tbl_hold_ccc[Current Face]),0) -> 0 | D48: =IFERROR(SUMPRODUCT(tbl_hold_ccc[WAL],tbl_hold_ccc[Current Face])/SUM(tbl_hold_ccc[Current Face]),0) -> 0 | E48: =SUM(tbl_hold_ccc[Current Face]) -> 0 | F48: =SUM(tbl_hold_ccc[Market Value]) -> 0 | G48: =IFERROR(Report!$F48/Report!$E48,0) -> 0
B49: CLO/ABS Debt - NR | C49: =IFERROR(SUMPRODUCT(tbl_hold_nr[Coupon],tbl_hold_nr[Current Face])/SUM(tbl_hold_nr[Current Face]),0) -> 0 | D49: =IFERROR(SUMPRODUCT(tbl_hold_nr[WAL],tbl_hold_nr[Current Face])/SUM(tbl_hold_nr[Current Face]),0) -> 0 | E49: =SUM(tbl_hold_nr[Current Face]) -> 0 | F49: =SUM(tbl_hold_nr[Market Value]) -> 0 | G49: =IFERROR(Report!$F49/Report!$E49,0) -> 0
B50: Total | C50: =IFERROR(SUMPRODUCT(Report!$C$42:$C$49,Report!$E$42:$E$49)/Report!$E$50,0) -> 0 | D50: =IFERROR(SUMPRODUCT(Report!$D$42:$D$49,Report!$E$42:$E$49)/Report!$E$50,0) -> 0 | E50: =SUBTOTAL(109,Report!$E$42:$E$49) -> 0 | F50: =SUBTOTAL(109,Report!$F$42:$F$49) -> 0 | G50: =IFERROR(Report!$F$50/Report!$E$50,0) -> 0
B53: Top Exposure by Manager
B54: Summary of Manager Total | C54: =SUM(tbl_report_manager[Current Face]) -> 1.792046e+09 | D54: =SUM(tbl_report_manager[Market Value]) -> 1.7675354e+09 | E54: =SUM(tbl_report_manager[Current Face %]) -> 1 | F54: =SUM(tbl_report_manager[Market Value %]) -> 1 | G54: =SUM(tbl_report_manager[No. of Issuers]) -> 37 | H54: =SUM(tbl_report_manager[No. of Cusips]) -> 226 | I54: =SUM(tbl_report_manager[No. of Positions]) -> 288
B55: Manager Name | C55: Current Face | D55: Market Value | E55: Current Face % | F55: Market Value % | G55: No. of Issuers | H55: No. of Cusips | I55: No. of Positions
B56: Carlyle CLO Management | C56: =IF($C$4="All Portfolios", SUMIFS(tbl_rawhold[Current Face],tbl_rawhold[Manager], tbl_report_manager[[#This Row],[Manager Name]]), SUMIFS(tbl_rawhold[Current Face], tbl_rawhold[Portfolio_Name], $C$4,tbl_rawhold[Manager], tbl_report_manager[[#This Row],[Manager Name]])) -> 5.5737268e+08 | D56: =IF($C$4="All Portfolios", SUMIFS(tbl_rawhold[BASEMarket Value],tbl_rawhold[Manager], tbl_report_manager[[#This Row],[Manager Name]]), SUMIFS(tbl_rawhold[BASEMarket Value], tbl_rawhold[Portfolio_Name], $C$4,tbl_rawhold[Manager], tbl_report_manager[[#This Row],[Manager Name]])) -> 5.319988e+08 | E56: =IFERROR(tbl_report_manager[[#This Row],[Current Face]]/$C$54,0) -> 0.31102588 | F56: =IFERROR(tbl_report_manager[[#This Row],[Market Value]]/$D$54,0) -> 0.30098339 | G56: {=IF($C$4="All Portfolios", IFERROR(ROWS(_xlfn.UNIQUE(_xlfn._xlws.FILTER(Positions!$F$2:$F$644, Positions!$O$2:$O$644=tbl_report_manager[[#This Row],[Manager Name]]))),0), IFERROR(ROWS(_xlfn.UNIQUE(_xlfn._xlws.FILTER(Positions!$F$2:$F$644, (Positions!$O$2:$O$644=tbl_report_manager[[#This Row],[Manager Name]])*(Positions!$M$2:$M$644=$C$4)))),0) )} -> 4 | H56: {=IF($C$4="All Portfolios", IFERROR(ROWS(_xlfn.UNIQUE(_xlfn._xlws.FILTER(Positions!$B$2:$B$644, Positions!$O$2:$O$644=tbl_report_manager[[#This Row],[Manager Name]]))),0), IFERROR(ROWS(_xlfn.UNIQUE(_xlfn._xlws.FILTER(Positions!$B$2:$B$644, (Positions!$O$2:$O$644=tbl_report_manager[[#This Row],[Manager Name]])*(Positions!$M$2:$M$644=$C$4)))),0) )} -> 43 | I56: =IF($C$4="All Portfolios", COUNTIFS(Positions!$O$2:$O$644, tbl_report_manager[[#This Row],[Manager Name]]), COUNTIFS(Positions!$M$2:$M$644, $C$4,Positions!$O$2:$O$644, tbl_report_manager[[#This Row],[Manager Name]]) ) -> 58
B57: Ares CLO Management | C57: =IF($C$4="All Portfolios", SUMIFS(tbl_rawhold[Current Face],tbl_rawhold[Manager], tbl_report_manager[[#This Row],[Manager Name]]), SUMIFS(tbl_rawhold[Current Face], tbl_rawhold[Portfolio_Name], $C$4,tbl_rawhold[Manager], tbl_report_manager[[#This Row],[Manager Name]])) -> 172943485 | D57: =IF($C$4="All Portfolios", SUMIFS(tbl_rawhold[BASEMarket Value],tbl_rawhold[Manager], tbl_report_manager[[#This Row],[Manager Name]]), SUMIFS(tbl_rawhold[BASEMarket Value], tbl_rawhold[Portfolio_Name], $C$4,tbl_rawhold[Manager], tbl_report_manager[[#This Row],[Manager Name]])) -> 1.7375827e+08 | E57: =IFERROR(tbl_report_manager[[#This Row],[Current Face]]/$C$54,0) -> 0.096506166 | F57: =IFERROR(tbl_report_manager[[#This Row],[Market Value]]/$D$54,0) -> 0.098305396 | G57: {=IF($C$4="All Portfolios", IFERROR(ROWS(_xlfn.UNIQUE(_xlfn._xlws.FILTER(Positions!$F$2:$F$644, Positions!$O$2:$O$644=tbl_report_manager[[#This Row],[Manager Name]]))),0), IFERROR(ROWS(_xlfn.UNIQUE(_xlfn._xlws.FILTER(Positions!$F$2:$F$644, (Positions!$O$2:$O$644=tbl_report_manager[[#This Row],[Manager Name]])*(Positions!$M$2:$M$644=$C$4)))),0) )} -> 1 | H57: {=IF($C$4="All Portfolios", IFERROR(ROWS(_xlfn.UNIQUE(_xlfn._xlws.FILTER(Positions!$B$2:$B$644, Positions!$O$2:$O$644=tbl_report_manager[[#This Row],[Manager Name]]))),0), IFERROR(ROWS(_xlfn.UNIQUE(_xlfn._xlws.FILTER(Positions!$B$2:$B$644, (Positions!$O$2:$O$644=tbl_report_manager[[#This Row],[Manager Name]])*(Positions!$M$2:$M$644=$C$4)))),0) )} -> 19 | I57: =IF($C$4="All Portfolios", COUNTIFS(Positions!$O$2:$O$644, tbl_report_manager[[#This Row],[Manager Name]]), COUNTIFS(Positions!$M$2:$M$644, $C$4,Positions!$O$2:$O$644, tbl_report_manager[[#This Row],[Manager Name]]) ) -> 27
B58: KKR Financial Advisors II | C58: =IF($C$4="All Portfolios", SUMIFS(tbl_rawhold[Current Face],tbl_rawhold[Manager], tbl_report_manager[[#This Row],[Manager Name]]), SUMIFS(tbl_rawhold[Current Face], tbl_rawhold[Portfolio_Name], $C$4,tbl_rawhold[Manager], tbl_report_manager[[#This Row],[Manager Name]])) -> 129707963 | D58: =IF($C$4="All Portfolios", SUMIFS(tbl_rawhold[BASEMarket Value],tbl_rawhold[Manager], tbl_report_manager[[#This Row],[Manager Name]]), SUMIFS(tbl_rawhold[BASEMarket Value], tbl_rawhold[Portfolio_Name], $C$4,tbl_rawhold[Manager], tbl_report_manager[[#This Row],[Manager Name]])) -> 1.2948672e+08 | E58: =IFERROR(tbl_report_manager[[#This Row],[Current Face]]/$C$54,0) -> 0.072379819 | F58: =IFERROR(tbl_report_manager[[#This Row],[Market Value]]/$D$54,0) -> 0.073258344 | G58: {=IF($C$4="All Portfolios", IFERROR(ROWS(_xlfn.UNIQUE(_xlfn._xlws.FILTER(Positions!$F$2:$F$644, Positions!$O$2:$O$644=tbl_report_manager[[#This Row],[Manager Name]]))),0), IFERROR(ROWS(_xlfn.UNIQUE(_xlfn._xlws.FILTER(Positions!$F$2:$F$644, (Positions!$O$2:$O$644=tbl_report_manager[[#This Row],[Manager Name]])*(Positions!$M$2:$M$644=$C$4)))),0) )} -> 2 | H58: {=IF($C$4="All Portfolios", IFERROR(ROWS(_xlfn.UNIQUE(_xlfn._xlws.FILTER(Positions!$B$2:$B$644, Positions!$O$2:$O$644=tbl_report_manager[[#This Row],[Manager Name]]))),0), IFERROR(ROWS(_xlfn.UNIQUE(_xlfn._xlws.FILTER(Positions!$B$2:$B$644, (Positions!$O$2:$O$644=tbl_report_manager[[#This Row],[Manager Name]])*(Positions!$M$2:$M$644=$C$4)))),0) )} -> 20 | I58: =IF($C$4="All Portfolios", COUNTIFS(Positions!$O$2:$O$644, tbl_report_manager[[#This Row],[Manager Name]]), COUNTIFS(Positions!$M$2:$M$644, $C$4,Positions!$O$2:$O$644, tbl_report_manager[[#This Row],[Manager Name]]) ) -> 27
B59: UBS Asset Management (Americas) | C59: =IF($C$4="All Portfolios", SUMIFS(tbl_rawhold[Current Face],tbl_rawhold[Manager], tbl_report_manager[[#This Row],[Manager Name]]), SUMIFS(tbl_rawhold[Current Face], tbl_rawhold[Portfolio_Name], $C$4,tbl_rawhold[Manager], tbl_report_manager[[#This Row],[Manager Name]])) -> 103700000 | D59: =IF($C$4="All Portfolios", SUMIFS(tbl_rawhold[BASEMarket Value],tbl_rawhold[Manager], tbl_report_manager[[#This Row],[Manager Name]]), SUMIFS(tbl_rawhold[BASEMarket Value], tbl_rawhold[Portfolio_Name], $C$4,tbl_rawhold[Manager], tbl_report_manager[[#This Row],[Manager Name]])) -> 1.0413743e+08 | E59: =IFERROR(tbl_report_manager[[#This Row],[Current Face]]/$C$54,0) -> 0.057866819 | F59: =IFERROR(tbl_report_manager[[#This Row],[Market Value]]/$D$54,0) -> 0.058916741 | G59: {=IF($C$4="All Portfolios", IFERROR(ROWS(_xlfn.UNIQUE(_xlfn._xlws.FILTER(Positions!$F$2:$F$644, Positions!$O$2:$O$644=tbl_report_manager[[#This Row],[Manager Name]]))),0), IFERROR(ROWS(_xlfn.UNIQUE(_xlfn._xlws.FILTER(Positions!$F$2:$F$644, (Positions!$O$2:$O$644=tbl_report_manager[[#This Row],[Manager Name]])*(Positions!$M$2:$M$644=$C$4)))),0) )} -> 1 | H59: {=IF($C$4="All Portfolios", IFERROR(ROWS(_xlfn.UNIQUE(_xlfn._xlws.FILTER(Positions!$B$2:$B$644, Positions!$O$2:$O$644=tbl_report_manager[[#This Row],[Manager Name]]))),0), IFERROR(ROWS(_xlfn.UNIQUE(_xlfn._xlws.FILTER(Positions!$B$2:$B$644, (Positions!$O$2:$O$644=tbl_report_manager[[#This Row],[Manager Name]])*(Positions!$M$2:$M$644=$C$4)))),0) )} -> 15 | I59: =IF($C$4="All Portfolios", COUNTIFS(Positions!$O$2:$O$644, tbl_report_manager[[#This Row],[Manager Name]]), COUNTIFS(Positions!$M$2:$M$644, $C$4,Positions!$O$2:$O$644, tbl_report_manager[[#This Row],[Manager Name]]) ) -> 16
B60: BlackRock Capital Investment Advisors | C60: =IF($C$4="All Portfolios", SUMIFS(tbl_rawhold[Current Face],tbl_rawhold[Manager], tbl_report_manager[[#This Row],[Manager Name]]), SUMIFS(tbl_rawhold[Current Face], tbl_rawhold[Portfolio_Name], $C$4,tbl_rawhold[Manager], tbl_report_manager[[#This Row],[Manager Name]])) -> 1.0246169e+08 | D60: =IF($C$4="All Portfolios", SUMIFS(tbl_rawhold[BASEMarket Value],tbl_rawhold[Manager], tbl_report_manager[[#This Row],[Manager Name]]), SUMIFS(tbl_rawhold[BASEMarket Value], tbl_rawhold[Portfolio_Name], $C$4,tbl_rawhold[Manager], tbl_report_manager[[#This Row],[Manager Name]])) -> 1.0092127e+08 | E60: =IFERROR(tbl_report_manager[[#This Row],[Current Face]]/$C$54,0) -> 0.057175816 | F60: =IFERROR(tbl_report_manager[[#This Row],[Market Value]]/$D$54,0) -> 0.057097172 | G60: {=IF($C$4="All Portfolios", IFERROR(ROWS(_xlfn.UNIQUE(_xlfn._xlws.FILTER(Positions!$F$2:$F$644, Positions!$O$2:$O$644=tbl_report_manager[[#This Row],[Manager Name]]))),0), IFERROR(ROWS(_xlfn.UNIQUE(_xlfn._xlws.FILTER(Positions!$F$2:$F$644, (Positions!$O$2:$O$644=tbl_report_manager[[#This Row],[Manager Name]])*(Positions!$M$2:$M$644=$C$4)))),0) )} -> 4 | H60: {=IF($C$4="All Portfolios", IFERROR(ROWS(_xlfn.UNIQUE(_xlfn._xlws.FILTER(Positions!$B$2:$B$644, Positions!$O$2:$O$644=tbl_report_manager[[#This Row],[Manager Name]]))),0), IFERROR(ROWS(_xlfn.UNIQUE(_xlfn._xlws.FILTER(Positions!$B$2:$B$644, (Positions!$O$2:$O$644=tbl_report_manager[[#This Row],[Manager Name]])*(Positions!$M$2:$M$644=$C$4)))),0) )} -> 9 | I60: =IF($C$4="All Portfolios", COUNTIFS(Positions!$O$2:$O$644, tbl_report_manager[[#This Row],[Manager Name]]), COUNTIFS(Positions!$M$2:$M$644, $C$4,Positions!$O$2:$O$644, tbl_report_manager[[#This Row],[Manager Name]]) ) -> 13
B61: First Eagle Alternative Credit | C61: =IF($C$4="All Portfolios", SUMIFS(tbl_rawhold[Current Face],tbl_rawhold[Manager], tbl_report_manager[[#This Row],[Manager Name]]), SUMIFS(tbl_rawhold[Current Face], tbl_rawhold[Portfolio_Name], $C$4,tbl_rawhold[Manager], tbl_report_manager[[#This Row],[Manager Name]])) -> 93016501 | D61: =IF($C$4="All Portfolios", SUMIFS(tbl_rawhold[BASEMarket Value],tbl_rawhold[Manager], tbl_report_manager[[#This Row],[Manager Name]]), SUMIFS(tbl_rawhold[BASEMarket Value], tbl_rawhold[Portfolio_Name], $C$4,tbl_rawhold[Manager], tbl_report_manager[[#This Row],[Manager Name]])) -> 92565341 | E61: =IFERROR(tbl_report_manager[[#This Row],[Current Face]]/$C$54,0) -> 0.051905198 | F61: =IFERROR(tbl_report_manager[[#This Row],[Market Value]]/$D$54,0) -> 0.052369723 | G61: {=IF($C$4="All Portfolios", IFERROR(ROWS(_xlfn.UNIQUE(_xlfn._xlws.FILTER(Positions!$F$2:$F$644, Positions!$O$2:$O$644=tbl_report_manager[[#This Row],[Manager Name]]))),0), IFERROR(ROWS(_xlfn.UNIQUE(_xlfn._xlws.FILTER(Positions!$F$2:$F$644, (Positions!$O$2:$O$644=tbl_report_manager[[#This Row],[Manager Name]])*(Positions!$M$2:$M$644=$C$4)))),0) )} -> 2 | H61: {=IF($C$4="All Portfolios", IFERROR(ROWS(_xlfn.UNIQUE(_xlfn._xlws.FILTER(Positions!$B$2:$B$644, Positions!$O$2:$O$644=tbl_report_manager[[#This Row],[Manager Name]]))),0), IFERROR(ROWS(_xlfn.UNIQUE(_xlfn._xlws.FILTER(Positions!$B$2:$B$644, (Positions!$O$2:$O$644=tbl_report_manager[[#This Row],[Manager Name]])*(Positions!$M$2:$M$644=$C$4)))),0) )} -> 14 | I61: =IF($C$4="All Portfolios", COUNTIFS(Positions!$O$2:$O$644, tbl_report_manager[[#This Row],[Manager Name]]), COUNTIFS(Positions!$M$2:$M$644, $C$4,Positions!$O$2:$O$644, tbl_report_manager[[#This Row],[Manager Name]]) ) -> 25
B62: CIFC Asset Management | C62: =IF($C$4="All Portfolios", SUMIFS(tbl_rawhold[Current Face],tbl_rawhold[Manager], tbl_report_manager[[#This Row],[Manager Name]]), SUMIFS(tbl_rawhold[Current Face], tbl_rawhold[Portfolio_Name], $C$4,tbl_rawhold[Manager], tbl_report_manager[[#This Row],[Manager Name]])) -> 77462000 | D62: =IF($C$4="All Portfolios", SUMIFS(tbl_rawhold[BASEMarket Value],tbl_rawhold[Manager], tbl_report_manager[[#This Row],[Manager Name]]), SUMIFS(tbl_rawhold[BASEMarket Value], tbl_rawhold[Portfolio_Name], $C$4,tbl_rawhold[Manager], tbl_report_manager[[#This Row],[Manager Name]])) -> 77803794 | E62: =IFERROR(tbl_report_manager[[#This Row],[Current Face]]/$C$54,0) -> 0.043225454 | F62: =IFERROR(tbl_report_manager[[#This Row],[Market Value]]/$D$54,0) -> 0.044018237 | G62: {=IF($C$4="All Portfolios", IFERROR(ROWS(_xlfn.UNIQUE(_xlfn._xlws.FILTER(Positions!$F$2:$F$644, Positions!$O$2:$O$644=tbl_report_manager[[#This Row],[Manager Name]]))),0), IFERROR(ROWS(_xlfn.UNIQUE(_xlfn._xlws.FILTER(Positions!$F$2:$F$644, (Positions!$O$2:$O$644=tbl_report_manager[[#This Row],[Manager Name]])*(Positions!$M$2:$M$644=$C$4)))),0) )} -> 3 | H62: {=IF($C$4="All Portfolios", IFERROR(ROWS(_xlfn.UNIQUE(_xlfn._xlws.FILTER(Positions!$B$2:$B$644, Positions!$O$2:$O$644=tbl_report_manager[[#This Row],[Manager Name]]))),0), IFERROR(ROWS(_xlfn.UNIQUE(_xlfn._xlws.FILTER(Positions!$B$2:$B$644, (Positions!$O$2:$O$644=tbl_report_manager[[#This Row],[Manager Name]])*(Positions!$M$2:$M$644=$C$4)))),0) )} -> 17 | I62: =IF($C$4="All Portfolios", COUNTIFS(Positions!$O$2:$O$644, tbl_report_manager[[#This Row],[Manager Name]]), COUNTIFS(Positions!$M$2:$M$644, $C$4,Positions!$O$2:$O$644, tbl_report_manager[[#This Row],[Manager Name]]) ) -> 21
B63: Maranon Management | C63: =IF($C$4="All Portfolios", SUMIFS(tbl_rawhold[Current Face],tbl_rawhold[Manager], tbl_report_manager[[#This Row],[Manager Name]]), SUMIFS(tbl_rawhold[Current Face], tbl_rawhold[Portfolio_Name], $C$4,tbl_rawhold[Manager], tbl_report_manager[[#This Row],[Manager Name]])) -> 74904405 | D63: =IF($C$4="All Portfolios", SUMIFS(tbl_rawhold[BASEMarket Value],tbl_rawhold[Manager], tbl_report_manager[[#This Row],[Manager Name]]), SUMIFS(tbl_rawhold[BASEMarket Value], tbl_rawhold[Portfolio_Name], $C$4,tbl_rawhold[Manager], tbl_report_manager[[#This Row],[Manager Name]])) -> 74467667 | E63: =IFERROR(tbl_report_manager[[#This Row],[Current Face]]/$C$54,0) -> 0.041798261 | F63: =IFERROR(tbl_report_manager[[#This Row],[Market Value]]/$D$54,0) -> 0.042130792 | G63: {=IF($C$4="All Portfolios", IFERROR(ROWS(_xlfn.UNIQUE(_xlfn._xlws.FILTER(Positions!$F$2:$F$644, Positions!$O$2:$O$644=tbl_report_manager[[#This Row],[Manager Name]]))),0), IFERROR(ROWS(_xlfn.UNIQUE(_xlfn._xlws.FILTER(Positions!$F$2:$F$644, (Positions!$O$2:$O$644=tbl_report_manager[[#This Row],[Manager Name]])*(Positions!$M$2:$M$644=$C$4)))),0) )} -> 1 | H63: {=IF($C$4="All Portfolios", IFERROR(ROWS(_xlfn.UNIQUE(_xlfn._xlws.FILTER(Positions!$B$2:$B$644, Positions!$O$2:$O$644=tbl_report_manager[[#This Row],[Manager Name]]))),0), IFERROR(ROWS(_xlfn.UNIQUE(_xlfn._xlws.FILTER(Positions!$B$2:$B$644, (Positions!$O$2:$O$644=tbl_report_manager[[#This Row],[Manager Name]])*(Positions!$M$2:$M$644=$C$4)))),0) )} -> 5 | I63: =IF($C$4="All Portfolios", COUNTIFS(Positions!$O$2:$O$644, tbl_report_manager[[#This Row],[Manager Name]]), COUNTIFS(Positions!$M$2:$M$644, $C$4,Positions!$O$2:$O$644, tbl_report_manager[[#This Row],[Manager Name]]) ) -> 5
B64: Octagon Credit Investors | C64: =IF($C$4="All Portfolios", SUMIFS(tbl_rawhold[Current Face],tbl_rawhold[Manager], tbl_report_manager[[#This Row],[Manager Name]]), SUMIFS(tbl_rawhold[Current Face], tbl_rawhold[Portfolio_Name], $C$4,tbl_rawhold[Manager], tbl_report_manager[[#This Row],[Manager Name]])) -> 70255823 | D64: =IF($C$4="All Portfolios", SUMIFS(tbl_rawhold[BASEMarket Value],tbl_rawhold[Manager], tbl_report_manager[[#This Row],[Manager Name]]), SUMIFS(tbl_rawhold[BASEMarket Value], tbl_rawhold[Portfolio_Name], $C$4,tbl_rawhold[Manager], tbl_report_manager[[#This Row],[Manager Name]])) -> 70471704 | E64: =IFERROR(tbl_report_manager[[#This Row],[Current Face]]/$C$54,0) -> 0.039204253 | F64: =IFERROR(tbl_report_manager[[#This Row],[Market Value]]/$D$54,0) -> 0.039870038 | G64: {=IF($C$4="All Portfolios", IFERROR(ROWS(_xlfn.UNIQUE(_xlfn._xlws.FILTER(Positions!$F$2:$F$644, Positions!$O$2:$O$644=tbl_report_manager[[#This Row],[Manager Name]]))),0), IFERROR(ROWS(_xlfn.UNIQUE(_xlfn._xlws.FILTER(Positions!$F$2:$F$644, (Positions!$O$2:$O$644=tbl_report_manager[[#This Row],[Manager Name]])*(Positions!$M$2:$M$644=$C$4)))),0) )} -> 2 | H64: {=IF($C$4="All Portfolios", IFERROR(ROWS(_xlfn.UNIQUE(_xlfn._xlws.FILTER(Positions!$B$2:$B$644, Positions!$O$2:$O$644=tbl_report_manager[[#This Row],[Manager Name]]))),0), IFERROR(ROWS(_xlfn.UNIQUE(_xlfn._xlws.FILTER(Positions!$B$2:$B$644, (Positions!$O$2:$O$644=tbl_report_manager[[#This Row],[Manager Name]])*(Positions!$M$2:$M$644=$C$4)))),0) )} -> 13 | I64: =IF($C$4="All Portfolios", COUNTIFS(Positions!$O$2:$O$644, tbl_report_manager[[#This Row],[Manager Name]]), COUNTIFS(Positions!$M$2:$M$644, $C$4,Positions!$O$2:$O$644, tbl_report_manager[[#This Row],[Manager Name]]) ) -> 17
B65: Oak Hill Advisors | C65: =IF($C$4="All Portfolios", SUMIFS(tbl_rawhold[Current Face],tbl_rawhold[Manager], tbl_report_manager[[#This Row],[Manager Name]]), SUMIFS(tbl_rawhold[Current Face], tbl_rawhold[Portfolio_Name], $C$4,tbl_rawhold[Manager], tbl_report_manager[[#This Row],[Manager Name]])) -> 68165000 | D65: =IF($C$4="All Portfolios", SUMIFS(tbl_rawhold[BASEMarket Value],tbl_rawhold[Manager], tbl_report_manager[[#This Row],[Manager Name]]), SUMIFS(tbl_rawhold[BASEMarket Value], tbl_rawhold[Portfolio_Name], $C$4,tbl_rawhold[Manager], tbl_report_manager[[#This Row],[Manager Name]])) -> 68505232 | E65: =IFERROR(tbl_report_manager[[#This Row],[Current Face]]/$C$54,0) -> 0.038037529 | F65: =IFERROR(tbl_report_manager[[#This Row],[Market Value]]/$D$54,0) -> 0.038757488 | G65: {=IF($C$4="All Portfolios", IFERROR(ROWS(_xlfn.UNIQUE(_xlfn._xlws.FILTER(Positions!$F$2:$F$644, Positions!$O$2:$O$644=tbl_report_manager[[#This Row],[Manager Name]]))),0), IFERROR(ROWS(_xlfn.UNIQUE(_xlfn._xlws.FILTER(Positions!$F$2:$F$644, (Positions!$O$2:$O$644=tbl_report_manager[[#This Row],[Manager Name]])*(Positions!$M$2:$M$644=$C$4)))),0) )} -> 4 | H65: {=IF($C$4="All Portfolios", IFERROR(ROWS(_xlfn.UNIQUE(_xlfn._xlws.FILTER(Positions!$B$2:$B$644, Positions!$O$2:$O$644=tbl_report_manager[[#This Row],[Manager Name]]))),0), IFERROR(ROWS(_xlfn.UNIQUE(_xlfn._xlws.FILTER(Positions!$B$2:$B$644, (Positions!$O$2:$O$644=tbl_report_manager[[#This Row],[Manager Name]])*(Positions!$M$2:$M$644=$C$4)))),0) )} -> 13 | I65: =IF($C$4="All Portfolios", COUNTIFS(Positions!$O$2:$O$644, tbl_report_manager[[#This Row],[Manager Name]]), COUNTIFS(Positions!$M$2:$M$644, $C$4,Positions!$O$2:$O$644, tbl_report_manager[[#This Row],[Manager Name]]) ) -> 13
B66: CVC Credit Partners | C66: =IF($C$4="All Portfolios", SUMIFS(tbl_rawhold[Current Face],tbl_rawhold[Manager], tbl_report_manager[[#This Row],[Manager Name]]), SUMIFS(tbl_rawhold[Current Face], tbl_rawhold[Portfolio_Name], $C$4,tbl_rawhold[Manager], tbl_report_manager[[#This Row],[Manager Name]])) -> 67496000 | D66: =IF($C$4="All Portfolios", SUMIFS(tbl_rawhold[BASEMarket Value],tbl_rawhold[Manager], tbl_report_manager[[#This Row],[Manager Name]]), SUMIFS(tbl_rawhold[BASEMarket Value], tbl_rawhold[Portfolio_Name], $C$4,tbl_rawhold[Manager], tbl_report_manager[[#This Row],[Manager Name]])) -> 67720522 | E66: =IFERROR(tbl_report_manager[[#This Row],[Current Face]]/$C$54,0) -> 0.037664213 | F66: =IFERROR(tbl_report_manager[[#This Row],[Market Value]]/$D$54,0) -> 0.03831353 | G66: {=IF($C$4="All Portfolios", IFERROR(ROWS(_xlfn.UNIQUE(_xlfn._xlws.FILTER(Positions!$F$2:$F$644, Positions!$O$2:$O$644=tbl_report_manager[[#This Row],[Manager Name]]))),0), IFERROR(ROWS(_xlfn.UNIQUE(_xlfn._xlws.FILTER(Positions!$F$2:$F$644, (Positions!$O$2:$O$644=tbl_report_manager[[#This Row],[Manager Name]])*(Positions!$M$2:$M$644=$C$4)))),0) )} -> 1 | H66: {=IF($C$4="All Portfolios", IFERROR(ROWS(_xlfn.UNIQUE(_xlfn._xlws.FILTER(Positions!$B$2:$B$644, Positions!$O$2:$O$644=tbl_report_manager[[#This Row],[Manager Name]]))),0), IFERROR(ROWS(_xlfn.UNIQUE(_xlfn._xlws.FILTER(Positions!$B$2:$B$644, (Positions!$O$2:$O$644=tbl_report_manager[[#This Row],[Manager Name]])*(Positions!$M$2:$M$644=$C$4)))),0) )} -> 13 | I66: =IF($C$4="All Portfolios", COUNTIFS(Positions!$O$2:$O$644, tbl_report_manager[[#This Row],[Manager Name]]), COUNTIFS(Positions!$M$2:$M$644, $C$4,Positions!$O$2:$O$644, tbl_report_manager[[#This Row],[Manager Name]]) ) -> 15
B67: Elmwood Asset Management | C67: =IF($C$4="All Portfolios", SUMIFS(tbl_rawhold[Current Face],tbl_rawhold[Manager], tbl_report_manager[[#This Row],[Manager Name]]), SUMIFS(tbl_rawhold[Current Face], tbl_rawhold[Portfolio_Name], $C$4,tbl_rawhold[Manager], tbl_report_manager[[#This Row],[Manager Name]])) -> 66637000 | D67: =IF($C$4="All Portfolios", SUMIFS(tbl_rawhold[BASEMarket Value],tbl_rawhold[Manager], tbl_report_manager[[#This Row],[Manager Name]]), SUMIFS(tbl_rawhold[BASEMarket Value], tbl_rawhold[Portfolio_Name], $C$4,tbl_rawhold[Manager], tbl_report_manager[[#This Row],[Manager Name]])) -> 67014236 | E67: =IFERROR(tbl_report_manager[[#This Row],[Current Face]]/$C$54,0) -> 0.037184872 | F67: =IFERROR(tbl_report_manager[[#This Row],[Market Value]]/$D$54,0) -> 0.037913942 | G67: {=IF($C$4="All Portfolios", IFERROR(ROWS(_xlfn.UNIQUE(_xlfn._xlws.FILTER(Positions!$F$2:$F$644, Positions!$O$2:$O$644=tbl_report_manager[[#This Row],[Manager Name]]))),0), IFERROR(ROWS(_xlfn.UNIQUE(_xlfn._xlws.FILTER(Positions!$F$2:$F$644, (Positions!$O$2:$O$644=tbl_report_manager[[#This Row],[Manager Name]])*(Positions!$M$2:$M$644=$C$4)))),0) )} -> 1 | H67: {=IF($C$4="All Portfolios", IFERROR(ROWS(_xlfn.UNIQUE(_xlfn._xlws.FILTER(Positions!$B$2:$B$644, Positions!$O$2:$O$644=tbl_report_manager[[#This Row],[Manager Name]]))),0), IFERROR(ROWS(_xlfn.UNIQUE(_xlfn._xlws.FILTER(Positions!$B$2:$B$644, (Positions!$O$2:$O$644=tbl_report_manager[[#This Row],[Manager Name]])*(Positions!$M$2:$M$644=$C$4)))),0) )} -> 14 | I67: =IF($C$4="All Portfolios", COUNTIFS(Positions!$O$2:$O$644, tbl_report_manager[[#This Row],[Manager Name]]), COUNTIFS(Positions!$M$2:$M$644, $C$4,Positions!$O$2:$O$644, tbl_report_manager[[#This Row],[Manager Name]]) ) -> 14
... B71: Blackstone CLO Management | C71: =IF($C$4="All Portfolios", SUMIFS(tbl_rawhold[Current Face],tbl_rawhold[Manager], tbl_report_manager[[#This Row],[Manager Name]]), SUMIFS(tbl_rawhold[Current Face], tbl_rawhold[Portfolio_Name], $C$4,tbl_rawhold[Manager], tbl_report_manager[[#This Row],[Manager Name]])) -> 48750530 | D71: =IF($C$4="All Portfolios", SUMIFS(tbl_rawhold[BASEMarket Value],tbl_rawhold[Manager], tbl_report_manager[[#This Row],[Manager Name]]), SUMIFS(tbl_rawhold[BASEMarket Value], tbl_rawhold[Portfolio_Name], $C$4,tbl_rawhold[Manager], tbl_report_manager[[#This Row],[Manager Name]])) -> 48929357 | E71: =IFERROR(tbl_report_manager[[#This Row],[Current Face]]/$C$54,0) -> 0.027203839 | F71: =IFERROR(tbl_report_manager[[#This Row],[Market Value]]/$D$54,0) -> 0.02768225 | G71: {=IF($C$4="All Portfolios", IFERROR(ROWS(_xlfn.UNIQUE(_xlfn._xlws.FILTER(Positions!$F$2:$F$644, Positions!$O$2:$O$644=tbl_report_manager[[#This Row],[Manager Name]]))),0), IFERROR(ROWS(_xlfn.UNIQUE(_xlfn._xlws.FILTER(Positions!$F$2:$F$644, (Positions!$O$2:$O$644=tbl_report_manager[[#This Row],[Manager Name]])*(Positions!$M$2:$M$644=$C$4)))),0) )} -> 6 | H71: {=IF($C$4="All Portfolios", IFERROR(ROWS(_xlfn.UNIQUE(_xlfn._xlws.FILTER(Positions!$B$2:$B$644, Positions!$O$2:$O$644=tbl_report_manager[[#This Row],[Manager Name]]))),0), IFERROR(ROWS(_xlfn.UNIQUE(_xlfn._xlws.FILTER(Positions!$B$2:$B$644, (Positions!$O$2:$O$644=tbl_report_manager[[#This Row],[Manager Name]])*(Positions!$M$2:$M$644=$C$4)))),0) )} -> 8 | I71: =IF($C$4="All Portfolios", COUNTIFS(Positions!$O$2:$O$644, tbl_report_manager[[#This Row],[Manager Name]]), COUNTIFS(Positions!$M$2:$M$644, $C$4,Positions!$O$2:$O$644, tbl_report_manager[[#This Row],[Manager Name]]) ) -> 8
B78: Type | C78: Issuer | D78: Security Description | E78: Cusip | F78: Settle Date | G78: Face Value | H78: Tranche Rating
B86: Issuer | C86: Security Description | D86: Cusip | E86: Trade Date | F86: Settle Date | G86: Face Value | H86: Sale Price | I86: Maturity Date | J86: Tranche Rating
B94: Issuer | C94: Security Description | D94: Cusip | E94: Trade Date | F94: Settle Date | G94: Face Value | H94: Purchase Price | I94: Maturity Date | J94: Tranche Rating
B103: Cusip | C103: Issuer | D103: Security Description | E103: Issue Date | F103: Maturity Date | G103: Coupon | H103: Spread | I103: Current Face | J103: Factor | K103: Market Price | L103: Market Value | M103: NRSRO | N103: NRSRO Rating | O103: WAL | P103: Par Sub | Q103: Implied DM | R103: Next Payment Date | S103: Non-Call Date
B111: Cusip | C111: Issuer | D111: Security Description | E111: Issue Date | F111: Maturity Date | G111: Coupon | H111: Spread | I111: Current Face | J111: Factor | K111: Market Price | L111: Market Value | M111: NRSRO | N111: NRSRO Rating | O111: WAL | P111: Par Sub | Q111: Implied DM | R111: Next Payment Date | S111: Non-Call Date
B124: Cusip | C124: Issuer | D124: Security Description | E124: Issue Date | F124: Maturity Date | G124: Coupon | H124: Spread | I124: Current Face | J124: Factor | K124: Market Price | L124: Market Value | M124: NRSRO | N124: NRSRO Rating | O124: WAL | P124: Par Sub | Q124: Implied DM | R124: Next Payment Date | S124: Non-Call Date
B142: Cusip | C142: Issuer | D142: Security Description | E142: Issue Date | F142: Maturity Date | G142: Coupon | H142: Spread | I142: Current Face | J142: Factor | K142: Market Price | L142: Market Value | M142: NRSRO | N142: NRSRO Rating | O142: WAL | P142: Par Sub | Q142: Implied DM | R142: Next Payment Date | S142: Non-Call Date
B162: Cusip | C162: Issuer | D162: Security Description | E162: Issue Date | F162: Maturity Date | G162: Coupon | H162: Spread | I162: Current Face | J162: Factor | K162: Market Price | L162: Market Value | M162: NRSRO | N162: NRSRO Rating | O162: WAL | P162: Par Sub | Q162: Implied DM | R162: Next Payment Date | S162: Non-Call Date
B182: Cusip | C182: Issuer | D182: Security Description | E182: Issue Date | F182: Maturity Date | G182: Coupon | H182: Spread | I182: Current Face | J182: Factor | K182: Market Price | L182: Market Value | M182: NRSRO | N182: NRSRO Rating | O182: WAL | P182: Par Sub | Q182: Implied DM | R182: Next Payment Date | S182: Non-Call Date
B192: Cusip | C192: Issuer | D192: Security Description | E192: Issue Date | F192: Maturity Date | G192: Coupon | H192: Spread | I192: Current Face | J192: Factor | K192: Market Price | L192: Market Value | M192: NRSRO | N192: NRSRO Rating | O192: WAL | P192: Par Sub | Q192: Implied DM | R192: Next Payment Date | S192: Non-Call Date
B200: Cusip | C200: Issuer | D200: Security Description | E200: Issue Date | F200: Maturity Date | G200: Coupon | H200: Spread | I200: Current Face | J200: Factor | K200: Market Price | L200: Market Value | M200: NRSRO | N200: NRSRO Rating | O200: WAL | P200: Par Sub | Q200: Implied DM | R200: Next Payment Date | S200: Non-Call Date

Sheet ValidationLists
A1: All Portfolios
A2: 43CH;IG CLO Strategy
A3: 44K8;HY CLO Strategy
A4: 44F6;Atypical CLO Strategy
A5: 44D7;ABS Strategy

Sheet Transactions
A1: Portfolio | B1: Security ID | C1: Security Description | D1: Trade Date | E1: Settle Date | F1: Maturity Date | G1: Quantity | H1: Price | I1: Cost Proceeds | J1: Coupon Rate | K1: Portfolio_Name | L1: Type
A2: SBL_404_404 | B2: 442911AS2 | C2: HLM 2023-18A CR 20-Jul-2039 | D2: 07-01-2025 | E2: 07-21-2025 | F2: 07-20-2039 | G2: 4464912 | H2: 100 | I2: 4464912 | J2: 6.32549 | K2: 43CH;IG CLO Strategy | L2: BUY
A3: SBL_404_404 | B3: 442911AU7 | C3: HLM 2023-18A D1R 20-Jul-2039 | D3: 07-01-2025 | E3: 07-21-2025 | F3: 07-20-2039 | G3: 6700000 | H3: 100 | I3: 6700000 | J3: 7.37549 | K3: 43CH;IG CLO Strategy | L3: BUY
A4: SBL_111_111 | B4: 442921AJ1 | C4: HLM 2023-18A ER 20-Jul-2039 | D4: 07-01-2025 | E4: 07-21-2025 | F4: 07-20-2039 | G4: 300000 | H4: 100 | I4: 300000 | J4: 10.32549 | K4: 44K8;HY CLO Strategy | L4: BUY
A5: SBL_404_404 | B5: 03770MAG8 | C5: APID 2023-45A D 26-Apr-2036 | D5: 07-02-2025 | E5: 07-02-2025 | F5: 04-26-2036 | G5: -5957000 | H5: 100 | I5: -5957000 | J5: 9.48262 | K5: 43CH;IG CLO Strategy | L5: Paydown
A6: SBL_404_404 | B6: 83013LAG9 | C6: SIXST 2025-30A D 17-Jul-2038 | D6: 07-02-2025 | E6: 08-13-2025 | F6: 07-17-2038 | G6: 7800000 | H6: 100 | I6: 7800000 | J6: 7.18949 | K6: 43CH;IG CLO Strategy | L6: BUY
A7: SBL_404_404 | B7: 26243EAC5 | C7: DRSLF 2017-53A C 15-Jan-2031 | D7: 07-08-2025 | E7: 07-08-2025 | F7: 01-15-2031 | G7: -13280000 | H7: 100 | I7: -13280000 | J7: 12.43542 | K7: 43CH;IG CLO Strategy | L7: Paydown
A8: SBL_404_404 | B8: 67402LAJ5 | C8: OAKCL 2022-1A C 15-May-2033 | D8: 07-08-2025 | E8: 07-08-2025 | F8: 05-15-2033 | G8: -4000000 | H8: 100 | I8: -4000000 | J8: 7.22633 | K8: 43CH;IG CLO Strategy | L8: Paydown
A9: SBL_404_404 | B9: 38139QAL0 | C9: GLM 2025-26A D 20-Jul-2038 | D9: 07-09-2025 | E9: 08-07-2025 | F9: 07-20-2038 | G9: 9900000 | H9: 100 | I9: 9900000 | J9: 7.02411 | K9: 43CH;IG CLO Strategy | L9: BUY
A10: SBL_404_404 | B10: 69704GAJ7 | C10: PLMRS 2025-3A D1 20-Jul-2038 | D10: 07-09-2025 | E10: 08-20-2025 | F10: 07-20-2038 | G10: 9900000 | H10: 100 | I10: 9900000 | J10: 7.07546 | K10: 43CH;IG CLO Strategy | L10: BUY
A11: SBL_111_111 | B11: 29003KAA9 | C11: ELM15 2022-2A E 22-Apr-2035 | D11: 07-10-2025 | E11: 07-10-2025 | F11: 04-22-2035 | G11: -250000 | H11: 100 | I11: -250000 | J11: 11.52238 | K11: 44K8;HY CLO Strategy | L11: Paydown
A12: SBL_404_404 | B12: 43128QAL3 | C12: HIGPK 2025-1A D1 24-Jul-2038 | D12: 07-10-2025 | E12: 08-21-2025 | F12: 07-24-2038 | G12: 9900000 | H12: 100 | I12: 9900000 | J12: 7.02366 | K12: 43CH;IG CLO Strategy | L12: BUY
A13: SBL_404_404 | B13: 001210AJ2 | C13: AGL 2022-19A D 21-Jul-2035 | D13: 07-11-2025 | E13: 07-11-2025 | F13: 07-21-2035 | G13: -3750000 | H13: 100 | I13: -3750000 | J13: 8.90317 | K13: 43CH;IG CLO Strategy | L13: Paydown
... A61: SBL_105_105 | B61: 78396YAA1 | C61: SESAC 2019-1 A2 25-Jul-2049 | D61: 07-31-2025 | E61: 07-31-2025 | F61: 07-25-2049 | G61: -14100000 | H61: 100 | I61: -14100000 | J61: 5.216 | K61: 44D7;ABS Strategy | L61: Call

Sheet Positions
A1: Portfolio Code | B1: CUSIP | C1: Current Face | D1: BASEMarket Value | E1: BASEOriginal Cost | F1: Issuer Name | G1: Coupon Rate | H1: Security Description | I1: Maturity Date | J1: Spread | K1: Factor | L1: Yield | M1: Portfolio_Name | N1: Row Labels | O1: Manager | P1: WAL | Q1: Implied DM | R1: Vintage | S1: Collateral Type | T1: Tranche Rating | U1: WAL_Range | V1: coupon_Range
A2: SBL_404_404 | B2: 00119AAS4 | C2: 9073000 | D2: 9156426.2 | E2: 9073000 | F2: AGL CLO Ltd | G2: 6.46899 | H2: AGL 2023-24A CR 31-Mar-2038 | I2: 50495 | J2: 215 | K2: 1 | L2: 6.468205 | M2: 43CH;IG CLO Strategy | N2: 00119AAS4 | O2: AGL CLO Credit Management | P2: 9.1695377 | Q2: 202.15609 | R2: 2025 | T2: A | U2: 8<10 | V2: 6<7
A3: SBL_404_404 | B3: 00119AAU9 | C3: 10207000 | D3: 10148483 | E3: 10207000 | F3: AGL CLO Ltd | G3: 7.61899 | H3: AGL 2023-24A D1R 31-Mar-2038 | I3: 50495 | J3: 330 | K3: 1 | L3: 7.617901 | M3: 43CH;IG CLO Strategy | N3: 00119AAU9 | O3: AGL CLO Credit Management | P3: 9.7045333 | Q3: 337.95476 | R3: 2025 | T3: BBB | U3: 8<10 | V3: 7+
A4: SBL_404_404 | B4: 00119BAE3 | C4: 2800000 | D4: 2823270.8 | E4: 2800000 | F4: AGL CLO Ltd | G4: 8.07549 | H4: AGL 2024-29A D 21-Apr-2037 | I4: 50151 | J4: 375 | K4: 1 | L4: 8.07426 | M4: 43CH;IG CLO Strategy | N4: 00119BAE3 | O4: AGL CLO Credit Management | P4: 8.6122414 | Q4: 361.88465 | R4: 2024 | T4: BBB | U4: 8<10 | V4: 7+
A5: SBL_404_404 | B5: 00120NAU8 | C5: 5048267 | D5: 5073205.4 | E5: 5048267 | F5: AGL CLO Ltd | G5: 7.22322 | H5: AGL 2023-25A D1R 21-Jul-2038 | I5: 50607 | J5: 290 | K5: 1 | L5: 7.220994 | M5: 43CH;IG CLO Strategy | N5: 00120NAU8 | O5: AGL CLO Credit Management | P5: 9.6224766 | Q5: 282.97731 | R5: 2025 | T5: BBB | U5: 8<10 | V5: 7+
A6: SBL_404_404 | B6: 001210AY9 | C6: 12500000 | D6: 12550712 | E6: 12500000 | F6: AGL CLO Ltd | G6: 7.37046 | H6: AGL 2022-19A D1R 21-Jul-2038 | I6: 50607 | J6: 305 | K6: 1 | L6: 7.369067 | M6: 43CH;IG CLO Strategy | N6: 001210AY9 | O6: AGL CLO Credit Management | P6: 9.2339746 | Q6: 299.10923 | R6: 2025 | T6: BBB | U6: 8<10 | V6: 7+
A7: SBL_404_404 | B7: 00121JAJ1 | C7: 4000000 | D7: 4020632 | E7: 4050000 | F7: AGL CLO Ltd | G7: 7.23199 | H7: AGL 2024-34A D1 22-Jan-2038 | I7: 50427 | J7: 290 | K7: 1 | L7: 2.48927 | M7: 43CH;IG CLO Strategy | N7: 00121JAJ1 | O7: AGL CLO Credit Management | P7: 9.2368901 | Q7: 282.51285 | R7: 2024 | T7: BBB | U7: 8<10 | V7: 7+
A8: SBL_404_404 | B8: 00121XAJ0 | C8: 6700000 | D8: 6712127 | E8: 6700000 | F8: AGL CLO Ltd | G8: 6.71291 | H8: AGL 2025-39A D1 20-Apr-2038 | I8: 50515 | J8: 250 | K8: 1 | L8: 6.706031 | M8: 43CH;IG CLO Strategy | N8: 00121XAJ0 | O8: AGL CLO Credit Management | P8: 9.4166014 | Q8: 247.36839 | R8: 2025 | T8: BBB | U8: 8<10 | V8: 6<7
A9: SBL_404_404 | B9: 00190YBV6 | C9: 10000000 | D9: 10013290 | E9: 10000000 | F9: ARES CLO | G9: 7.31381 | H9: ARES 2013-2A DR3 28-Oct-2034 | I9: 49245 | J9: 300 | K9: 1 | L9: 7.312799 | M9: 43CH;IG CLO Strategy | N9: 00190YBV6 | O9: Ares CLO Management | P9: 5.7484801 | Q9: 297.06337 | R9: 2024 | T9: BBB | U9: 4<6 | V9: 7+
A10: SBL_404_404 | B10: 00901AAW7 | C10: 450000 | D10: 451706.85 | E10: 450000 | F10: Aimco CDO | G10: 6.38199 | H10: AIMCO 2019-10A CRR 22-Jul-2037 | I10: 50243 | J10: 205 | K10: 1 | L10: 6.381222 | M10: 43CH;IG CLO Strategy | N10: 00901AAW7 | O10: Allstate Investment Management Co | P10: 8.2745266 | Q10: 199.21467 | R10: 2024 | T10: A | U10: 8<10 | V10: 6<7
A11: SBL_404_404 | B11: 00901AAY3 | C11: 650000 | D11: 651902.55 | E11: 650000 | F11: Aimco CDO | G11: 7.33199 | H11: AIMCO 2019-10A D1RR 22-Jul-2037 | I11: 50243 | J11: 300 | K11: 1 | L11: 7.330977 | M11: 43CH;IG CLO Strategy | N11: 00901AAY3 | O11: Allstate Investment Management Co | P11: 8.8400927 | Q11: 295.5374 | R11: 2024 | T11: BBB | U11: 8<10 | V11: 7+
A12: SBL_404_404 | B12: 00901UAE3 | C12: 4000000 | D12: 4026364 | E12: 4000000 | F12: Aimco CDO | G12: 6.72549 | H12: AIMCO 2024-22A C 19-Apr-2037 | I12: 50149 | J12: 240 | K12: 1 | L12: 6.724689 | M12: 43CH;IG CLO Strategy | N12: 00901UAE3 | O12: Allstate Investment Management Co | P12: 8.0334814 | Q12: 229.63818 | R12: 2024 | T12: A | U12: 8<10 | V12: 6<7
A13: SBL_404_404 | B13: 00901UAG8 | C13: 4000000 | D13: 4035132 | E13: 4000000 | F13: Aimco CDO | G13: 7.72549 | H13: AIMCO 2024-22A D 19-Apr-2037 | I13: 50149 | J13: 340 | K13: 1 | L13: 7.724435 | M13: 43CH;IG CLO Strategy | N13: 00901UAG8 | O13: Allstate Investment Management Co | P13: 8.6491278 | Q13: 326.44972 | R13: 2024 | T13: BBB | U13: 8<10 | V13: 7+
... A27: SBL_404_404 | B27: 03770CAW5 | C27: 3750000 | D27: 3760511.2 | E27: 3750000 | F27: Apidos CLO | G27: 7.32549 | H27: APID 2022-41A D1R 20-Oct-2037 | I27: 50333 | J27: 300 | K27: 1 | L27: 7.32451 | M27: 43CH;IG CLO Strategy | N27: 03770CAW5 | O27: CVC Credit Partners | P27: 9.1320602 | Q27: 295.82525 | R27: 2024 | T27: BBB | U27: 8<10 | V27: 7+
A28: SBL_404_404 | B28: 03770MAU7 | C28: 4840000 | D28: 4849307.3 | E28: 4840000 | F28: Apidos CLO | G28: 7.10273 | H28: APID 2023-45A D1R 26-Jul-2038 | I28: 50612 | J28: 285 | L28: 7.100834 | M28: 43CH;IG CLO Strategy | N28: 03770MAU7 | O28: CVC Credit Partners | P28: 9.7105044 | Q28: 282.17599 | R28: 2025 | T28: BBB | U28: 8<10 | V28: 7+
A29: SBL_404_404 | B29: 03770QAJ3 | C29: 10000000 | D29: 10062390 | E29: 10000000 | F29: Apidos CLO | G29: 7.71381 | H29: APID 2024-47A D1 26-Apr-2037 | I29: 50156 | J29: 340 | K29: 1 | L29: 7.712768 | M29: 43CH;IG CLO Strategy | N29: 03770QAJ3 | O29: CVC Credit Partners | P29: 8.5484472 | Q29: 330.26119 | R29: 2024 | T29: BBB | U29: 8<10 | V29: 7+
A30: SBL_404_404 | B30: 03771EAL4 | C30: 2600000 | D30: 2607404.8 | E30: 2600000 | F30: Apidos CLO | G30: 7.82854 | H30: APID 2025-53A D1 20-Jul-2038 | I30: 50606 | J30: 350 | K30: 1 | L30: 7.823481 | M30: 43CH;IG CLO Strategy | N30: 03771EAL4 | O30: CVC Credit Partners | P30: 9.6992958 | Q30: 345.64255 | R30: 2025 | T30: BBB | U30: 8<10 | V30: 7+
A31: SBL_404_404 | B31: 03771JAG4 | C31: 2300000 | D31: 2302812.9 | E31: 2300000 | F31: Apidos CLO | G31: 6.07549 | H31: APID 2024-51A C 20-Jan-2038 | I31: 50425 | J31: 175 | K31: 1 | L31: 6.074815 | M31: 43CH;IG CLO Strategy | N31: 03771JAG4 | O31: CVC Credit Partners | P31: 8.7332149 | Q31: 173.17659 | R31: 2025 | T31: A | U31: 8<10 | V31: 6<7
A32: SBL_404_404 | B32: 03771JAJ8 | C32: 11500000 | D32: 11530026 | E32: 11500000 | F32: Apidos CLO | G32: 6.92549 | H32: APID 2024-51A D1 20-Jan-2038 | I32: 50425 | J32: 260 | K32: 1 | L32: 6.924614 | M32: 43CH;IG CLO Strategy | N32: 03771JAJ8 | O32: CVC Credit Partners | P32: 9.2544951 | Q32: 256.21664 | R32: 2025 | T32: BBB | U32: 8<10 | V32: 6<7
A33: SBL_404_404 | B33: 037989AQ3 | C33: 7606000 | D33: 7630856.4 | E33: 7606000 | F33: Apidos CLO | G33: 7.16381 | H33: APID 2023-44A D1R 26-Oct-2037 | I33: 50339 | J33: 285 | K33: 1 | L33: 7.162909 | M33: 43CH;IG CLO Strategy | N33: 037989AQ3 | O33: CVC Credit Partners | P33: 9.0925477 | Q33: 280.18418 | R33: 2024 | T33: BBB | U33: 8<10 | V33: 7+
A34: SBL_404_404 | B34: 039937BA4 | C34: 4400000 | D34: 4417111.6 | E34: 4400000 | F34: ARES CLO | G34: 7.28307 | H34: ARES 2022-63A D1R 15-Oct-2038 | I34: 50693 | J34: 300 | K34: 1 | L34: 0 | M34: 43CH;IG CLO Strategy | N34: 039937BA4 | O34: Ares CLO Management | P34: 0 | Q34: 293.33317 | R34: 2025 | T34: BBB | U34: 0<2 | V34: 7+
A35: SBL_404_404 | B35: 039939AW3 | C35: 5000000 | D35: 5006585 | E35: 5000000 | F35: ARES CLO | G35: 6.01846 | H35: ARES 2022-67A CR 25-Jan-2038 | I35: 50430 | J35: 170 | K35: 1 | L35: 6.017774 | M35: 43CH;IG CLO Strategy | N35: 039939AW3 | O35: Ares CLO Management | P35: 8.7640608 | Q35: 168.05691 | R35: 2025 | T35: A | U35: 8<10 | V35: 6<7
A36: SBL_404_404 | B36: 039939AY9 | C36: 5450000 | D36: 5447236.8 | E36: 5450000 | F36: ARES CLO | G36: 6.91846 | H36: ARES 2022-67A D1R 25-Jan-2038 | I36: 50430 | J36: 260 | K36: 1 | L36: 6.917554 | M36: 43CH;IG CLO Strategy | N36: 039939AY9 | O36: Ares CLO Management | P36: 9.283191 | Q36: 260.60747 | R36: 2025 | T36: BBB | U36: 8<10 | V36: 6<7
A37: SBL_404_404 | B37: 039948AG9 | C37: 5700000 | D37: 5717100 | E37: 5700000 | F37: ARES CLO | G37: 6.16755 | H37: ARES 2024-75A C 15-Jan-2037 | I37: 50055 | J37: 185 | K37: 1 | L37: 6.166825 | M37: 43CH;IG CLO Strategy | N37: 039948AG9 | O37: Ares CLO Management | P37: 8.7414527 | Q37: 180.6388 | R37: 2025 | T37: A | U37: 8<10 | V37: 6<7
A38: SBL_404_404 | B38: 039948AJ3 | C38: 14400000 | D38: 14535778 | E38: 14400000 | F38: ARES CLO | G38: 7.11755 | H38: ARES 2024-75A D1 15-Jan-2037 | I38: 50055 | J38: 280 | K38: 1 | L38: 7.116585 | M38: 43CH;IG CLO Strategy | N38: 039948AJ3 | O38: Ares CLO Management | P38: 9.2397408 | Q38: 266.53896 | R38: 2025 | T38: BBB | U38: 8<10 | V38: 7+
A39: SBL_404_404 | B39: 039951AJ7 | C39: 2000000 | D39: 2011268 | E39: 2000000 | F39: ARES CLO | G39: 8.81846 | H39: ARES 2023-70A D1 25-Oct-2035 | I39: 49607 | J39: 450 | K39: 1 | L39: 8.816983 | M39: 43CH;IG CLO Strategy | N39: 039951AJ7 | O39: Ares U.S. CLO Management | P39: 7.9824592 | Q39: 440.29024 | R39: 2023 | T39: BBB | U39: 6<8 | V39: 7+
A40: SBL_404_404 | B40: 039953AJ3 | C40: 1000000 | D40: 1005631 | E40: 1000000 | F40: ARES CLO | G40: 7.91755 | H40: ARES 2024-69A D 15-Apr-2036 | I40: 49780 | J40: 360 | K40: 1 | L40: 7.916354 | M40: 43CH;IG CLO Strategy | N40: 039953AJ3 | O40: Ares CLO Management | P40: 8.6684642 | Q40: 351.19647 | R40: 2024 | T40: BBB | U40: 8<10 | V40: 7+
... A43: SBL_404_404 | B43: 04015GAV1 | C43: 12150000 | D43: 12166743 | E43: 12171651 | F43: ARES CLO | G43: 7.68401 | H43: ARES 2015-2A DR 17-Apr-2033 | I43: 48686 | J43: 336.161 | K43: 1 | L43: 7.782248 | M43: 43CH;IG CLO Strategy | N43: 04015GAV1 | O43: Ares CLO Management | P43: 5.164905 | Q43: 332.84789 | R43: 2020 | T43: BBB | U43: 4<6 | V43: 7+
A44: SBL_404_404 | B44: 04016NAX1 | C44: 484000 | D44: 484024.2 | E44: 484000 | F44: ARES CLO | G44: 7.97916 | H44: ARES 2017-44A CR 15-Apr-2034 | I44: 49049 | J44: 366.161 | K44: 1 | L44: 8.051111 | M44: 43CH;IG CLO Strategy | N44: 04016NAX1 | O44: Ares CLO Management | P44: 5.7848789 | R44: 2021 | T44: BBB | U44: 4<6 | V44: 7+
A45: SBL_404_404 | B45: 04016NAX1 | C45: 5808000 | D45: 5808290.4 | E45: 5808000 | F45: ARES CLO | G45: 7.97916 | H45: ARES 2017-44A CR 15-Apr-2034 | I45: 49049 | J45: 366.161 | K45: 1 | L45: 8.051111 | M45: 43CH;IG CLO Strategy | N45: 04016NAX1 | O45: Ares CLO Management | P45: 5.7848789 | R45: 2021 | T45: BBB | U45: 4<6 | V45: 7+
A46: SBL_404_404 | B46: 04016NAX1 | C46: 1450000 | D46: 1450072.5 | E46: 1458082.3 | F46: ARES CLO | G46: 7.97916 | H46: ARES 2017-44A CR 15-Apr-2034 | I46: 49049 | J46: 366.161 | K46: 1 | L46: 8.051111 | M46: 43CH;IG CLO Strategy | N46: 04016NAX1 | O46: Ares CLO Management | P46: 5.7848789 | R46: 2021 | T46: BBB | U46: 4<6 | V46: 7+
A47: SBL_404_404 | B47: 04016NAX1 | C47: 3250000 | D47: 3250162.5 | E47: 3271168.8 | F47: ARES CLO | G47: 7.97916 | H47: ARES 2017-44A CR 15-Apr-2034 | I47: 49049 | J47: 366.161 | K47: 1 | L47: 8.051111 | M47: 43CH;IG CLO Strategy | N47: 04016NAX1 | O47: Ares CLO Management | P47: 5.7848789 | R47: 2021 | T47: BBB | U47: 4<6 | V47: 7+
A48: SBL_404_404 | B48: 04016NAX1 | C48: 4700000 | D48: 4700235 | E48: 4719277.9 | F48: ARES CLO | G48: 7.97916 | H48: ARES 2017-44A CR 15-Apr-2034 | I48: 49049 | J48: 366.161 | K48: 1 | L48: 8.051111 | M48: 43CH;IG CLO Strategy | N48: 04016NAX1 | O48: Ares CLO Management | P48: 5.7848789 | R48: 2021 | T48: BBB | U48: 4<6 | V48: 7+
A49: SBL_404_404 | B49: 04016PBA5 | C49: 18000000 | D49: 18172332 | E49: 18000000 | F49: ARES CLO | G49: 7.31755 | H49: ARES 2017-43A D1R2 15-Jan-2038 | I49: 50420 | J49: 300 | K49: 1 | L49: 7.316534 | M49: 43CH;IG CLO Strategy | N49: 04016PBA5 | O49: Ares CLO Management | P49: 9.2465226 | Q49: 286.21597 | R49: 2024 | T49: BBB | U49: 8<10 | V49: 7+
A50: SBL_404_404 | B50: 04018EAG6 | C50: 387000 | D50: 388631.21 | E50: 387000 | F50: ARES CLO | G50: 7.73007 | H50: ARES 2021-59A D 25-Apr-2034 | I50: 49059 | J50: 341.161 | K50: 1 | L50: 7.842499 | M50: 43CH;IG CLO Strategy | N50: 04018EAG6 | O50: Ares CLO Management | P50: 5.8614029 | Q50: 332.19381 | R50: 2021 | T50: BBB | U50: 4<6 | V50: 7+
A51: SBL_404_404 | B51: 04018EAG6 | C51: 4650000 | D51: 4669599.8 | E51: 4650000 | F51: ARES CLO | G51: 7.73007 | H51: ARES 2021-59A D 25-Apr-2034 | I51: 49059 | J51: 341.161 | K51: 1 | L51: 7.842499 | M51: 43CH;IG CLO Strategy | N51: 04018EAG6 | O51: Ares CLO Management | P51: 5.8614029 | Q51: 332.19381 | R51: 2021 | T51: BBB | U51: 4<6 | V51: 7+
A52: SBL_404_404 | B52: 04018EAG6 | C52: 570000 | D52: 572402.55 | E52: 571179.33 | F52: ARES CLO | G52: 7.73007 | H52: ARES 2021-59A D 25-Apr-2034 | I52: 49059 | J52: 341.161 | K52: 1 | L52: 7.842499 | M52: 43CH;IG CLO Strategy | N52: 04018EAG6 | O52: Ares CLO Management | P52: 5.8614029 | Q52: 332.19381 | R52: 2021 | T52: BBB | U52: 4<6 | V52: 7+
A53: SBL_404_404 | B53: 04018NBE0 | C53: 11112500 | D53: 11154472 | E53: 11112500 | F53: ARES CLO | G53: 7.16846 | H53: ARES 2020-56A D1R2 25-Jan-2038 | I53: 50430 | J53: 285 | K53: 1 | L53: 7.167487 | M53: 43CH;IG CLO Strategy | N53: 04018NBE0 | O53: Ares CLO Management | P53: 9.2682575 | Q53: 279.52015 | R53: 2025 | T53: BBB | U53: 8<10 | V53: 7+
A54: SBL_404_404 | B54: 04019DAU6 | C54: 2000000 | D54: 2016986 | E54: 2000000 | F54: ARES CLO | G54: 8.22549 | H54: ARES 2021-61A DR 20-Apr-2037 | I54: 50150 | J54: 390 | K54: 1 | L54: 8.224256 | M54: 43CH;IG CLO Strategy | N54: 04019DAU6 | O54: Ares CLO Management | P54: 8.6960655 | Q54: 376.67666 | R54: 2024 | T54: BBB | U54: 8<10 | V54: 7+
A55: SBL_404_404 | B55: 04019LBC7 | C55: 10006985 | D55: 10090753 | E55: 10006985 | F55: ARES CLO | G55: 7.46755 | H55: ARES 2019-51A D1R2 15-Oct-2037 | I55: 50328 | J55: 315 | K55: 1 | L55: 7.466491 | M55: 43CH;IG CLO Strategy | N55: 04019LBC7 | O55: Ares CLO Management | P55: 8.6515573 | Q55: 302.22791 | R55: 2024 | T55: BBB | U55: 8<10 | V55: 7+
A56: SBL_404_404 | B56: 04019RBA8 | C56: 4725000 | D56: 4761821.9 | E56: 4725000 | F56: ARES CLO | G56: 9.31846 | H56: ARES 2022-66A DR 25-Jul-2036 | I56: 49881 | J56: 500 | K56: 1 | L56: 9.316815 | M56: 43CH;IG CLO Strategy | N56: 04019RBA8 | O56: Ares CLO Management | P56: 7.670194 | Q56: 485.99716 | R56: 2023 | T56: BBB | U56: 6<8 | V56: 7+
A57: SBL_404_404 | B57: 04020FAE4 | C57: 1000000 | D57: 1005684 | E57: 1000000 | F57: ARES CLO | G57: 7.41755 | H57: ARES 2023-ALF4A C 15-Oct-2036 | I57: 49963 | J57: 310 | K57: 1 | L57: 7.416502 | M57: 43CH;IG CLO Strategy | N57: 04020FAE4 | O57: Ares CLO Management | P57: 7.3271128 | Q57: 300.13749 | R57: 2023 | T57: A | U57: 6<8 | V57: 7+
A58: SBL_404_404 | B58: 04020FAG9 | C58: 1000000 | D58: 1008484 | E58: 980000 | F58: ARES CLO | G58: 8.99755 | H58: ARES 2023-ALF4A D 15-Oct-2036 | I58: 49963 | J58: 468 | K58: 1 | L58: 9.371395 | M58: 43CH;IG CLO Strategy | N58: 04020FAG9 | O58: Ares CLO Management | P58: 7.9490822 | Q58: 453.36465 | R58: 2023 | T58: BBB | U58: 6<8 | V58: 7+
A59: SBL_404_404 | B59: 04021MAG3 | C59: 10000000 | D59: 10039000 | E59: 10000000 | F59: ARES CLO | G59: 6.16869 | H59: ARES 2024-ALF8 C 24-Jan-2038 | I59: 50429 | J59: 185 | K59: 1 | L59: 6.167968 | M59: 43CH;IG CLO Strategy | N59: 04021MAG3 | O59: Ares CLO Management | P59: 8.6883225 | Q59: 179.33429 | R59: 2025 | T59: A | U59: 8<10 | V59: 6<7
A60: SBL_404_404 | B60: 04021MAJ7 | C60: 25000000 | D60: 25161100 | E60: 25000000 | F60: ARES CLO | G60: 6.96869 | H60: ARES 2024-ALF8 D1 24-Jan-2038 | I60: 50429 | J60: 265 | K60: 1 | L60: 6.967768 | M60: 43CH;IG CLO Strategy | N60: 04021MAJ7 | O60: Ares CLO Management | P60: 9.2225401 | Q60: 255.79666 | R60: 2025 | T60: BBB | U60: 8<10 | V60: 6<7
... A68: SBL_404_404 | B68: 05876KAS4 | C68: 7540000 | D68: 7422097 | E68: 7540000 | F68: Ballyrock CLO Ltd | G68: 7.07549 | H68: BALLY 2021-16A C1R 20-Apr-2038 | I68: 50515 | J68: 275 | K68: 1 | L68: 7.074576 | M68: 43CH;IG CLO Strategy | N68: 05876KAS4 | O68: Ballyrock Investment Advisors | P68: 9.4884475 | Q68: 296.88244 | R68: 2025 | T68: BBB | U68: 8<10 | V68: 7+
A69: SBL_404_404 | B69: 05876UAE3 | C69: 4700000 | D69: 4712403.3 | E69: 4700000 | F69: Ballyrock CLO Ltd | G69: 0 | H69: BALLY 2025-30A C1 25-Oct-2038 | I69: 50703 | J69: 285 | K69: 1 | L69: 0 | M69: 43CH;IG CLO Strategy | N69: 05876UAE3 | O69: Ballyrock Ltd | P69: 9.03 | R69: 2025 | T69: BBB | U69: unknown | V69: 0<3
A70: SBL_404_404 | B70: 06744BAG8 | C70: 3825000 | D70: 3812136.5 | E70: 3710250 | F70: Bardin Hill CLO Ltd | G70: 7.94007 | H70: BARDN 2021-2A D 25-Oct-2034 | I70: 49242 | J70: 362.161 | K70: 1 | L70: 8.065007 | M70: 43CH;IG CLO Strategy | N70: 06744BAG8 | O70: Bardin Hill Performing Credit Management | P70: 6.1038458 | Q70: 368.74098 | R70: 2021 | T70: BBB | U70: 6<8 | V70: 7+
A71: SBL_404_404 | B71: 06744BAG8 | C71: 340000 | D71: 338856.58 | E71: 340009.52 | F71: Bardin Hill CLO Ltd | G71: 7.94007 | H71: BARDN 2021-2A D 25-Oct-2034 | I71: 49242 | J71: 362.161 | K71: 1 | L71: 8.065007 | M71: 43CH;IG CLO Strategy | N71: 06744BAG8 | O71: Bardin Hill Performing Credit Management | P71: 6.1038458 | Q71: 368.74098 | R71: 2021 | T71: BBB | U71: 6<8 | V71: 7+
A72: SBL_404_404 | B72: 06744BAG8 | C72: 570000 | D72: 568083.09 | E72: 569454.63 | F72: Bardin Hill CLO Ltd | G72: 7.94007 | H72: BARDN 2021-2A D 25-Oct-2034 | I72: 49242 | J72: 362.161 | K72: 1 | L72: 8.065007 | M72: 43CH;IG CLO Strategy | N72: 06744BAG8 | O72: Bardin Hill Performing Credit Management | P72: 6.1038458 | Q72: 368.74098 | R72: 2021 | T72: BBB | U72: 6<8 | V72: 7+
A73: SBL_404_404 | B73: 06744BAG8 | C73: 880000 | D73: 877040.56 | E73: 878066.74 | F73: Bardin Hill CLO Ltd | G73: 7.94007 | H73: BARDN 2021-2A D 25-Oct-2034 | I73: 49242 | J73: 362.161 | K73: 1 | L73: 8.065007 | M73: 43CH;IG CLO Strategy | N73: 06744BAG8 | O73: Bardin Hill Performing Credit Management | P73: 6.1038458 | Q73: 368.74098 | R73: 2021 | T73: BBB | U73: 6<8 | V73: 7+
A74: SBL_404_404 | B74: 06759JAW8 | C74: 4715544 | D74: 4727842.1 | E74: 4715544 | F74: BABSN 2018 3X | G74: 8.22916 | H74: BABSN 2019-1A DR 15-Apr-2035 | I74: 49414 | J74: 391.161 | K74: 1 | L74: -3.380264 | M74: 43CH;IG CLO Strategy | N74: 06759JAW8 | O74: Barings | P74: 5.891748 | Q74: 385.47442 | R74: 2021 | T74: BBB | U74: 4<6 | V74: 7+
A75: SBL_404_404 | B75: 06759JAW8 | C75: 1410000 | D75: 1413677.3 | E75: 1416402.8 | F75: BABSN 2018 3X | G75: 8.22916 | H75: BABSN 2019-1A DR 15-Apr-2035 | I75: 49414 | J75: 391.161 | K75: 1 | L75: -3.380264 | M75: 43CH;IG CLO Strategy | N75: 06759JAW8 | O75: Barings | P75: 5.891748 | Q75: 385.47442 | R75: 2021 | T75: BBB | U75: 4<6 | V75: 7+
A76: SBL_404_404 | B76: 06759JAW8 | C76: 1700000 | D76: 1704433.6 | E76: 1707860.8 | F76: BABSN 2018 3X | G76: 8.22916 | H76: BABSN 2019-1A DR 15-Apr-2035 | I76: 49414 | J76: 391.161 | K76: 1 | L76: -3.380264 | M76: 43CH;IG CLO Strategy | N76: 06759JAW8 | O76: Barings | P76: 5.891748 | Q76: 385.47442 | R76: 2021 | T76: BBB | U76: 4<6 | V76: 7+
A77: SBL_404_404 | B77: 06759JAW8 | C77: 2890000 | D77: 2897537.1 | E77: 2899739.8 | F77: BABSN 2018 3X | G77: 8.22916 | H77: BABSN 2019-1A DR 15-Apr-2035 | I77: 49414 | J77: 391.161 | K77: 1 | L77: -3.380264 | M77: 43CH;IG CLO Strategy | N77: 06759JAW8 | O77: Barings | P77: 5.891748 | Q77: 385.47442 | R77: 2021 | T77: BBB | U77: 4<6 | V77: 7+
A78: SBL_404_404 | B78: 06759JAW8 | C78: 3170000 | D78: 3178267.4 | E78: 3187055.5 | F78: BABSN 2018 3X | G78: 8.22916 | H78: BABSN 2019-1A DR 15-Apr-2035 | I78: 49414 | J78: 391.161 | K78: 1 | L78: -3.380264 | M78: 43CH;IG CLO Strategy | N78: 06759JAW8 | O78: Barings | P78: 5.891748 | Q78: 385.47442 | R78: 2021 | T78: BBB | U78: 4<6 | V78: 7+
A79: SBL_404_404 | B79: 06762JAG8 | C79: 250000 | D79: 251655 | E79: 231875 | F79: BABSN 2018 3X | G79: 7.72916 | H79: BABSN 2021-2A D 15-Jul-2034 | I79: 49140 | J79: 341.161 | K79: 1 | L79: 6.676434 | M79: 43CH;IG CLO Strategy | N79: 06762JAG8 | O79: Barings | P79: 5.9726698 | Q79: 327.47682 | R79: 2021 | T79: BBB | U79: 4<6 | V79: 7+
A80: SBL_404_404 | B80: 06762JAG8 | C80: 1602024 | D80: 1612629.4 | E80: 1481872.2 | F80: BABSN 2018 3X | G80: 7.72916 | H80: BABSN 2021-2A D 15-Jul-2034 | I80: 49140 | J80: 341.161 | K80: 1 | L80: 6.676434 | M80: 43CH;IG CLO Strategy | N80: 06762JAG8 | O80: Barings | P80: 5.9726698 | Q80: 327.47682 | R80: 2021 | T80: BBB | U80: 4<6 | V80: 7+
A81: SBL_404_404 | B81: 06763FAD2 | C81: 6925356 | D81: 6951464.6 | E81: 6925356 | F81: BABSN 2018 3X | G81: 7.37549 | H81: BABSN 2023-2A C 20-Jul-2036 | I81: 49876 | J81: 305 | K81: 1 | L81: 7.374497 | M81: 43CH;IG CLO Strategy | N81: 06763FAD2 | O81: Barings | P81: 7.0784279 | Q81: 298.2324 | R81: 2023 | T81: A | U81: 6<8 | V81: 7+
... A110: SBL_404_404 | B110: 09077CAY8 | C110: 4400000 | D110: 4412430 | E110: 4400000 | F110: Birch Grove CLO | G110: 7.51755 | H110: BGCLO 2022-4A D1R 15-Jul-2037 | I110: 50236 | J110: 320 | K110: 1 | L110: 7.516476 | M110: 43CH;IG CLO Strategy | N110: 09077CAY8 | O110: Birch Grove Capital | P110: 8.8606201 | Q110: 315.64964 | R110: 2024 | T110: BBB | U110: 8<10 | V110: 7+
A111: SBL_404_404 | B111: 09077FAU9 | C111: 4330000 | D111: 4356196.5 | E111: 4330000 | F111: Birch Grove CLO | G111: 7.52087 | H111: BGCLO 2023-6A D1R 20-Jul-2038 | I111: 50606 | J111: 315 | L111: 7.512195 | M111: 43CH;IG CLO Strategy | N111: 09077FAU9 | O111: Birch Grove Capital | P111: 9.6493194 | Q111: 304.51114 | R111: 2025 | T111: BBB | U111: 8<10 | V111: 7+
A112: SBL_404_404 | B112: 09077LAU6 | C112: 3000000 | D112: 3011019 | E112: 3000000 | F112: Birch Grove CLO | G112: 7.47549 | H112: BGCLO 2021-2A D1R 19-Oct-2037 | I112: 50332 | J112: 315 | K112: 1 | L112: 7.4745 | M112: 43CH;IG CLO Strategy | N112: 09077LAU6 | O112: Birch Grove Capital | P112: 9.070457 | Q112: 309.50006 | R112: 2024 | T112: BBB | U112: 8<10 | V112: 7+
A113: SBL_404_404 | B113: 09090MAJ2 | C113: 14000000 | D113: 14043652 | E113: 14000000 | F113: Birch Grove CLO | G113: 7.09284 | H113: BGCLO 2025-12A D1 22-Apr-2038 | I113: 50517 | J113: 275 | K113: 1 | L113: 7.084381 | M113: 43CH;IG CLO Strategy | N113: 09090MAJ2 | O113: Birch Grove Capital | P113: 9.4552336 | Q113: 270.3358 | R113: 2025 | T113: BBB | U113: 8<10 | V113: 7+
A114: SBL_404_404 | B114: 09261MAY2 | C114: 7817058 | D114: 7828494.4 | E114: 7817058 | F114: Blackrock CLO Ltd | G114: 7.27549 | H114: BLKMM 2021-6A CR 20-Apr-2037 | I114: 50150 | J114: 295 | K114: 1 | L114: 7.274523 | M114: 43CH;IG CLO Strategy | N114: 09261MAY2 | O114: BlackRock Capital Investment Advisors | P114: 7.4787455 | Q114: 292.40153 | R114: 2025 | T114: A | U114: 6<8 | V114: 7+
A115: SBL_404_404 | B115: 09262WAE3 | C115: 4000000 | D115: 4011808 | E115: 4000000 | F115: BlackRock DLF IX-L CLO, LP | G115: 8.42549 | H115: BLKMM 2023-2A C 20-Oct-2033 | I115: 48872 | J115: 410 | K115: 1 | L115: 8.4242 | M115: 43CH;IG CLO Strategy | N115: 09262WAE3 | O115: BlackRock Capital Investment Advisors | P115: 3.1294006 | Q115: 398.82862 | R115: 2023 | T115: A | U115: 2<4 | V115: 7+
A116: SBL_404_404 | B116: 09290EAL3 | C116: 14700000 | D116: 14516441 | E116: 14700000 | F116: Blackrock CLO Ltd | G116: 6.66755 | H116: BLKMM 2022-1A CR 15-Jan-2038 | I116: 50420 | J116: 235 | K116: 1 | L116: 6.666706 | M116: 43CH;IG CLO Strategy | N116: 09290EAL3 | O116: BlackRock Capital Investment Advisors | P116: 8.2323538 | Q116: 254.04246 | R116: 2024 | T116: A | U116: 8<10 | V116: 6<7
A117: SBL_404_404 | B117: 09290EAN9 | C117: 16400000 | D117: 16163233 | E117: 16400000 | F117: Blackrock CLO Ltd | G117: 8.21755 | H117: BLKMM 2022-1A DR 15-Jan-2038 | I117: 50420 | J117: 390 | K117: 1 | L117: 8.216268 | M117: 43CH;IG CLO Strategy | N117: 09290EAN9 | O117: BlackRock Capital Investment Advisors | P117: 8.7429403 | Q117: 412.36306 | R117: 2024 | T117: BBB | U117: 8<10 | V117: 7+
A118: SBL_404_404 | B118: 09631BAJ2 | C118: 4290000 | D118: 4283063.1 | E118: 4257825 | F118: BlueMountain CLO Ltd | G118: 7.5871 | H118: BLUEM 2021-31A D 19-Apr-2034 | I118: 49053 | J118: 326.161 | K118: 1 | L118: 7.689329 | M118: 43CH;IG CLO Strategy | N118: 09631BAJ2 | O118: Sound Point Capital Management | P118: 6.0357852 | Q118: 329.24995 | R118: 2021 | T118: BBB | U118: 6<8 | V118: 7+
A119: SBL_404_404 | B119: 12481HAW5 | C119: 41840107 | D119: 41918934 | E119: 41840107 | F119: CBAM Ltd | G119: 8.08401 | H119: CBAM 2017-3A DR 17-Jul-2034 | I119: 49142 | J119: 376.161 | K119: 1 | L119: 8.203324 | M119: 43CH;IG CLO Strategy | N119: 12481HAW5 | O119: Carlyle CLO Management | P119: 6.1117026 | Q119: 372.16351 | R119: 2021 | T119: BBB | U119: 6<8 | V119: 7+
A120: SBL_404_404 | B120: 12481KAY4 | C120: 25827082 | D120: 25878220 | E120: 25827082 | F120: CBAM Ltd | G120: 7.93401 | H120: CBAM 2017-2A DR 17-Jul-2034 | I120: 49142 | J120: 361.161 | K120: 1 | L120: 8.051073 | M120: 43CH;IG CLO Strategy | N120: 12481KAY4 | O120: Carlyle CLO Management | P120: 5.9506013 | Q120: 356.92804 | R120: 2021 | T120: BBB | U120: 4<6 | V120: 7+
A121: SBL_404_404 | B121: 12481QAJ4 | C121: 49875000 | D121: 49927468 | E121: 49875000 | F121: CBAMR Ltd | G121: 6.33401 | H121: CBAMR 2018-5A C 17-Apr-2031 | I121: 47955 | J121: 201.161 | K121: 1 | L121: 6.426961 | M121: 43CH;IG CLO Strategy | N121: 12481QAJ4 | O121: Carlyle CLO Management | P121: 2.6908278 | Q121: 196.60919 | R121: 2018 | T121: AA | U121: 2<4 | V121: 6<7
A122: SBL_103_103 | B122: 12481QAL9 | C122: 9375000 | D122: 9416437.5 | E122: 9375000 | F122: CBAMR Ltd | G122: 7.08401 | H122: CBAMR 2018-5A D 17-Apr-2031 | I122: 47955 | J122: 276.161 | K122: 1 | L122: 7.188124 | M122: 43CH;IG CLO Strategy | N122: 12481QAL9 | O122: Carlyle CLO Management | P122: 3.0286459 | Q122: 259.61456 | R122: 2018 | T122: BBB | U122: 2<4 | V122: 7+
A123: SBL_404_404 | B123: 12482JAE0 | C123: 5250000 | D123: 5266899.8 | E123: 5250000 | F123: CBAM Ltd | G123: 6.1871 | H123: CBAM 2018-7A B2 20-Jul-2031 | I123: 48049 | J123: 186.161 | K123: 1 | L123: 6.272555 | M123: 43CH;IG CLO Strategy | N123: 12482JAE0 | O123: Carlyle CLO Management | P123: 2.509138 | Q123: 171.24414 | R123: 2018 | T123: AAA | U123: 2<4 | V123: 6<7
... A126: SBL_404_404 | B126: 12482JAJ9 | C126: 25125000 | D126: 25175401 | E126: 25125000 | F126: CBAM Ltd | G126: 7.3871 | H126: CBAM 2018-7A D 20-Jul-2031 | I126: 48049 | J126: 306.161 | K126: 1 | L126: 7.489003 | M126: 43CH;IG CLO Strategy | N126: 12482JAJ9 | O126: Carlyle CLO Management | P126: 3.2730262 | Q126: 298.87448 | R126: 2018 | T126: BBB | U126: 2<4 | V126: 7+
A127: SBL_404_404 | B127: 12516EAL5 | C127: 10000000 | D127: 10010670 | E127: 10000000 | F127: CBAMR Ltd | G127: 7.28109 | H127: CBAMR 2017-4A D1R 31-Mar-2038 | I127: 50495 | J127: 300 | L127: 7.272195 | M127: 43CH;IG CLO Strategy | N127: 12516EAL5 | O127: Carlyle CLO Management | P127: 9.5236411 | Q127: 296.80929 | R127: 2025 | T127: BBB | U127: 8<10 | V127: 7+
A128: SBL_404_404 | B128: 12516GAJ5 | C128: 3800000 | D128: 3806513.2 | E128: 3800000 | F128: CBAMR Ltd | G128: 8.03997 | H128: CBAMR 2018-6A D1R2 31-Mar-2038 | I128: 50495 | J128: 375 | K128: 1 | L128: 8.032201 | M128: 43CH;IG CLO Strategy | N128: 12516GAJ5 | O128: Carlyle CLO Management | P128: 9.264825 | Q128: 372.10684 | R128: 2025 | T128: BBB | U128: 8<10 | V128: 7+
A129: SBL_404_404 | B129: 12516GAL0 | C129: 1140000 | D129: 1163243.5 | E129: 1140000 | F129: CBAMR Ltd | G129: 10.28997 | H129: CBAMR 2018-6A D2R2 31-Mar-2038 | I129: 50495 | J129: 600 | K129: 1 | L129: 10.276665 | M129: 43CH;IG CLO Strategy | N129: 12516GAL0 | O129: Carlyle CLO Management | P129: 9.5529454 | Q129: 567.33707 | R129: 2025 | T129: BBB | U129: 8<10 | V129: 7+
A130: SBL_404_404 | B130: 12529QAJ8 | C130: 5675000 | D130: 5629032.5 | E130: 5648895 | F130: CFIP CLO Ltd | G130: 8.1271 | H130: CFIP 2021-1A D 20-Jan-2035 | I130: 49329 | J130: 380.161 | K130: 1 | L130: 8.140431 | M130: 43CH;IG CLO Strategy | N130: 12529QAJ8 | O130: CFI Partners | P130: 6.4179559 | Q130: 395.84945 | R130: 2021 | T130: BBB | U130: 6<8 | V130: 7+
A131: SBL_404_404 | B131: 12529QAJ8 | C131: 910000 | D131: 902629 | E131: 908920.09 | F131: CFIP CLO Ltd | G131: 8.1271 | H131: CFIP 2021-1A D 20-Jan-2035 | I131: 49329 | J131: 380.161 | K131: 1 | L131: 8.140431 | M131: 43CH;IG CLO Strategy | N131: 12529QAJ8 | O131: CFI Partners | P131: 6.4179559 | Q131: 395.84945 | R131: 2021 | T131: BBB | U131: 6<8 | V131: 7+
A132: SBL_404_404 | B132: 12529QAJ8 | C132: 1870000 | D132: 1854853 | E132: 1865728.2 | F132: CFIP CLO Ltd | G132: 8.1271 | H132: CFIP 2021-1A D 20-Jan-2035 | I132: 49329 | J132: 380.161 | K132: 1 | L132: 8.140431 | M132: 43CH;IG CLO Strategy | N132: 12529QAJ8 | O132: CFI Partners | P132: 6.4179559 | Q132: 395.84945 | R132: 2021 | T132: BBB | U132: 6<8 | V132: 7+
A133: SBL_404_404 | B133: 12550ABM7 | C133: 6250000 | D133: 6289037.5 | E133: 6250000 | F133: CIFC Funding Ltd | G133: 7.5724 | H133: CIFC 2014-5A D1R3 17-Jul-2037 | I133: 50238 | J133: 325 | K133: 1 | L133: 7.571299 | M133: 43CH;IG CLO Strategy | N133: 12550ABM7 | O133: CIFC Asset Management | P133: 8.1791669 | Q133: 314.99478 | R133: 2024 | T133: BBB | U133: 8<10 | V133: 7+
A134: SBL_404_404 | B134: 12550ABP0 | C134: 1800000 | D134: 1817402.4 | E134: 1827000 | F134: CIFC Funding Ltd | G134: 9.2224 | H134: CIFC 2014-5A D2R3 17-Jul-2037 | I134: 50238 | J134: 490 | K134: 1 | L134: 8.943765 | M134: 43CH;IG CLO Strategy | N134: 12550ABP0 | O134: CIFC Asset Management | P134: 8.4638889 | Q134: 473.93627 | R134: 2024 | T134: BBB | U134: 8<10 | V134: 7+
A135: SBL_404_404 | B135: 12555XAY7 | C135: 1000000 | D135: 1008521 | E135: 1000000 | F135: CIFC Funding Ltd | G135: 7.61777 | H135: CIFC 2019-6A D1R 16-Jul-2037 | I135: 50237 | J135: 330 | K135: 1 | L135: 7.616665 | M135: 43CH;IG CLO Strategy | N135: 12555XAY7 | O135: CIFC Asset Management | P135: 8.4375997 | Q135: 316.6926 | R135: 2024 | T135: BBB | U135: 8<10 | V135: 7+
A136: SBL_404_404 | B136: 12560EAU0 | C136: 5375000 | D136: 5401165.5 | E136: 5375000 | F136: CIFC Funding Ltd | G136: 7.6871 | H136: CIFC 2020-3A DR 20-Oct-2034 | I136: 49237 | J136: 336.161 | K136: 1 | L136: 7.794699 | M136: 43CH;IG CLO Strategy | N136: 12560EAU0 | O136: CIFC Asset Management | P136: 6.253337 | Q136: 326.49885 | R136: 2021 | T136: BBB | U136: 6<8 | V136: 7+
A137: SBL_404_404 | B137: 12562RAS4 | C137: 6300000 | D137: 6323643.9 | E137: 6300000 | F137: CIFC Funding Ltd | G137: 7.11755 | H137: CIFC 2020-4A DR 15-Jan-2040 | I137: 51150 | J137: 280 | K137: 1 | L137: 7.116591 | M137: 43CH;IG CLO Strategy | N137: 12562RAS4 | O137: CIFC Asset Management | P137: 9.1877874 | Q137: 274.52921 | R137: 2024 | T137: BBB | U137: 8<10 | V137: 7+
A138: SBL_404_404 | B138: 12563EAU7 | C138: 3000000 | D138: 3016140 | E138: 3000000 | F138: CIFC Funding Ltd | G138: 7.46846 | H138: CIFC 2021-1A D1R 25-Jul-2037 | I138: 50246 | J138: 315 | K138: 1 | L138: 7.467403 | M138: 43CH;IG CLO Strategy | N138: 12563EAU7 | O138: CIFC Asset Management | P138: 8.8329233 | Q138: 306.84251 | R138: 2024 | T138: BBB | U138: 8<10 | V138: 7+
A139: SBL_404_404 | B139: 12564DAG9 | C139: 510000 | D139: 512373.03 | E139: 508087.5 | F139: CIFC Funding Ltd | G139: 7.57916 | H139: CIFC 2021-3A D 15-Jul-2036 | I139: 49871 | J139: 326.161 | K139: 1 | L139: 7.992126 | M139: 43CH;IG CLO Strategy | N139: 12564DAG9 | O139: CIFC Asset Management | P139: 6.0957346 | Q139: 316.75027 | R139: 2021 | T139: BBB | U139: 6<8 | V139: 7+
... A148: SBL_404_404 | B148: 12572VAG9 | C148: 10000000 | D148: 10017600 | E148: 10000000 | F148: CIFC Funding 2018-IV Ltd | G148: 6.77618 | H148: CIFC 2025-1A D1 23-Apr-2038 | I148: 50518 | J148: 250 | K148: 1 | L148: 6.76689 | M148: 43CH;IG CLO Strategy | N148: 12572VAG9 | O148: CIFC Asset Management | P148: 9.403847 | Q148: 247.26418 | R148: 2025 | T148: BBB | U148: 8<10 | V148: 6<7
A149: SBL_404_404 | B149: 13875MAG1 | C149: 1000000 | D149: 1001911 | E149: 971250 | F149: Canyon CLO | G149: 7.62916 | H149: CANYC 2021-3A D 15-Jul-2034 | I149: 49140 | J149: 331.161 | K149: 1 | L149: 8.226153 | M149: 43CH;IG CLO Strategy | N149: 13875MAG1 | O149: Canyon CLO Advisors | P149: 6.0435283 | R149: 2021 | T149: BBB | U149: 6<8 | V149: 7+
A150: SBL_404_404 | B150: 13876XAN1 | C150: 2434928 | D150: 2439678.5 | E150: 2434928 | F150: Canyon Capital CLO Ltd | G150: 7.92916 | H150: CANYC 2021-2A D 15-Apr-2034 | I150: 49049 | J150: 361.161 | K150: 1 | L150: 8.021602 | M150: 43CH;IG CLO Strategy | N150: 13876XAN1 | O150: Canyon CLO Advisors | P150: 5.7851951 | Q150: 356.83061 | R150: 2021 | T150: BBB | U150: 4<6 | V150: 7+
A151: SBL_404_404 | B151: 13876XAN1 | C151: 520000 | D151: 521014.52 | E151: 523604.64 | F151: Canyon Capital CLO Ltd | G151: 7.92916 | H151: CANYC 2021-2A D 15-Apr-2034 | I151: 49049 | J151: 361.161 | K151: 1 | L151: 8.021602 | M151: 43CH;IG CLO Strategy | N151: 13876XAN1 | O151: Canyon CLO Advisors | P151: 5.7851951 | Q151: 356.83061 | R151: 2021 | T151: BBB | U151: 4<6 | V151: 7+
A152: SBL_404_404 | B152: 13876XAN1 | C152: 1180000 | D152: 1182302.2 | E152: 1183133.1 | F152: Canyon Capital CLO Ltd | G152: 7.92916 | H152: CANYC 2021-2A D 15-Apr-2034 | I152: 49049 | J152: 361.161 | K152: 1 | L152: 8.021602 | M152: 43CH;IG CLO Strategy | N152: 13876XAN1 | O152: Canyon CLO Advisors | P152: 5.7851951 | Q152: 356.83061 | R152: 2021 | T152: BBB | U152: 4<6 | V152: 7+
A153: SBL_404_404 | B153: 13876XAN1 | C153: 1709999 | D153: 1713335.2 | E153: 1713369.8 | F153: Canyon Capital CLO Ltd | G153: 7.92916 | H153: CANYC 2021-2A D 15-Apr-2034 | I153: 49049 | J153: 361.161 | K153: 1 | L153: 8.021602 | M153: 43CH;IG CLO Strategy | N153: 13876XAN1 | O153: Canyon CLO Advisors | P153: 5.7851951 | Q153: 356.83061 | R153: 2021 | T153: BBB | U153: 4<6 | V153: 7+
A154: SBL_404_404 | B154: 13887TBA4 | C154: 3500000 | D154: 3531353 | E154: 3500000 | F154: Canyon Capital CLO Ltd | G154: 7.96755 | H154: CANYC 2019-1A D1RR 15-Jul-2037 | I154: 50236 | J154: 365 | K154: 1 | L154: 7.966344 | M154: 43CH;IG CLO Strategy | N154: 13887TBA4 | O154: Canyon CLO Advisors | P154: 8.7783984 | Q154: 351.20959 | R154: 2024 | T154: BBB | U154: 8<10 | V154: 7+
A155: SBL_404_404 | B155: 13887TBC0 | C155: 3200000 | D155: 3229504 | E155: 3248000 | F155: Canyon Capital CLO Ltd | G155: 9.46755 | H155: CANYC 2019-1A D2RR 15-Jul-2037 | I155: 50236 | J155: 515 | K155: 1 | L155: 9.187351 | M155: 43CH;IG CLO Strategy | N155: 13887TBC0 | O155: Canyon CLO Advisors | P155: 9.1088964 | Q155: 500.24838 | R155: 2024 | T155: BBB | U155: 8<10 | V155: 7+
A156: SBL_404_404 | B156: 138919AJ4 | C156: 12000000 | D156: 12068196 | E156: 12000000 | F156: Canyon CLO | G156: 7.03612 | H156: CANYC 2025-1A D1 15-Apr-2038 | I156: 50510 | J156: 275 | K156: 1 | L156: 7.027919 | M156: 43CH;IG CLO Strategy | N156: 138919AJ4 | O156: Canyon Capital Advisors | P156: 9.4424039 | Q156: 266.67059 | R156: 2025 | T156: BBB | U156: 8<10 | V156: 7+
A157: SBL_404_404 | B157: 14074EAJ0 | C157: 3900000 | D157: 3925119.9 | E157: 3900000 | F157: Captree Park CLO Ltd | G157: 6.62549 | H157: CPTPK 2024-1A C 20-Jul-2037 | I157: 50241 | J157: 230 | K157: 1 | L157: 6.624688 | M157: 43CH;IG CLO Strategy | N157: 14074EAJ0 | O157: Blackstone CLO Management | P157: 8.2162903 | Q157: 220.09591 | R157: 2024 | T157: A | U157: 8<10 | V157: 6<7
A158: SBL_404_404 | B158: 14074EAL5 | C158: 3200000 | D158: 3224432 | E158: 3200000 | F158: Captree Park CLO Ltd | G158: 7.57549 | H158: CPTPK 2024-1A D 20-Jul-2037 | I158: 50241 | J158: 325 | K158: 1 | L158: 7.574443 | M158: 43CH;IG CLO Strategy | N158: 14074EAL5 | O158: Blackstone CLO Management | P158: 8.8070333 | Q158: 313.43341 | R158: 2024 | T158: BBB | U158: 8<10 | V158: 7+
A159: SBL_404_404 | B159: 14311UBG2 | C159: 6400000 | D159: 6412595.2 | E159: 6400000 | F159: Carlyle Global Market Strategies | G159: 7.17549 | H159: CGMS 2016-3A DRRR 20-Jul-2034 | I159: 49145 | J159: 285 | K159: 1 | L159: 7.174554 | M159: 43CH;IG CLO Strategy | N159: 14311UBG2 | O159: Carlyle CLO Management | P159: 5.7513621 | Q159: 280.77001 | R159: 2024 | T159: BBB | U159: 4<6 | V159: 7+
A160: SBL_103_103 | B160: 143120AG8 | C160: 7541000 | D160: 7576050.6 | E160: 7543262.3 | F160: Carlyle Global Market Strategies | G160: 7.77916 | H160: CGMS 2021-8A D 15-Oct-2034 | I160: 49232 | J160: 346.161 | K160: 1 | L160: 7.444584 | M160: 43CH;IG CLO Strategy | N160: 143120AG8 | O160: Carlyle CLO Management | P160: 6.2373314 | Q160: 336.90265 | R160: 2021 | T160: BBB | U160: 6<8 | V160: 7+
...

Sheet Sec_Master
A1: cusip | B1: Row Labels | C1: WAL | D1: Next Payment Date | E1: Non-Call Date | F1: Par Sub | G1: Implied DM | H1: Market Price | I1: Manager | J1: Issue Date | K1: SP Rating | L1: Moody Rating | M1: Fitch Rating | N1: KBRA Rating | O1: DBRS Rating | P1: Issuer Name | Q1: Vintage | R1: Collateral Type | S1: NRSRO Rating | T1: NRSRO | U1: Tranche Rating
A2: 00119AAG0 | B2: 00119AAG0 | D2: 45953 | E2: 46591 | I2: AGL CLO Credit Management | J2: 20230511 | K2: NR | L2: NR | M2: A | N2: NR | O2: NR | P2: AGL CLO Ltd. | S2: A | T2: Fitch | U2: A
A3: 00119AAJ4 | B3: 00119AAJ4 | D3: 45953 | E3: 46591 | I3: AGL CLO Credit Management | J3: 20230511 | K3: NR | L3: NR | M3: BBB- | N3: NR | O3: NR | P3: AGL CLO Ltd. | S3: BBB- | T3: Fitch | U3: BBB
A4: 00119AAS4 | B4: 00119AAS4 | C4: 9.1695377 | D4: 45953 | E4: 46591 | F4: 17.880402 | G4: 202.15609 | H4: 100.9195 | I4: AGL CLO Credit Management | J4: 20250523 | K4: NR | L4: NR | M4: A | N4: NR | O4: NR | P4: AGL CLO Ltd. | Q4: 2025 | S4: A | T4: Fitch | U4: A
A5: 00119AAU9 | B5: 00119AAU9 | C5: 9.7045333 | D5: 45953 | E5: 46591 | F5: 11.871651 | G5: 337.95476 | H5: 99.4267 | I5: AGL CLO Credit Management | J5: 20250523 | K5: NR | L5: NR | M5: BBB- | N5: NR | O5: NR | P5: AGL CLO Ltd. | Q5: 2025 | S5: BBB- | T5: Fitch | U5: BBB
A6: 00120NAG9 | B6: 00120NAG9 | I6: AGL CLO Credit Management | J6: 20230613 | K6: NR | L6: NR | M6: BBB- | N6: NR | O6: NR | P6: AGL CLO Ltd. | S6: BBB- | T6: Fitch | U6: BBB
A7: 00120NAU8 | B7: 00120NAU8 | C7: 9.6224766 | F7: 12.445965 | G7: 282.97731 | H7: 100.494 | I7: AGL CLO Credit Management | J7: 20250625 | K7: NR | L7: NR | M7: BBB | N7: NR | O7: NR | P7: AGL CLO Ltd. | Q7: 2025 | S7: BBB | T7: Fitch | U7: BBB
A8: 001210AJ2 | B8: 001210AJ2 | D8: 45951 | E8: 46589 | I8: AGL CLO Credit Management | J8: 20220627 | K8: NR | L8: NR | M8: BBB- | N8: NR | O8: NR | P8: AGL CLO 19 Ltd | S8: BBB- | T8: Fitch | U8: BBB
A9: 001210AY9 | B9: 001210AY9 | C9: 9.2339746 | D9: 45951 | E9: 46589 | F9: 11.770896 | G9: 299.10923 | H9: 100.4057 | I9: AGL CLO Credit Management | J9: 20250711 | K9: NR | L9: NR | M9: BBB- | N9: NR | O9: NR | P9: AGL CLO 19 Ltd | Q9: 2025 | S9: BBB- | T9: Fitch | U9: BBB
A10: 01750WAJ8 | B10: 01750WAJ8 | D10: 45950 | E10: 46588 | I10: AXA Investment Managers | J10: 20210628 | K10: NR | L10: Baa3 | M10: NR | N10: NR | O10: NR | P10: Allegro CLO Ltd | S10: Baa3 | T10: Moody's | U10: BBB
A11: 03328QCC3 | B11: 03328QCC3 | C11: 0 | D11: 45952 | E11: 45769 | G11: 298.47644 | H11: 100.375 | I11: Anchorage Collateral Management | J11: 20250811 | K11: NR | L11: NR | M11: BBB- | N11: NR | O11: NR | P11: Anchorage Capital CLO LTD | Q11: 2025 | S11: BBB- | T11: Fitch | U11: BBB
A12: 03770JAA8 | B12: 03770JAA8 | I12: CVC Credit Partners | J12: 20230327 | K12: NR | L12: NR | M12: BB | N12: NR | O12: NR | P12: Apidos CLO Ltd | S12: BB | T12: Fitch | U12: BB
A13: 03770JAG5 | B13: 03770JAG5 | C13: 10.359942 | F13: 8.1656529 | G13: 516.99473 | H13: 101.2028 | I13: CVC Credit Partners | J13: 20250618 | K13: NR | L13: NR | M13: BB+ | N13: NR | O13: NR | P13: Apidos CLO Ltd | Q13: 2025 | S13: BB+ | T13: Fitch | U13: BB
A14: 03770MAG8 | B14: 03770MAG8 | D14: 45956 | E14: 46594 | I14: CVC Credit Partners | J14: 20230525 | K14: NR | L14: NR | M14: BBB- | N14: NR | O14: NR | P14: Apidos CLO Ltd | S14: BBB- | T14: Fitch | U14: BBB
A15: 03770MAU7 | B15: 03770MAU7 | C15: 9.7105044 | D15: 45956 | E15: 46594 | F15: 12.197847 | G15: 282.17599 | H15: 100.1923 | I15: CVC Credit Partners | J15: 20250702 | K15: NR | L15: NR | M15: BBB- | N15: NR | O15: NR | P15: Apidos CLO Ltd | Q15: 2025 | S15: BBB- | T15: Fitch | U15: BBB
A16: 039937BA4 | B16: 039937BA4 | C16: 0 | D16: 45950 | E16: 45402 | G16: 293.33317 | H16: 100.3889 | I16: Ares CLO Management | J16: 20250807 | K16: NR | L16: NR | M16: BBB- | N16: NR | O16: NR | P16: ARES CLO Ltd | Q16: 2025 | S16: BBB- | T16: Fitch | U16: BBB
A17: 04039BAG7 | B17: 04039BAG7 | C17: 9.6083371 | F17: 12 | G17: 318.24635 | H17: 100.3889 | I17: Arini Loan Management US | J17: 20250820 | K17: BBB- | L17: NR | M17: NR | N17: NR | O17: NR | P17: Arini US CLO Limited | Q17: 2025 | S17: BBB- | T17: SP | U17: BBB
A18: 04942CAL0 | B18: 04942CAL0 | D18: 45950 | E18: 44915 | F18: 13.115368 | I18: Crescent Capital Group | J18: 20190614 | K18: NR | L18: Baa3 | M18: NR | N18: NR | O18: NR | P18: Atlas Senior Loan Fund LTD | S18: Baa3 | T18: Moody's | U18: BBB
A19: 05553MAE1 | B19: 05553MAE1 | I19: Blackstone Private Credit Fund | J19: 20210629 | K19: NR | L19: A2 | M19: NR | N19: NR | O19: NR | P19: BCRED BSL Static CLO Ltd | S19: A2 | T19: Moody's | U19: A
A20: 05553MAG6 | B20: 05553MAG6 | I20: Blackstone Private Credit Fund | J20: 20210629 | K20: NR | L20: Baa3 | M20: NR | N20: NR | O20: NR | P20: BCRED BSL Static CLO Ltd | S20: Baa3 | T20: Moody's | U20: BBB
A21: 05684GAJ5 | B21: 05684GAJ5 | C21: 7.6345538 | D21: 45948 | E21: 45856 | F21: 12.146295 | H21: 100.005 | I21: Bain Capital Credit U.S. CLO Manager II | J21: 20230621 | K21: NR | L21: NR | M21: BBB- | N21: NR | O21: NR | P21: Bain Capital Credit CLO, Limit | S21: BBB- | T21: Fitch | U21: BBB
A22: 05875AAQ1 | B22: 05875AAQ1 | C22: 9.7609555 | D22: 45945 | E22: 46583 | F22: 11.965117 | G22: 292.44529 | H22: 100.1764 | I22: Ballyrock Investment Advisors | J22: 20250711 | K22: BBB- | L22: NR | M22: NR | N22: NR | O22: NR | P22: Ballyrock Ltd | Q22: 2025 | S22: BBB- | T22: SP | U22: BBB
A23: 05876GAJ3 | B23: 05876GAJ3 | C23: 9.712812 | D23: 46047 | E23: 46585 | F23: 12 | G23: 286.84214 | H23: 100.1116 | I23: Ballyrock Investment Advisors | J23: 20250717 | K23: BBB- | L23: NR | M23: NR | N23: NR | O23: NR | P23: Ballyrock Ltd | Q23: 2025 | S23: BBB- | T23: SP | U23: BBB
A24: 05876UAE3 | B24: 05876UAE3 | H24: 100.2639 | I24: Ballyrock Ltd | J24: 20250904 | K24: BBB | L24: NR | M24: NR | N24: NR | O24: NR | P24: Ballyrock Ltd | Q24: 2025 | S24: BBB | T24: SP | U24: BBB
A25: 09077FAU9 | B25: 09077FAU9 | C25: 9.6493194 | D25: 46042 | E25: 46575 | F25: 12.439622 | G25: 304.51114 | H25: 100.605 | I25: Birch Grove Capital | J25: 20250707 | K25: NR | L25: NR | M25: BBB- | N25: NR | O25: NR | P25: Birch Grove CLO Ltd. | Q25: 2025 | S25: BBB- | T25: Fitch | U25: BBB
A26: 12481NAE2 | B26: 12481NAE2 | D26: 46037 | E26: 46583 | I26: CBAM CLO Management | J26: 20171206 | K26: NR | L26: Aa1 | M26: NR | N26: NR | O26: NR | P26: CBAMR Ltd | S26: Aa1 | T26: Moody's | U26: AA
A27: 12481NAF9 | B27: 12481NAF9 | D27: 46037 | E27: 46583 | I27: CBAM CLO Management | J27: 20171206 | K27: NR | L27: Baa2 | M27: NR | N27: NR | O27: NR | P27: CBAMR Ltd | S27: Baa2 | T27: Moody's | U27: BBB
A28: 12481PAA5 | B28: 12481PAA5 | D28: 46037 | E28: 46583 | I28: CBAM CLO Management | J28: 20171206 | K28: NR | L28: Ba3 | M28: NR | N28: NR | O28: NR | P28: CBAMR Ltd | S28: Ba3 | T28: Moody's | U28: BB
A29: 12509VAN2 | B29: 12509VAN2 | C29: 1.8178755 | D29: 45950 | E29: 45127 | F29: 12.490974 | G29: 438.95855 | H29: 90.3116 | I29: CBAM Partners | J29: 20210720 | K29: NR | L29: NR | M29: NR | N29: BBB- | O29: NR | P29: CBAM CLO Management | Q29: 2021 | S29: BBB- | T29: KBRA | U29: BBB
A30: 12510TAE4 | B30: 12510TAE4 | C30: 2.0454133 | D30: 45950 | E30: 45311 | F30: 10.888076 | G30: 554.98042 | H30: 87.1538 | I30: CBAM Partners | J30: 20211119 | K30: NR | L30: NR | M30: NR | N30: BBB- | O30: NR | P30: CBAM CLO Management | Q30: 2021 | S30: BBB- | T30: KBRA | U30: BBB
A31: 12511AAG9 | B31: 12511AAG9 | C31: 2.9825431 | D31: 45950 | E31: 44911 | F31: 15.174783 | G31: 323.02062 | H31: 88.4144 | I31: CBAM Partners | J31: 20201216 | K31: NR | L31: NR | M31: NR | N31: BBB- | O31: NR | P31: CBAM CLO Management | Q31: 2020 | S31: BBB- | T31: KBRA | U31: BBB
A32: 12516EAL5 | B32: 12516EAL5 | C32: 9.5236411 | D32: 46037 | E32: 46583 | F32: 13.427808 | G32: 296.80929 | H32: 100.1067 | I32: CBAM CLO Management | J32: 20250627 | K32: NR | L32: NR | M32: BBB+ | N32: NR | O32: NR | P32: CBAMR Ltd | Q32: 2025 | S32: BBB+ | T32: Fitch | U32: BBB
A33: 12516JAA8 | B33: 12516JAA8 | C33: 10.153624 | D33: 46037 | E33: 46583 | F33: 8.4523949 | G33: 579.82288 | H33: 101.1726 | I33: CBAM CLO Management | J33: 20250627 | K33: NR | L33: NR | M33: BB- | N33: NR | O33: NR | P33: CBAMR Ltd | Q33: 2025 | S33: BB- | T33: Fitch | U33: BB
A34: 14315BAG1 | B34: 14315BAG1 | D34: 45945 | E34: 43845 | I34: Carlyle CLO Management | J34: 20171130 | K34: NR | L34: A3 | M34: NR | N34: NR | O34: NR | P34: Carlyle Global Market Strategi | S34: A3 | T34: Moody's | U34: A
A35: 14315DAG7 | B35: 14315DAG7 | C35: 0.93416698 | D35: 45945 | E35: 45031 | F35: 14.153221 | G35: 270.60899 | H35: 96.347 | I35: Carlyle CLO Management | J35: 20210331 | K35: NR | L35: NR | M35: NR | N35: BBB | O35: NR | P35: Carlyle Global Market Strategi | Q35: 2021 | S35: BBB | T35: KBRA | U35: BBB
A36: 14315LAJ3 | B36: 14315LAJ3 | D36: 45957 | E36: 44039 | I36: Carlyle CLO Management | J36: 20180612 | K36: BBB- | L36: NR | M36: NR | N36: NR | O36: NR | P36: Carlyle Global Market Strategi | S36: BBB- | T36: SP | U36: BBB
A37: 26243EAC5 | B37: 26243EAC5 | D37: 45945 | E37: 46030 | I37: PGIM | J37: 20180111 | K37: NR | L37: A1 | M37: NR | N37: NR | O37: NR | P37: Dryden Senior Loan Fund | S37: A1 | T37: Moody's | U37: A
A38: 26246GAW3 | B38: 26246GAW3 | C38: 0 | G38: 309.69888 | H38: 100.375 | I38: PGIM | J38: 20250808 | K38: NR | L38: NR | M38: BBB- | N38: NR | O38: NR | P38: Dryden Senior Loan Fund | Q38: 2025 | S38: BBB- | T38: Fitch | U38: BBB
A39: 26253QAG6 | B39: 26253QAG6 | D39: 45945 | E39: 46492 | I39: PGIM | J39: 20230328 | K39: BBB- | L39: NR | M39: NR | N39: NR | O39: NR | P39: Dryden Senior Loan Fund | S39: BBB- | T39: SP | U39: BBB
A40: 26253QAS0 | B40: 26253QAS0 | C40: 9.4551501 | D40: 45945 | E40: 46492 | F40: 12.059184 | G40: 373.2646 | H40: 100.4377 | I40: PGIM | J40: 20250522 | K40: BBB- | L40: NR | M40: NR | N40: NR | O40: NR | P40: Dryden Senior Loan Fund | Q40: 2025 | S40: BBB- | T40: SP | U40: BBB
A41: 29002HBE8 | B41: 29002HBE8 | D41: 45948 | E41: 46193 | F41: 10.447594 | I41: Elmwood Asset Management | J41: 20240620 | K41: NR | L41: NR | M41: BBB- | N41: NR | O41: NR | P41: Elmwood CLO III Ltd | S41: BBB- | T41: Fitch | U41: BBB
A42: 29003KAA9 | B42: 29003KAA9 | D42: 45952 | E42: 46213 | I42: Elmwood RR CLO | J42: 20220330 | K42: BB- | L42: NR | M42: NR | N42: NR | O42: NR | P42: Elmwood CLO 15 Ltd | S42: BB- | T42: SP | U42: BB
A43: 29004KAJ9 | B43: 29004KAJ9 | C43: 9.68211 | D43: 46042 | E43: 46585 | F43: 12 | G43: 272.36225 | H43: 100.4378 | I43: Elmwood Asset Management | J43: 20250717 | K43: NR | L43: NR | M43: BBB- | N43: NR | O43: NR | P43: Elmwood CLO 43 Ltd | Q43: 2025 | S43: BBB- | T43: Fitch | U43: BBB
A44: 30605YAB7 | B44: 30605YAB7 | C44: 0.041666667 | D44: 45884 | F44: 91.081592 | G44: -12848.936 | H44: 99.43349 | I44: Falcon Aerospace Ltd | J44: 20170214 | K44: A | L44: NR | M44: NR | N44: A- | O44: NR | P44: Falcon Aerospace Ltd | R44: Aircraft Portfolio | S44: A | T44: SP | U44: A
A45: 33883DAE4 | B45: 33883DAE4 | D45: 45947 | E45: 46183 | I45: NYL Investors | J45: 20230509 | K45: NR | L45: NR | M45: A | N45: NR | O45: NR | P45: Flatiron CLO Ltd | S45: A | T45: Fitch | U45: A
A46: 33883DAG9 | B46: 33883DAG9 | D46: 45947 | E46: 46183 | I46: NYL Investors | J46: 20230509 | K46: NR | L46: NR | M46: BBB- | N46: NR | O46: NR | P46: Flatiron CLO Ltd | S46: BBB- | T46: Fitch | U46: BBB
A47: 33883DAU8 | B47: 33883DAU8 | C47: 6.8201395 | D47: 45947 | E47: 46183 | F47: 18.039227 | G47: 170.27213 | H47: 100.5538 | I47: NYL Investors | J47: 20250610 | K47: NR | L47: NR | M47: A+ | N47: NR | O47: NR | P47: Flatiron CLO Ltd | Q47: 2025 | S47: A+ | T47: Fitch | U47: A
A48: 36626AAD7 | B48: 36626AAD7 | C48: 8.1636231 | F48: 18 | G48: 215.11399 | H48: 100.5387 | I48: Garnet Credit Management | J48: 20250703 | K48: A | L48: NR | M48: NR | N48: NR | O48: NR | P48: Garnet CLO Ltd | Q48: 2025 | S48: A | T48: SP | U48: A
A49: 38139FAG5 | B49: 38139FAG5 | D49: 45950 | E49: 46562 | I49: GLM II | J49: 20230622 | K49: NR | L49: NR | M49: A | N49: NR | O49: NR | P49: GoldenTree Loan Management US | S49: A | T49: Fitch | U49: A
A50: 38139FAJ9 | B50: 38139FAJ9 | D50: 45950 | E50: 46562 | I50: GLM II | J50: 20230622 | K50: NR | L50: NR | M50: BBB- | N50: NR | O50: NR | P50: GoldenTree Loan Management US | S50: BBB- | T50: Fitch | U50: BBB
A51: 38139FAW0 | B51: 38139FAW0 | C51: 9.6833798 | D51: 45950 | E51: 46562 | F51: 12.042431 | G51: 273.0174 | H51: 100.501 | I51: GLM II | J51: 20250624 | K51: NR | L51: NR | M51: BBB- | N51: NR | O51: NR | P51: GoldenTree Loan Management US | Q51: 2025 | S51: BBB- | T51: Fitch | U51: BBB
A52: 38139QAL0 | B52: 38139QAL0 | C52: 9.6333088 | F52: 12 | G52: 268.34362 | H52: 100.3889 | I52: GLM III | J52: 20250807 | K52: NR | L52: NR | M52: BBB- | N52: NR | O52: NR | P52: GoldenTree Loan Management US | Q52: 2025 | S52: BBB- | T52: Fitch | U52: BBB
A53: 38174YAE5 | B53: 38174YAE5 | I53: GC Investment Management | J53: 20171109 | K53: AA | L53: NR | M53: NR | N53: NR | O53: NR | P53: Golub Capital Partners CLO Ltd | S53: AA | T53: SP | U53: AA
A54: 38174YAG0 | B54: 38174YAG0 | I54: GC Investment Management | J54: 20171109 | K54: BBB+ | L54: NR | M54: NR | N54: NR | O54: NR | P54: Golub Capital Partners CLO Ltd | S54: BBB+ | T54: SP | U54: BBB
A55: 38181PAG0 | B55: 38181PAG0 | C55: 0 | D55: 45955 | E55: 45863 | G55: 190.34991 | H55: 100.25 | I55: OPAL BSL | J55: 20250815 | K55: NR | L55: NR | M55: A | N55: NR | O55: NR | P55: Golub Capital Partners CLO, LT | Q55: 2025 | S55: A | T55: Fitch | U55: A
A56: 40169CAJ5 | B56: 40169CAJ5 | C56: 2.0965508 | D56: 45945 | E56: 45282 | F56: 13.816869 | G56: 460.1772 | H56: 93.1954 | I56: Guggenheim Corporate Funding | J56: 20211222 | K56: NR | L56: NR | M56: NR | N56: BBB- | O56: NR | P56: Guggenheim CLO Ltd | Q56: 2021 | S56: BBB- | T56: KBRA | U56: BBB
A57: 41757PAJ2 | B57: 41757PAJ2 | C57: 9.6645992 | D57: 46039 | E57: 46585 | F57: 12 | G57: 338.07629 | H57: 100.3888 | I57: Investcorp Credit Management US | J57: 20250730 | K57: NR | L57: NR | M57: BBB- | N57: NR | O57: NR | P57: Harvest US CLO Ltd | Q57: 2025 | S57: BBB- | T57: Fitch | U57: BBB
A58: 43128QAL3 | B58: 43128QAL3 | C58: 9.6223237 | F58: 12 | G58: 268.4338 | H58: 100.3889 | I58: Blackstone CLO Management | J58: 20250821 | K58: NR | L58: NR | M58: BBB- | N58: NR | O58: NR | P58: Higley Park Clo Ltd | Q58: 2025 | S58: BBB- | T58: Fitch | U58: BBB
A59: 442911AG8 | B59: 442911AG8 | D59: 45950 | E59: 46588 | I59: HPS Investment Partners | J59: 20230627 | K59: A | L59: NR | M59: NR | N59: NR | O59: NR | P59: HPS Loan Management Ltd | S59: A | T59: SP | U59: A
A60: 442911AJ2 | B60: 442911AJ2 | D60: 45950 | E60: 46588 | I60: HPS Investment Partners | J60: 20230627 | K60: BBB- | L60: NR | M60: NR | N60: NR | O60: NR | P60: HPS Loan Management Ltd | S60: BBB- | T60: SP | U60: BBB
A61: 442911AS2 | B61: 442911AS2 | C61: 9.1879788 | D61: 45950 | E61: 46588 | F61: 18.156844 | G61: 198.69778 | H61: 100.0881 | I61: HPS Investment Partners | J61: 20250721 | K61: NR | L61: NR | M61: A | N61: NR | O61: NR | P61: HPS Loan Management Ltd | Q61: 2025 | S61: A | T61: Fitch | U61: A
A62: 442911AU7 | B62: 442911AU7 | C62: 9.7230354 | D62: 45950 | E62: 46588 | F62: 12.168321 | G62: 303.31823 | H62: 100.1129 | I62: HPS Investment Partners | J62: 20250721 | K62: NR | L62: NR | M62: BBB- | N62: NR | O62: NR | P62: HPS Loan Management Ltd | Q62: 2025 | S62: BBB- | T62: Fitch | U62: BBB
A63: 442921AJ1 | B63: 442921AJ1 | C63: 10.331832 | D63: 45950 | E63: 46588 | F63: 8.1759715 | G63: 595.77877 | H63: 100.262 | I63: HPS Investment Partners | J63: 20250721 | K63: NR | L63: NR | M63: BB- | N63: NR | O63: NR | P63: HPS Loan Management Ltd | Q63: 2025 | S63: BB- | T63: Fitch | U63: BB
A64: 449272AN3 | B64: 449272AN3 | D64: 45956 | E64: 45225 | F64: 7.999505 | I64: ICG Debt Advisors | J64: 20211103 | K64: NR | L64: NR | M64: NR | N64: BBB- | O64: NR | P64: ICG Rhinebeck CLO 2021-4 Ltd | S64: BBB- | T64: KBRA | U64: BBB
A65: 449272AQ6 | B65: 449272AQ6 | D65: 45956 | E65: 45225 | F65: 3.3245518 | I65: ICG Debt Advisors | J65: 20211103 | K65: NR | L65: NR | M65: NR | N65: BB- | O65: NR | P65: ICG Rhinebeck CLO 2021-4 Ltd | S65: BB- | T65: KBRA | U65: BB
A66: 449278AG5 | B66: 449278AG5 | D66: 45948 | E66: 46586 | I66: ICG Debt Advisors | J66: 20230906 | K66: BBB- | L66: NR | M66: NR | N66: NR | O66: NR | P66: ICG US CLO Ltd | S66: BBB- | T66: SP | U66: BBB
A67: 44931NAW1 | B67: 44931NAW1 | C67: 5.258316 | D67: 45959 | E67: 45045 | F67: 8.8787906 | G67: 384.3399 | H67: 100.2865 | I67: ICG Debt Advisors | J67: 20210528 | K67: BBB- | L67: NR | M67: NR | N67: NR | O67: NR | P67: ICG US CLO Ltd | Q67: 2021 | S67: BBB- | T67: SP | U67: BBB
A68: 46091RAE3 | B68: 46091RAE3 | D68: 45945 | E68: 46583 | I68: Invesco CLO Equity Fund 3 | J68: 20230817 | K68: A | L68: NR | M68: NR | N68: NR | O68: NR | P68: Invesco U.S. CLO 2025-2, Ltd. | S68: A | T68: SP | U68: A
A69: 46091RAG8 | B69: 46091RAG8 | D69: 45945 | E69: 46583 | I69: Invesco CLO Equity Fund 3 | J69: 20230817 | K69: BBB- | L69: NR | M69: NR | N69: NR | O69: NR | P69: Invesco U.S. CLO 2025-2, Ltd. | S69: BBB- | T69: SP | U69: BBB
A70: 46147KAD4 | B70: 46147KAD4 | D70: 45951 | E70: 46498 | I70: Invesco CLO Equity Fund 3 | J70: 20230328 | K70: NR | L70: NR | M70: BBB- | N70: NR | O70: NR | P70: Invesco U.S. CLO 2025-2, Ltd. | S70: BBB- | T70: Fitch | U70: BBB
A71: 481954AG0 | B71: 481954AG0 | C71: 9.7071233 | D71: 46037 | E71: 46583 | F71: 12 | G71: 339.92339 | H71: 100.2393 | I71: KKR Financial Advisors II | J71: 20250703 | K71: NR | L71: NR | M71: BBB- | N71: NR | O71: NR | P71: KKR Financial CLO Ltd | Q71: 2025 | S71: BBB- | T71: Fitch | U71: BBB
A72: 48255XAW8 | B72: 48255XAW8 | C72: 9.6372363 | D72: 45946 | E72: 46584 | F72: 12.970114 | G72: 299.11142 | H72: 100.7623 | I72: KKR Financial Advisors II | J72: 20250707 | K72: NR | L72: NR | M72: BBB | N72: NR | O72: NR | P72: KKR Financial CLO Ltd | Q72: 2025 | S72: BBB | T72: Fitch | U72: BBB
A73: 48257CAJ1 | B73: 48257CAJ1 | C73: 7.6881911 | D73: 46037 | E73: 46189 | F73: 11.572145 | G73: 371.04705 | H73: 100.6784 | I73: KKR Financial Advisors II | J73: 20250616 | K73: NR | L73: NR | M73: BBB- | N73: NR | O73: NR | P73: KKR Financial CLO Ltd | Q73: 2025 | S73: BBB- | T73: Fitch | U73: BBB
A74: 542798AG8 | B74: 542798AG8 | C74: 2.3373505 | D74: 45947 | E74: 43847 | F74: 38.541549 | G74: 173.29035 | H74: 100.4838 | I74: Blackstone Liquid Credit Strategies | J74: 20171228 | K74: NR | L74: Aa1 | M74: NR | N74: NR | O74: NR | P74: Long Point Park CLO Ltd | S74: Aa1 | T74: Moody's | U74: AA
A75: 55817GAG6 | B75: 55817GAG6 | D75: 45951 | E75: 46543 | I75: UBS Asset Management (Americas) | J75: 20230512 | K75: NR | L75: NR | M75: A | N75: NR | O75: NR | P75: Madison Park Funding Ltd | S75: A | T75: Fitch | U75: A
A76: 55817GAU5 | B76: 55817GAU5 | C76: 9.1379108 | D76: 45951 | E76: 46543 | F76: 18.548484 | G76: 201.96637 | H76: 100.9312 | I76: UBS Asset Management (Americas) | J76: 20250605 | K76: NR | L76: NR | M76: A+ | N76: NR | O76: NR | P76: Madison Park Funding Ltd | Q76: 2025 | S76: A+ | T76: Fitch | U76: A
A77: 55817GAW1 | B77: 55817GAW1 | C77: 9.6369096 | D77: 45951 | E77: 46543 | F77: 13.229202 | G77: 307.19499 | H77: 100.5496 | I77: UBS Asset Management (Americas) | J77: 20250605 | K77: NR | L77: NR | M77: BBB | N77: NR | O77: NR | P77: Madison Park Funding Ltd | Q77: 2025 | S77: BBB | T77: Fitch | U77: BBB
A78: 55821MAA0 | B78: 55821MAA0 | C78: 6.4471528 | D78: 45947 | E78: 45094 | F78: 7.8203246 | G78: 607.81424 | H78: 100.8671 | I78: Credit Suisse Asset Management | J78: 20210617 | K78: BB- | L78: NR | M78: NR | N78: NR | O78: NR | P78: Madison Park Funding Ltd | Q78: 2021 | S78: BB- | T78: SP | U78: BB
A79: 559922AG4 | B79: 559922AG4 | D79: 45955 | E79: 46549 | I79: Blackrock Financial Management | J79: 20230608 | K79: BBB- | L79: NR | M79: NR | N79: NR | O79: NR | P79: Magnetite CLO Ltd | S79: BBB- | T79: SP | U79: BBB
A80: 56577GAJ8 | B80: 56577GAJ8 | C80: 1.1724087 | D80: 45945 | E80: 44576 | F80: 34.628597 | G80: 380.14373 | H80: 96.9857 | I80: Maranon Capital | J80: 20201208 | K80: NR | L80: NR | M80: NR | N80: BBB+ | O80: NR | P80: Maranon Loan Funding Ltd | Q80: 2020 | S80: BBB+ | T80: KBRA | U80: BBB
A81: 56577JAG8 | B81: 56577JAG8 | C81: 0.38137399 | D81: 45945 | E81: 45122 | F81: 19.48584 | G81: 487.78704 | H81: 98.7781 | I81: Maranon Management | J81: 20210623 | K81: NR | L81: NR | M81: NR | N81: BBB | O81: NR | P81: Maranon Loan Funding Ltd | Q81: 2021 | S81: BBB | T81: KBRA | U81: BBB
A82: 56577LAN8 | B82: 56577LAN8 | C82: 0.29289842 | D82: 45945 | E82: 45031 | F82: 20.125623 | G82: 455.54444 | H82: 99.1429 | I82: Maranon Capital | J82: 20210519 | K82: NR | L82: NR | M82: NR | N82: BBB | O82: NR | P82: Maranon Loan Funding Ltd | Q82: 2021 | S82: BBB | T82: KBRA | U82: BBB
A83: 59803TAY7 | B83: 59803TAY7 | D83: 45948 | E83: 46586 | I83: MidOcean Credit RR Manager | J83: 20240418 | K83: NR | L83: NR | M83: BBB- | N83: NR | O83: NR | P83: MidOcean Credit CLO | S83: BBB- | T83: Fitch | U83: BBB
A84: 64133JAQ7 | B84: 64133JAQ7 | C84: 5.4661879 | D84: 45950 | E84: 45677 | F84: 7.2437066 | G84: 703.4057 | H84: 101.0785 | I84: Neuberger Berman Loan Advisers | J84: 20240311 | K84: BB- | L84: NR | M84: NR | N84: NR | O84: NR | P84: Neuberger Berman CLO Ltd | Q84: 2024 | S84: BB- | T84: SP | U84: BB
A85: 64133KAQ4 | B85: 64133KAQ4 | C85: 4.6386328 | D85: 45950 | E85: 45677 | F85: 11.841798 | G85: 363.07192 | H85: 100.3075 | I85: Neuberger Berman Loan Advisers | J85: 20210120 | K85: BBB- | L85: NR | M85: NR | N85: NR | O85: NR | P85: Neuberger Berman CLO Ltd | Q85: 2021 | S85: BBB- | T85: SP | U85: BBB
A86: 67116TAM8 | B86: 67116TAM8 | I86: Oak Hill Advisors | J86: 20230524 | K86: BBB- | L86: NR | M86: NR | N86: NR | O86: NR | P86: Oak Hill Credit | S86: BBB- | T86: SP | U86: BBB
A87: 67181DAE1 | B87: 67181DAE1 | C87: 0.30534781 | D87: 45889 | F87: 27.4503 | G87: 1220.0108 | H87: 97.17864 | I87: Oak Street Investment Grade Ne | J87: 20201113 | K87: BBB+ | L87: NR | M87: NR | N87: NR | O87: NR | P87: Oak Street Investment Grade Ne | R87: Triple Net Lease | S87: BBB+ | T87: SP | U87: BBB
A88: 67190AAC0 | B88: 67190AAC0 | C88: 0.47170212 | D88: 45889 | F88: 27.4503 | G88: 464.5625 | H88: 97.78384 | I88: Oak Street Investment Grade Ne | J88: 20210127 | K88: BBB+ | L88: NR | M88: NR | N88: NR | O88: NR | P88: Oak Street Investment Grade Ne | R88: Triple Net Lease | S88: BBB+ | T88: SP | U88: BBB
A89: 67190AAD8 | B89: 67190AAD8 | C89: 2.4303684 | D89: 45889 | F89: 27.4503 | G89: 585.29407 | H89: 87.626225 | I89: Oak Street Investment Grade Ne | J89: 20210127 | K89: BBB+ | L89: NR | M89: NR | N89: NR | O89: NR | P89: Oak Street Investment Grade Ne | R89: Triple Net Lease | S89: BBB+ | T89: SP | U89: BBB
A90: 67402LAJ5 | B90: 67402LAJ5 | D90: 45945 | E90: 46583 | I90: Oaktree Capital Management | J90: 20220429 | K90: A+ | L90: NR | M90: NR | N90: NR | O90: NR | P90: Oaktree CLO Ltd | S90: A+ | T90: SP | U90: A
A91: 67571LAJ0 | B91: 67571LAJ0 | D91: 45955 | E91: 46527 | I91: Octagon Credit Investors | J91: 20230329 | K91: NR | L91: NR | M91: BBB- | N91: NR | O91: NR | P91: Octagon 67 Ltd | S91: BBB- | T91: Fitch | U91: BBB
A92: 67571LAW1 | B92: 67571LAW1 | C92: 9.7381478 | D92: 45955 | E92: 46527 | F92: 11.89095 | G92: 377.50389 | H92: 100.8619 | I92: Octagon Credit Investors | J92: 20250520 | K92: NR | L92: NR | M92: BBB- | N92: NR | O92: NR | P92: Octagon 67 Ltd | Q92: 2025 | S92: BBB- | T92: Fitch | U92: BBB
A93: 67577YAA5 | B93: 67577YAA5 | D93: 45955 | E93: 46527 | I93: Octagon Credit Investors | J93: 20230329 | K93: NR | L93: NR | M93: BB- | N93: NR | O93: NR | P93: Octagon 67 Ltd | S93: BB- | T93: Fitch | U93: BB
A94: 67590EBN3 | B94: 67590EBN3 | D94: 45949 | E94: 44589 | I94: Octagon Credit Investors | J94: 20210728 | K94: BBB- | L94: NR | M94: NR | N94: NR | O94: NR | P94: Octagon Investment Partners XV | S94: BBB- | T94: SP | U94: BBB
A95: 67707LAE8 | B95: 67707LAE8 | C95: 6.4722222 | D95: 45948 | E95: 45277 | F95: 10.863803 | H95: 100.45 | I95: Oak Hill Advisors | J95: 20211217 | K95: NR | L95: NR | M95: BBB- | N95: NR | O95: NR | P95: Oak Hill Credit | S95: BBB- | T95: Fitch | U95: BBB
A96: 69688FAW0 | B96: 69688FAW0 | C96: 0 | D96: 45945 | E96: 45269 | G96: 274.85899 | H96: 100.375 | I96: Palmer Square Capital Management | J96: 20250814 | K96: NR | L96: NR | M96: BBB- | N96: NR | O96: NR | P96: Palmer Square CLO Ltd | Q96: 2025 | S96: BBB- | T96: Fitch | U96: BBB
A97: 69703AAG7 | B97: 69703AAG7 | D97: 45950 | E97: 46588 | I97: Palmer Square Capital Management | J97: 20230601 | K97: A | L97: NR | M97: NR | N97: NR | O97: NR | P97: Palmer Square CLO Ltd | S97: A | T97: SP | U97: A
A98: 69703AAJ1 | B98: 69703AAJ1 | D98: 45950 | E98: 46588 | I98: Palmer Square Capital Management | J98: 20230601 | K98: BBB- | L98: NR | M98: NR | N98: NR | O98: NR | P98: Palmer Square CLO Ltd | S98: BBB- | T98: SP | U98: BBB
A99: 69703AAU6 | B99: 69703AAU6 | C99: 9.6737587 | D99: 45950 | E99: 46588 | F99: 12.50252 | G99: 337.84601 | H99: 100.1432 | I99: Palmer Square Capital Management | J99: 20250522 | K99: BBB- | L99: NR | M99: NR | N99: NR | O99: NR | P99: Palmer Square CLO Ltd | Q99: 2025 | S99: BBB- | T99: SP | U99: BBB
A100: 69704GAJ7 | B100: 69704GAJ7 | C100: 9.6362707 | F100: 12 | G100: 273.43681 | H100: 100.3889 | I100: Palmer Square Capital Management | J100: 20250820 | K100: BBB- | L100: NR | M100: NR | N100: NR | O100: NR | P100: Palmer Square CLO Ltd | Q100: 2025 | S100: BBB- | T100: SP | U100: BBB
...
