Workbook

Sheet Report
B1: SkyRidge CLO ABS Report
B2: Prepared As of: | C2: View As Portfolio:
C3: Choose the desired portfolio in the drop down
B4: 45869 | C4: All Portfolios
B6: Summary Page
B8: Executive Summary | E8: Tranche Rating | I8: Weighted Average Life | M8: CLO Debt Coupon
B9: Analytics | C9: CLO/ABS Debt | E9: Tranche Rating | F9: Portfolio % CF | G9: Portfolio % MV | I9: WAL | J9: Portfolio % CF | K9: Portfolio % MV | M9: Coupon | N9: Portfolio % CF | O9: Portfolio % MV
B10: Face Value | C10: =C37 -> 181607248 | E10: AAA | F10: =IFERROR(IF($C$4="All Portfolios", SUMIFS(Positions!$D$2:$D$644,Positions!$Q$2:$Q$644,Table13[[#This Row],[Tranche Rating]])/$C$10, SUMIFS(Positions!$D$2:$D$644,Positions!$Q$2:$Q$644,Table13[[#This Row],[Tranche Rating]],Positions!$M$2:$M$644,$C$4)/$C$10),0) -> 0 | G10: =IFERROR(IF($C$4="All Portfolios", SUMIFS(Positions!$E$2:$E$644,Positions!$Q$2:$Q$644,Table13[[#This Row],[Tranche Rating]])/$C$11, SUMIFS(Positions!$E$2:$E$644,Positions!$Q$2:$Q$644,Table13[[#This Row],[Tranche Rating]],Positions!$M$2:$M$644,$C$4)/$C$11),0) -> 0 | I10: 0<2 | J10: =IFERROR(IF($C$4="All Portfolios", SUMIFS(Positions!$D$2:$D$644,Positions!$R$2:$R$644,Table14[[#This Row],[WAL]])/$C$10, SUMIFS(Positions!$D$2:$D$644,Positions!$R$2:$R$644,Table14[[#This Row],[WAL]],Positions!$M$2:$M$644,$C$4)/$C$10),0) -> 0.64632199 | K10: =IFERROR(IF($C$4="All Portfolios", SUMIFS(Positions!$E$2:$E$644,Positions!$R$2:$R$644,Table14[[#This Row],[WAL]])/$C$11, SUMIFS(Positions!$E$2:$E$644,Positions!$R$2:$R$644,Table14[[#This Row],[WAL]],Positions!$M$2:$M$644,$C$4)/$C$11),0) -> 0.63241358 | M10: 0<3 | N10: =IFERROR(IF($C$4="All Portfolios", SUMIFS(Positions!$D$2:$D$644,Positions!$S$2:$S$644,Table15[[#This Row],[Coupon]])/$C$10, SUMIFS(Positions!$D$2:$D$644,Positions!$S$2:$S$644,Table15[[#This Row],[Coupon]],Positions!$M$2:$M$644,$C$4)/$C$10),0) -> 0.46488782 | O10: =IFERROR(IF($C$4="All Portfolios", SUMIFS(Positions!$E$2:$E$644,Positions!$S$2:$S$644,Table15[[#This Row],[Coupon]])/$C$11, SUMIFS(Positions!$E$2:$E$644,Positions!$S$2:$S$644,Table15[[#This Row],[Coupon]],Positions!$M$2:$M$644,$C$4)/$C$11),0) -> 0.45944395
B11: Market Value | C11: =D37 -> 1.8264345e+08 | E11: AA | F11: =IFERROR(IF($C$4="All Portfolios", SUMIFS(Positions!$D$2:$D$644,Positions!$Q$2:$Q$644,Table13[[#This Row],[Tranche Rating]])/$C$10, SUMIFS(Positions!$D$2:$D$644,Positions!$Q$2:$Q$644,Table13[[#This Row],[Tranche Rating]],Positions!$M$2:$M$644,$C$4)/$C$10),0) -> 0.089297301 | G11: =IFERROR(IF($C$4="All Portfolios", SUMIFS(Positions!$E$2:$E$644,Positions!$Q$2:$Q$644,Table13[[#This Row],[Tranche Rating]])/$C$11, SUMIFS(Positions!$E$2:$E$644,Positions!$Q$2:$Q$644,Table13[[#This Row],[Tranche Rating]],Positions!$M$2:$M$644,$C$4)/$C$11),0) -> 0.088525361 | I11: 2<4 | J11: =IFERROR(IF($C$4="All Portfolios", SUMIFS(Positions!$D$2:$D$644,Positions!$R$2:$R$644,Table14[[#This Row],[WAL]])/$C$10, SUMIFS(Positions!$D$2:$D$644,Positions!$R$2:$R$644,Table14[[#This Row],[WAL]],Positions!$M$2:$M$644,$C$4)/$C$10),0) -> 1.2951276 | K11: =IFERROR(IF($C$4="All Portfolios", SUMIFS(Positions!$E$2:$E$644,Positions!$R$2:$R$644,Table14[[#This Row],[WAL]])/$C$11, SUMIFS(Positions!$E$2:$E$644,Positions!$R$2:$R$644,Table14[[#This Row],[WAL]],Positions!$M$2:$M$644,$C$4)/$C$11),0) -> 1.2645383 | M11: 3<4 | N11: =IFERROR(IF($C$4="All Portfolios", SUMIFS(Positions!$D$2:$D$644,Positions!$S$2:$S$644,Table15[[#This Row],[Coupon]])/$C$10, SUMIFS(Positions!$D$2:$D$644,Positions!$S$2:$S$644,Table15[[#This Row],[Coupon]],Positions!$M$2:$M$644,$C$4)/$C$10),0) -> 0.12522093 | O11: =IFERROR(IF($C$4="All Portfolios", SUMIFS(Positions!$E$2:$E$644,Positions!$S$2:$S$644,Table15[[#This Row],[Coupon]])/$C$11, SUMIFS(Positions!$E$2:$E$644,Positions!$S$2:$S$644,Table15[[#This Row],[Coupon]],Positions!$M$2:$M$644,$C$4)/$C$11),0) -> 0.11924929
B12: WA Coupon | C12: {=IFERROR(IF( $C$4 = "All Portfolios", SUMPRODUCT( Positions!$D$2:$D$644 * (Positions!$H$2:$H$644 * 0.01) ) / C10, SUMPRODUCT((Positions!$M$2:$M$644 = $C$4) * Positions!$D$2:$D$644 * (Positions!$H$2:$H$644 * 0.01) ) / C10),0)} -> 1.0455414 | E12: A | F12: =IFERROR(IF($C$4="All Portfolios", SUMIFS(Positions!$D$2:$D$644,Positions!$Q$2:$Q$644,Table13[[#This Row],[Tranche Rating]])/$C$10, SUMIFS(Positions!$D$2:$D$644,Positions!$Q$2:$Q$644,Table13[[#This Row],[Tranche Rating]],Positions!$M$2:$M$644,$C$4)/$C$10),0) -> 1.4491611 | G12: =IFERROR(IF($C$4="All Portfolios", SUMIFS(Positions!$E$2:$E$644,Positions!$Q$2:$Q$644,Table13[[#This Row],[Tranche Rating]])/$C$11, SUMIFS(Positions!$E$2:$E$644,Positions!$Q$2:$Q$644,Table13[[#This Row],[Tranche Rating]],Positions!$M$2:$M$644,$C$4)/$C$11),0) -> 1.4387011 | I12: 4<6 | J12: =IFERROR(IF($C$4="All Portfolios", SUMIFS(Positions!$D$2:$D$644,Positions!$R$2:$R$644,Table14[[#This Row],[WAL]])/$C$10, SUMIFS(Positions!$D$2:$D$644,Positions!$R$2:$R$644,Table14[[#This Row],[WAL]],Positions!$M$2:$M$644,$C$4)/$C$10),0) -> 1.2325245 | K12: =IFERROR(IF($C$4="All Portfolios", SUMIFS(Positions!$E$2:$E$644,Positions!$R$2:$R$644,Table14[[#This Row],[WAL]])/$C$11, SUMIFS(Positions!$E$2:$E$644,Positions!$R$2:$R$644,Table14[[#This Row],[WAL]],Positions!$M$2:$M$644,$C$4)/$C$11),0) -> 1.215319 | M12: 4<5 | N12: =IFERROR(IF($C$4="All Portfolios", SUMIFS(Positions!$D$2:$D$644,Positions!$S$2:$S$644,Table15[[#This Row],[Coupon]])/$C$10, SUMIFS(Positions!$D$2:$D$644,Positions!$S$2:$S$644,Table15[[#This Row],[Coupon]],Positions!$M$2:$M$644,$C$4)/$C$10),0) -> 0.24129959 | O12: =IFERROR(IF($C$4="All Portfolios", SUMIFS(Positions!$E$2:$E$644,Positions!$S$2:$S$644,Table15[[#This Row],[Coupon]])/$C$11, SUMIFS(Positions!$E$2:$E$644,Positions!$S$2:$S$644,Table15[[#This Row],[Coupon]],Positions!$M$2:$M$644,$C$4)/$C$11),0) -> 0.22963708
B13: WA Purchase Price | C13: =IFERROR(IF($C$4="All Portfolios", SUM(Positions!$F$2:$F$644)/C10, SUMIF(Positions!$M$2:$M$644,$C$4,Positions!$F$2:$F$644)/C10),0) -> 13.27242 | E13: BBB | F13: =IFERROR(IF($C$4="All Portfolios", SUMIFS(Positions!$D$2:$D$644,Positions!$Q$2:$Q$644,Table13[[#This Row],[Tranche Rating]])/$C$10, SUMIFS(Positions!$D$2:$D$644,Positions!$Q$2:$Q$644,Table13[[#This Row],[Tranche Rating]],Positions!$M$2:$M$644,$C$4)/$C$10),0) -> 9.2524817 | G13: =IFERROR(IF($C$4="All Portfolios", SUMIFS(Positions!$E$2:$E$644,Positions!$Q$2:$Q$644,Table13[[#This Row],[Tranche Rating]])/$C$11, SUMIFS(Positions!$E$2:$E$644,Positions!$Q$2:$Q$644,Table13[[#This Row],[Tranche Rating]],Positions!$M$2:$M$644,$C$4)/$C$11),0) -> 9.2127374 | I13: 6<8 | J13: =IFERROR(IF($C$4="All Portfolios", SUMIFS(Positions!$D$2:$D$644,Positions!$R$2:$R$644,Table14[[#This Row],[WAL]])/$C$10, SUMIFS(Positions!$D$2:$D$644,Positions!$R$2:$R$644,Table14[[#This Row],[WAL]],Positions!$M$2:$M$644,$C$4)/$C$10),0) -> 3.9567123 | K13: =IFERROR(IF($C$4="All Portfolios", SUMIFS(Positions!$E$2:$E$644,Positions!$R$2:$R$644,Table14[[#This Row],[WAL]])/$C$11, SUMIFS(Positions!$E$2:$E$644,Positions!$R$2:$R$644,Table14[[#This Row],[WAL]],Positions!$M$2:$M$644,$C$4)/$C$11),0) -> 3.9182328 | M13: 5<6 | N13: =IFERROR(IF($C$4="All Portfolios", SUMIFS(Positions!$D$2:$D$644,Positions!$S$2:$S$644,Table15[[#This Row],[Coupon]])/$C$10, SUMIFS(Positions!$D$2:$D$644,Positions!$S$2:$S$644,Table15[[#This Row],[Coupon]],Positions!$M$2:$M$644,$C$4)/$C$10),0) -> 0.3149654 | O13: =IFERROR(IF($C$4="All Portfolios", SUMIFS(Positions!$E$2:$E$644,Positions!$S$2:$S$644,Table15[[#This Row],[Coupon]])/$C$11, SUMIFS(Positions!$E$2:$E$644,Positions!$S$2:$S$644,Table15[[#This Row],[Coupon]],Positions!$M$2:$M$644,$C$4)/$C$11),0) -> 0.3153702
B14: WA Market Price | C14: =IFERROR(C11/C10,0) -> 1.0057057 | E14: BB | F14: =IFERROR(IF($C$4="All Portfolios", SUMIFS(Positions!$D$2:$D$644,Positions!$Q$2:$Q$644,Table13[[#This Row],[Tranche Rating]])/$C$10, SUMIFS(Positions!$D$2:$D$644,Positions!$Q$2:$Q$644,Table13[[#This Row],[Tranche Rating]],Positions!$M$2:$M$644,$C$4)/$C$10),0) -> 2.218058 | G14: =IFERROR(IF($C$4="All Portfolios", SUMIFS(Positions!$E$2:$E$644,Positions!$Q$2:$Q$644,Table13[[#This Row],[Tranche Rating]])/$C$11, SUMIFS(Positions!$E$2:$E$644,Positions!$Q$2:$Q$644,Table13[[#This Row],[Tranche Rating]],Positions!$M$2:$M$644,$C$4)/$C$11),0) -> 2.1890735 | I14: 8<10 | J14: =IFERROR(IF($C$4="All Portfolios", SUMIFS(Positions!$D$2:$D$644,Positions!$R$2:$R$644,Table14[[#This Row],[WAL]])/$C$10, SUMIFS(Positions!$D$2:$D$644,Positions!$R$2:$R$644,Table14[[#This Row],[WAL]],Positions!$M$2:$M$644,$C$4)/$C$10),0) -> 5.8738745 | K14: =IFERROR(IF($C$4="All Portfolios", SUMIFS(Positions!$E$2:$E$644,Positions!$R$2:$R$644,Table14[[#This Row],[WAL]])/$C$11, SUMIFS(Positions!$E$2:$E$644,Positions!$R$2:$R$644,Table14[[#This Row],[WAL]],Positions!$M$2:$M$644,$C$4)/$C$11),0) -> 5.8688264 | M14: 6<7 | N14: =IFERROR(IF($C$4="All Portfolios", SUMIFS(Positions!$D$2:$D$644,Positions!$S$2:$S$644,Table15[[#This Row],[Coupon]])/$C$10, SUMIFS(Positions!$D$2:$D$644,Positions!$S$2:$S$644,Table15[[#This Row],[Coupon]],Positions!$M$2:$M$644,$C$4)/$C$10),0) -> 1.141694 | O14: =IFERROR(IF($C$4="All Portfolios", SUMIFS(Positions!$E$2:$E$644,Positions!$S$2:$S$644,Table15[[#This Row],[Coupon]])/$C$11, SUMIFS(Positions!$E$2:$E$644,Positions!$S$2:$S$644,Table15[[#This Row],[Coupon]],Positions!$M$2:$M$644,$C$4)/$C$11),0) -> 1.1386958
B15: WA Life | C15: {=IFERROR(IF( $C$4 = "All Portfolios", SUMPRODUCT( Positions!$D$2:$D$644 * Positions!$P$2:$P$644 ) / C10, SUMPRODUCT((Positions!$M$2:$M$644 = $C$4) * Positions!$D$2:$D$644 * Positions!$P$2:$P$644 ) / C10),0)} -> 92.365459 | E15: B | F15: =IFERROR(IF($C$4="All Portfolios", SUMIFS(Positions!$D$2:$D$644,Positions!$Q$2:$Q$644,Table13[[#This Row],[Tranche Rating]])/$C$10, SUMIFS(Positions!$D$2:$D$644,Positions!$Q$2:$Q$644,Table13[[#This Row],[Tranche Rating]],Positions!$M$2:$M$644,$C$4)/$C$10),0) -> 0.22373654 | G15: =IFERROR(IF($C$4="All Portfolios", SUMIFS(Positions!$E$2:$E$644,Positions!$Q$2:$Q$644,Table13[[#This Row],[Tranche Rating]])/$C$11, SUMIFS(Positions!$E$2:$E$644,Positions!$Q$2:$Q$644,Table13[[#This Row],[Tranche Rating]],Positions!$M$2:$M$644,$C$4)/$C$11),0) -> 0.22041767 | I15: 10+ | J15: =IFERROR(IF($C$4="All Portfolios", SUMIFS(Positions!$D$2:$D$644,Positions!$R$2:$R$644,Table14[[#This Row],[WAL]])/$C$10, SUMIFS(Positions!$D$2:$D$644,Positions!$R$2:$R$644,Table14[[#This Row],[WAL]],Positions!$M$2:$M$644,$C$4)/$C$10),0) -> 0.22276093 | K15: =IFERROR(IF($C$4="All Portfolios", SUMIFS(Positions!$E$2:$E$644,Positions!$R$2:$R$644,Table14[[#This Row],[WAL]])/$C$11, SUMIFS(Positions!$E$2:$E$644,Positions!$R$2:$R$644,Table14[[#This Row],[WAL]],Positions!$M$2:$M$644,$C$4)/$C$11),0) -> 0.22537175 | M15: 7+ | N15: =IFERROR(IF($C$4="All Portfolios", SUMIFS(Positions!$D$2:$D$644,Positions!$S$2:$S$644,Table15[[#This Row],[Coupon]])/$C$10, SUMIFS(Positions!$D$2:$D$644,Positions!$S$2:$S$644,Table15[[#This Row],[Coupon]],Positions!$M$2:$M$644,$C$4)/$C$10),0) -> 11.052686 | O15: =IFERROR(IF($C$4="All Portfolios", SUMIFS(Positions!$E$2:$E$644,Positions!$S$2:$S$644,Table15[[#This Row],[Coupon]])/$C$11, SUMIFS(Positions!$E$2:$E$644,Positions!$S$2:$S$644,Table15[[#This Row],[Coupon]],Positions!$M$2:$M$644,$C$4)/$C$11),0) -> 10.974791
B16: Number of Issuers | C16: =G37 -> 9 | E16: CCC | F16: =IFERROR(IF($C$4="All Portfolios", SUMIFS(Positions!$D$2:$D$644,Positions!$Q$2:$Q$644,Table13[[#This Row],[Tranche Rating]])/$C$10, SUMIFS(Positions!$D$2:$D$644,Positions!$Q$2:$Q$644,Table13[[#This Row],[Tranche Rating]],Positions!$M$2:$M$644,$C$4)/$C$10),0) -> 0.059617665 | G16: =IFERROR(IF($C$4="All Portfolios", SUMIFS(Positions!$E$2:$E$644,Positions!$Q$2:$Q$644,Table13[[#This Row],[Tranche Rating]])/$C$11, SUMIFS(Positions!$E$2:$E$644,Positions!$Q$2:$Q$644,Table13[[#This Row],[Tranche Rating]],Positions!$M$2:$M$644,$C$4)/$C$11),0) -> 0.039525865 | I16: unknown | J16: =IFERROR(IF($C$4="All Portfolios", SUMIFS(Positions!$D$2:$D$644,Positions!$R$2:$R$644,Table14[[#This Row],[WAL]])/$C$10, SUMIFS(Positions!$D$2:$D$644,Positions!$R$2:$R$644,Table14[[#This Row],[WAL]],Positions!$M$2:$M$644,$C$4)/$C$10),0) -> 0.1134316 | K16: =IFERROR(IF($C$4="All Portfolios", SUMIFS(Positions!$E$2:$E$644,Positions!$R$2:$R$644,Table14[[#This Row],[WAL]])/$C$11, SUMIFS(Positions!$E$2:$E$644,Positions!$R$2:$R$644,Table14[[#This Row],[WAL]],Positions!$M$2:$M$644,$C$4)/$C$11),0) -> 0.11248594 | M16: Total | N16: =SUBTOTAL(109,Table15[Portfolio % CF]) -> 13.340753 | O16: =SUBTOTAL(109,Table15[Portfolio % MV]) -> 13.237188
B17: Number of Managers | C17: =COUNTA(tbl_report_manager[CLO/ABS Debt]) -> 9 | E17: NR | F17: =IFERROR(IF($C$4="All Portfolios", SUMIFS(Positions!$D$2:$D$644,Positions!$Q$2:$Q$644,Table13[[#This Row],[Tranche Rating]])/$C$10, SUMIFS(Positions!$D$2:$D$644,Positions!$Q$2:$Q$644,Table13[[#This Row],[Tranche Rating]],Positions!$M$2:$M$644,$C$4)/$C$10),0) -> 0.048401152 | G17: =IFERROR(IF($C$4="All Portfolios", SUMIFS(Positions!$E$2:$E$644,Positions!$Q$2:$Q$644,Table13[[#This Row],[Tranche Rating]])/$C$11, SUMIFS(Positions!$E$2:$E$644,Positions!$Q$2:$Q$644,Table13[[#This Row],[Tranche Rating]],Positions!$M$2:$M$644,$C$4)/$C$11),0) -> 0.048206781 | I17: Total | J17: =SUBTOTAL(109,Table14[Portfolio % CF]) -> 13.340753 | K17: =SUBTOTAL(109,Table14[Portfolio % MV]) -> 13.237188
B18: Number of Cusips | C18: =H37 -> 46 | E18: Total | F18: =SUBTOTAL(109,Table13[Portfolio % CF]) -> 13.340753 | G18: =SUBTOTAL(109,Table13[Portfolio % MV]) -> 13.237188
B22: Holdings Summary
B23: Tranche Rating | C23: WA Coupon | D23: WA WAL | E23: Current Face | F23: Market Value | G23: Market Price
B24: CLO/ABS Debt - AAA | C24: =IFERROR(SUMPRODUCT(tbl_hold_aaa[Coupon],tbl_hold_aaa[Current Face])/SUM(tbl_hold_aaa[Current Face]),0) -> 0 | D24: =IFERROR(SUMPRODUCT(tbl_hold_aaa[WAL],tbl_hold_aaa[Current Face])/SUM(tbl_hold_aaa[Current Face]),0) -> 0 | E24: =SUM(tbl_hold_aaa[Current Face]) -> 0 | F24: =SUM(tbl_hold_aaa[Market Value]) -> 0 | G24: =IFERROR(Report!$F24/Report!$E24,0) -> 0
B25: CLO/ABS Debt - AA | C25: =IFERROR(SUMPRODUCT(tbl_hold_aa[Coupon],tbl_hold_aa[Current Face])/SUM(tbl_hold_aa[Current Face]),0) -> 2.9180759 | D25: =IFERROR(SUMPRODUCT(tbl_hold_aa[WAL],tbl_hold_aa[Current Face])/SUM(tbl_hold_aa[Current Face]),0) -> 0.29317174 | E25: =SUM(tbl_hold_aa[Current Face]) -> 16217037 | F25: =SUM(tbl_hold_aa[Market Value]) -> 16168578 | G25: =IFERROR(Report!$F25/Report!$E25,0) -> 0.99701182
B26: CLO/ABS Debt - A | C26: =IFERROR(SUMPRODUCT(tbl_hold_a[Coupon],tbl_hold_a[Current Face])/SUM(tbl_hold_a[Current Face]),0) -> 6.3981943 | D26: =IFERROR(SUMPRODUCT(tbl_hold_a[WAL],tbl_hold_a[Current Face])/SUM(tbl_hold_a[Current Face]),0) -> 8.4412285 | E26: =SUM(tbl_hold_a[Current Face]) -> 4977000 | F26: =SUM(tbl_hold_a[Market Value]) -> 5000885.4 | G26: =IFERROR(Report!$F26/Report!$E26,0) -> 1.0047992
B27: CLO/ABS Debt - BBB | C27: =IFERROR(SUMPRODUCT(tbl_hold_bbb[Coupon],tbl_hold_bbb[Current Face])/SUM(tbl_hold_bbb[Current Face]),0) -> 7.37046 | D27: =IFERROR(SUMPRODUCT(tbl_hold_bbb[WAL],tbl_hold_bbb[Current Face])/SUM(tbl_hold_bbb[Current Face]),0) -> 9.2339746 | E27: =SUM(tbl_hold_bbb[Current Face]) -> 3500000 | F27: =SUM(tbl_hold_bbb[Market Value]) -> 3514199.5 | G27: =IFERROR(Report!$F27/Report!$E27,0) -> 1.004057
B28: CLO/ABS Debt - BB | C28: =IFERROR(SUMPRODUCT(tbl_hold_bb[Coupon],tbl_hold_bb[Current Face])/SUM(tbl_hold_bb[Current Face]),0) -> 10.93549 | D28: =IFERROR(SUMPRODUCT(tbl_hold_bb[WAL],tbl_hold_bb[Current Face])/SUM(tbl_hold_bb[Current Face]),0) -> 10.114243 | E28: =SUM(tbl_hold_bb[Current Face]) -> 4500000 | F28: =SUM(tbl_hold_bb[Market Value]) -> 4538146.5 | G28: =IFERROR(Report!$F28/Report!$E28,0) -> 1.008477
B29: CLO/ABS Debt - B | C29: =IFERROR(SUMPRODUCT(tbl_hold_b[Coupon],tbl_hold_b[Current Face])/SUM(tbl_hold_b[Current Face]),0) -> 10.540353 | D29: =IFERROR(SUMPRODUCT(tbl_hold_b[WAL],tbl_hold_b[Current Face])/SUM(tbl_hold_b[Current Face]),0) -> 3.9801655 | E29: =SUM(tbl_hold_b[Current Face]) -> 40632177 | F29: =SUM(tbl_hold_b[Market Value]) -> 40257845 | G29: =IFERROR(Report!$F29/Report!$E29,0) -> 0.9907873
B30: CLO/ABS Debt - CCC | C30: =IFERROR(SUMPRODUCT(tbl_hold_ccc[Coupon],tbl_hold_ccc[Current Face])/SUM(tbl_hold_ccc[Current Face]),0) -> 13.0871 | D30: =IFERROR(SUMPRODUCT(tbl_hold_ccc[WAL],tbl_hold_ccc[Current Face])/SUM(tbl_hold_ccc[Current Face]),0) -> 5.0227397 | E30: =SUM(tbl_hold_ccc[Current Face]) -> 10827000 | F30: =SUM(tbl_hold_ccc[Market Value]) -> 7219140.5 | G30: =IFERROR(Report!$F30/Report!$E30,0) -> 0.666772
B31: CLO/ABS Debt - NR | C31: =IFERROR(SUMPRODUCT(tbl_hold_nr[Coupon],tbl_hold_nr[Current Face])/SUM(tbl_hold_nr[Current Face]),0) -> 7.42549 | D31: =IFERROR(SUMPRODUCT(tbl_hold_nr[WAL],tbl_hold_nr[Current Face])/SUM(tbl_hold_nr[Current Face]),0) -> 8.7084859 | E31: =SUM(tbl_hold_nr[Current Face]) -> 8790000 | F31: =SUM(tbl_hold_nr[Market Value]) -> 8804652.9 | G31: =IFERROR(Report!$F31/Report!$E31,0) -> 1.001667
B32: Total | C32: =IFERROR(SUMPRODUCT(Report!$C$24:$C$31,Report!$E$24:$E$31)/Report!$E$32,0) -> 8.8258707 | D32: =IFERROR(SUMPRODUCT(Report!$D$24:$D$31,Report!$E$24:$E$31)/Report!$E$32,0) -> 4.6649817 | E32: =SUBTOTAL(109,Report!$E$24:$E$31) -> 89443214 | F32: =SUBTOTAL(109,Report!$F$24:$F$31) -> 85503447 | G32: =IFERROR(Report!$F$32/Report!$E$32,0) -> 0.95595231
B36: Top Exposure by Manager
B37: Summary of Manager Total | C37: =SUM(tbl_report_manager[Current Face]) -> 181607248 | D37: =SUM(tbl_report_manager[Market Value]) -> 1.8264345e+08 | E37: =SUM(tbl_report_manager[Current Face %]) -> 1 | F37: =SUM(tbl_report_manager[Market Value %]) -> 1 | G37: =SUM(tbl_report_manager[No. of Issuers]) -> 9 | H37: =SUM(tbl_report_manager[No. of Cusips]) -> 46 | I37: =SUM(tbl_report_manager[No. of Positions]) -> 58
B38: CLO/ABS Debt | C38: Current Face | D38: Market Value | E38: Current Face % | F38: Market Value % | G38: No. of Issuers | H38: No. of Cusips | I38: No. of Positions
B39: AGL CLO Credit Management | C39: =IF($C$4="All Portfolios", SUMIFS(Positions!$D$2:$D$644,Positions!$O$2:$O$644, tbl_report_manager[[#This Row],[CLO/ABS Debt]]), SUMIFS(Positions!$D$2:$D$644, Positions!$M$2:$M$644, $C$4,Positions!$O$2:$O$644, tbl_report_manager[[#This Row],[CLO/ABS Debt]])) -> 23121733 | D39: =IF($C$4="All Portfolios", SUMIFS(Positions!$E$2:$E$644,Positions!$O$2:$O$644, tbl_report_manager[[#This Row],[CLO/ABS Debt]]), SUMIFS(Positions!$E$2:$E$644, Positions!$M$2:$M$644, $C$4,Positions!$O$2:$O$644, tbl_report_manager[[#This Row],[CLO/ABS Debt]])) -> 23256405 | E39: =IFERROR(tbl_report_manager[[#This Row],[Current Face]]/$C$37,0) -> 0.12731724 | F39: =IFERROR(tbl_report_manager[[#This Row],[Market Value]]/$D$37,0) -> 0.12733227 | G39: {=IF($C$4="All Portfolios", COUNTA(_xlfn.UNIQUE(_xlfn._xlws.FILTER(Positions!$G$2:$G$644,Positions!$O$2:$O$644= tbl_report_manager[[#This Row],[CLO/ABS Debt]]))), COUNTA(_xlfn.UNIQUE(_xlfn._xlws.FILTER(Positions!$G$2:$G$644, (Positions!$O$2:$O$644= tbl_report_manager[[#This Row],[CLO/ABS Debt]])*(Positions!$M$2:$M$644= $C$4)))) )} -> 1 | H39: {=IF($C$4="All Portfolios", COUNTA(_xlfn.UNIQUE(_xlfn._xlws.FILTER(Positions!$C$2:$C$644,Positions!$O$2:$O$644 = tbl_report_manager[[#This Row],[CLO/ABS Debt]]))), COUNTA(_xlfn.UNIQUE(_xlfn._xlws.FILTER(Positions!$C$2:$C$644, (Positions!$O$2:$O$644 = tbl_report_manager[[#This Row],[CLO/ABS Debt]])*(Positions!$M$2:$M$644= $C$4)))) )} -> 7 | I39: =IF($C$4="All Portfolios", COUNTIFS(Positions!$O$2:$O$644, tbl_report_manager[[#This Row],[CLO/ABS Debt]]), COUNTIFS(Positions!$M$2:$M$644, $C$4,Positions!$O$2:$O$644, tbl_report_manager[[#This Row],[CLO/ABS Debt]]) ) -> 7
B40: AXA Investment Managers | C40: =IF($C$4="All Portfolios", SUMIFS(Positions!$D$2:$D$644,Positions!$O$2:$O$644, tbl_report_manager[[#This Row],[CLO/ABS Debt]]), SUMIFS(Positions!$D$2:$D$644, Positions!$M$2:$M$644, $C$4,Positions!$O$2:$O$644, tbl_report_manager[[#This Row],[CLO/ABS Debt]])) -> 0 | D40: =IF($C$4="All Portfolios", SUMIFS(Positions!$E$2:$E$644,Positions!$O$2:$O$644, tbl_report_manager[[#This Row],[CLO/ABS Debt]]), SUMIFS(Positions!$E$2:$E$644, Positions!$M$2:$M$644, $C$4,Positions!$O$2:$O$644, tbl_report_manager[[#This Row],[CLO/ABS Debt]])) -> 0 | E40: =IFERROR(tbl_report_manager[[#This Row],[Current Face]]/$C$37,0) -> 0 | F40: =IFERROR(tbl_report_manager[[#This Row],[Market Value]]/$D$37,0) -> 0 | G40: {=IF($C$4="All Portfolios", COUNTA(_xlfn.UNIQUE(_xlfn._xlws.FILTER(Positions!$G$2:$G$644,Positions!$O$2:$O$644= tbl_report_manager[[#This Row],[CLO/ABS Debt]]))), COUNTA(_xlfn.UNIQUE(_xlfn._xlws.FILTER(Positions!$G$2:$G$644, (Positions!$O$2:$O$644= tbl_report_manager[[#This Row],[CLO/ABS Debt]])*(Positions!$M$2:$M$644= $C$4)))) )} -> 1 | H40: {=IF($C$4="All Portfolios", COUNTA(_xlfn.UNIQUE(_xlfn._xlws.FILTER(Positions!$C$2:$C$644,Positions!$O$2:$O$644 = tbl_report_manager[[#This Row],[CLO/ABS Debt]]))), COUNTA(_xlfn.UNIQUE(_xlfn._xlws.FILTER(Positions!$C$2:$C$644, (Positions!$O$2:$O$644 = tbl_report_manager[[#This Row],[CLO/ABS Debt]])*(Positions!$M$2:$M$644= $C$4)))) )} -> 1 | I40: =IF($C$4="All Portfolios", COUNTIFS(Positions!$O$2:$O$644, tbl_report_manager[[#This Row],[CLO/ABS Debt]]), COUNTIFS(Positions!$M$2:$M$644, $C$4,Positions!$O$2:$O$644, tbl_report_manager[[#This Row],[CLO/ABS Debt]]) ) -> 0
B41: Anchorage Collateral Management | C41: =IF($C$4="All Portfolios", SUMIFS(Positions!$D$2:$D$644,Positions!$O$2:$O$644, tbl_report_manager[[#This Row],[CLO/ABS Debt]]), SUMIFS(Positions!$D$2:$D$644, Positions!$M$2:$M$644, $C$4,Positions!$O$2:$O$644, tbl_report_manager[[#This Row],[CLO/ABS Debt]])) -> 19545000 | D41: =IF($C$4="All Portfolios", SUMIFS(Positions!$E$2:$E$644,Positions!$O$2:$O$644, tbl_report_manager[[#This Row],[CLO/ABS Debt]]), SUMIFS(Positions!$E$2:$E$644, Positions!$M$2:$M$644, $C$4,Positions!$O$2:$O$644, tbl_report_manager[[#This Row],[CLO/ABS Debt]])) -> 19660145 | E41: =IFERROR(tbl_report_manager[[#This Row],[Current Face]]/$C$37,0) -> 0.10762236 | F41: =IFERROR(tbl_report_manager[[#This Row],[Market Value]]/$D$37,0) -> 0.10764221 | G41: {=IF($C$4="All Portfolios", COUNTA(_xlfn.UNIQUE(_xlfn._xlws.FILTER(Positions!$G$2:$G$644,Positions!$O$2:$O$644= tbl_report_manager[[#This Row],[CLO/ABS Debt]]))), COUNTA(_xlfn.UNIQUE(_xlfn._xlws.FILTER(Positions!$G$2:$G$644, (Positions!$O$2:$O$644= tbl_report_manager[[#This Row],[CLO/ABS Debt]])*(Positions!$M$2:$M$644= $C$4)))) )} -> 1 | H41: {=IF($C$4="All Portfolios", COUNTA(_xlfn.UNIQUE(_xlfn._xlws.FILTER(Positions!$C$2:$C$644,Positions!$O$2:$O$644 = tbl_report_manager[[#This Row],[CLO/ABS Debt]]))), COUNTA(_xlfn.UNIQUE(_xlfn._xlws.FILTER(Positions!$C$2:$C$644, (Positions!$O$2:$O$644 = tbl_report_manager[[#This Row],[CLO/ABS Debt]])*(Positions!$M$2:$M$644= $C$4)))) )} -> 5 | I41: =IF($C$4="All Portfolios", COUNTIFS(Positions!$O$2:$O$644, tbl_report_manager[[#This Row],[CLO/ABS Debt]]), COUNTIFS(Positions!$M$2:$M$644, $C$4,Positions!$O$2:$O$644, tbl_report_manager[[#This Row],[CLO/ABS Debt]]) ) -> 8
B42: CVC Credit Partners | C42: =IF($C$4="All Portfolios", SUMIFS(Positions!$D$2:$D$644,Positions!$O$2:$O$644, tbl_report_manager[[#This Row],[CLO/ABS Debt]]), SUMIFS(Positions!$D$2:$D$644, Positions!$M$2:$M$644, $C$4,Positions!$O$2:$O$644, tbl_report_manager[[#This Row],[CLO/ABS Debt]])) -> 42004000 | D42: =IF($C$4="All Portfolios", SUMIFS(Positions!$E$2:$E$644,Positions!$O$2:$O$644, tbl_report_manager[[#This Row],[CLO/ABS Debt]]), SUMIFS(Positions!$E$2:$E$644, Positions!$M$2:$M$644, $C$4,Positions!$O$2:$O$644, tbl_report_manager[[#This Row],[CLO/ABS Debt]])) -> 42289257 | E42: =IFERROR(tbl_report_manager[[#This Row],[Current Face]]/$C$37,0) -> 0.23129033 | F42: =IFERROR(tbl_report_manager[[#This Row],[Market Value]]/$D$37,0) -> 0.23153996 | G42: {=IF($C$4="All Portfolios", COUNTA(_xlfn.UNIQUE(_xlfn._xlws.FILTER(Positions!$G$2:$G$644,Positions!$O$2:$O$644= tbl_report_manager[[#This Row],[CLO/ABS Debt]]))), COUNTA(_xlfn.UNIQUE(_xlfn._xlws.FILTER(Positions!$G$2:$G$644, (Positions!$O$2:$O$644= tbl_report_manager[[#This Row],[CLO/ABS Debt]])*(Positions!$M$2:$M$644= $C$4)))) )} -> 1 | H42: {=IF($C$4="All Portfolios", COUNTA(_xlfn.UNIQUE(_xlfn._xlws.FILTER(Positions!$C$2:$C$644,Positions!$O$2:$O$644 = tbl_report_manager[[#This Row],[CLO/ABS Debt]]))), COUNTA(_xlfn.UNIQUE(_xlfn._xlws.FILTER(Positions!$C$2:$C$644, (Positions!$O$2:$O$644 = tbl_report_manager[[#This Row],[CLO/ABS Debt]])*(Positions!$M$2:$M$644= $C$4)))) )} -> 12 | I42: =IF($C$4="All Portfolios", COUNTIFS(Positions!$O$2:$O$644, tbl_report_manager[[#This Row],[CLO/ABS Debt]]), COUNTIFS(Positions!$M$2:$M$644, $C$4,Positions!$O$2:$O$644, tbl_report_manager[[#This Row],[CLO/ABS Debt]]) ) -> 18
B43: Ares CLO Management | C43: =IF($C$4="All Portfolios", SUMIFS(Positions!$D$2:$D$644,Positions!$O$2:$O$644, tbl_report_manager[[#This Row],[CLO/ABS Debt]]), SUMIFS(Positions!$D$2:$D$644, Positions!$M$2:$M$644, $C$4,Positions!$O$2:$O$644, tbl_report_manager[[#This Row],[CLO/ABS Debt]])) -> 81556515 | D43: =IF($C$4="All Portfolios", SUMIFS(Positions!$E$2:$E$644,Positions!$O$2:$O$644, tbl_report_manager[[#This Row],[CLO/ABS Debt]]), SUMIFS(Positions!$E$2:$E$644, Positions!$M$2:$M$644, $C$4,Positions!$O$2:$O$644, tbl_report_manager[[#This Row],[CLO/ABS Debt]])) -> 82033270 | E43: =IFERROR(tbl_report_manager[[#This Row],[Current Face]]/$C$37,0) -> 0.44908183 | F43: =IFERROR(tbl_report_manager[[#This Row],[Market Value]]/$D$37,0) -> 0.44914432 | G43: {=IF($C$4="All Portfolios", COUNTA(_xlfn.UNIQUE(_xlfn._xlws.FILTER(Positions!$G$2:$G$644,Positions!$O$2:$O$644= tbl_report_manager[[#This Row],[CLO/ABS Debt]]))), COUNTA(_xlfn.UNIQUE(_xlfn._xlws.FILTER(Positions!$G$2:$G$644, (Positions!$O$2:$O$644= tbl_report_manager[[#This Row],[CLO/ABS Debt]])*(Positions!$M$2:$M$644= $C$4)))) )} -> 1 | H43: {=IF($C$4="All Portfolios", COUNTA(_xlfn.UNIQUE(_xlfn._xlws.FILTER(Positions!$C$2:$C$644,Positions!$O$2:$O$644 = tbl_report_manager[[#This Row],[CLO/ABS Debt]]))), COUNTA(_xlfn.UNIQUE(_xlfn._xlws.FILTER(Positions!$C$2:$C$644, (Positions!$O$2:$O$644 = tbl_report_manager[[#This Row],[CLO/ABS Debt]])*(Positions!$M$2:$M$644= $C$4)))) )} -> 15 | I43: =IF($C$4="All Portfolios", COUNTIFS(Positions!$O$2:$O$644, tbl_report_manager[[#This Row],[CLO/ABS Debt]]), COUNTIFS(Positions!$M$2:$M$644, $C$4,Positions!$O$2:$O$644, tbl_report_manager[[#This Row],[CLO/ABS Debt]]) ) -> 21
B44: Arini Loan Management US | C44: =IF($C$4="All Portfolios", SUMIFS(Positions!$D$2:$D$644,Positions!$O$2:$O$644, tbl_report_manager[[#This Row],[CLO/ABS Debt]]), SUMIFS(Positions!$D$2:$D$644, Positions!$M$2:$M$644, $C$4,Positions!$O$2:$O$644, tbl_report_manager[[#This Row],[CLO/ABS Debt]])) -> 3900000 | D44: =IF($C$4="All Portfolios", SUMIFS(Positions!$E$2:$E$644,Positions!$O$2:$O$644, tbl_report_manager[[#This Row],[CLO/ABS Debt]]), SUMIFS(Positions!$E$2:$E$644, Positions!$M$2:$M$644, $C$4,Positions!$O$2:$O$644, tbl_report_manager[[#This Row],[CLO/ABS Debt]])) -> 3915167.1 | E44: =IFERROR(tbl_report_manager[[#This Row],[Current Face]]/$C$37,0) -> 0.021474914 | F44: =IFERROR(tbl_report_manager[[#This Row],[Market Value]]/$D$37,0) -> 0.021436121 | G44: {=IF($C$4="All Portfolios", COUNTA(_xlfn.UNIQUE(_xlfn._xlws.FILTER(Positions!$G$2:$G$644,Positions!$O$2:$O$644= tbl_report_manager[[#This Row],[CLO/ABS Debt]]))), COUNTA(_xlfn.UNIQUE(_xlfn._xlws.FILTER(Positions!$G$2:$G$644, (Positions!$O$2:$O$644= tbl_report_manager[[#This Row],[CLO/ABS Debt]])*(Positions!$M$2:$M$644= $C$4)))) )} -> 1 | H44: {=IF($C$4="All Portfolios", COUNTA(_xlfn.UNIQUE(_xlfn._xlws.FILTER(Positions!$C$2:$C$644,Positions!$O$2:$O$644 = tbl_report_manager[[#This Row],[CLO/ABS Debt]]))), COUNTA(_xlfn.UNIQUE(_xlfn._xlws.FILTER(Positions!$C$2:$C$644, (Positions!$O$2:$O$644 = tbl_report_manager[[#This Row],[CLO/ABS Debt]])*(Positions!$M$2:$M$644= $C$4)))) )} -> 1 | I44: =IF($C$4="All Portfolios", COUNTIFS(Positions!$O$2:$O$644, tbl_report_manager[[#This Row],[CLO/ABS Debt]]), COUNTIFS(Positions!$M$2:$M$644, $C$4,Positions!$O$2:$O$644, tbl_report_manager[[#This Row],[CLO/ABS Debt]]) ) -> 1
B45: Crescent Capital Group | C45: =IF($C$4="All Portfolios", SUMIFS(Positions!$D$2:$D$644,Positions!$O$2:$O$644, tbl_report_manager[[#This Row],[CLO/ABS Debt]]), SUMIFS(Positions!$D$2:$D$644, Positions!$M$2:$M$644, $C$4,Positions!$O$2:$O$644, tbl_report_manager[[#This Row],[CLO/ABS Debt]])) -> 0 | D45: =IF($C$4="All Portfolios", SUMIFS(Positions!$E$2:$E$644,Positions!$O$2:$O$644, tbl_report_manager[[#This Row],[CLO/ABS Debt]]), SUMIFS(Positions!$E$2:$E$644, Positions!$M$2:$M$644, $C$4,Positions!$O$2:$O$644, tbl_report_manager[[#This Row],[CLO/ABS Debt]])) -> 0 | E45: =IFERROR(tbl_report_manager[[#This Row],[Current Face]]/$C$37,0) -> 0 | F45: =IFERROR(tbl_report_manager[[#This Row],[Market Value]]/$D$37,0) -> 0 | G45: {=IF($C$4="All Portfolios", COUNTA(_xlfn.UNIQUE(_xlfn._xlws.FILTER(Positions!$G$2:$G$644,Positions!$O$2:$O$644= tbl_report_manager[[#This Row],[CLO/ABS Debt]]))), COUNTA(_xlfn.UNIQUE(_xlfn._xlws.FILTER(Positions!$G$2:$G$644, (Positions!$O$2:$O$644= tbl_report_manager[[#This Row],[CLO/ABS Debt]])*(Positions!$M$2:$M$644= $C$4)))) )} -> 1 | H45: {=IF($C$4="All Portfolios", COUNTA(_xlfn.UNIQUE(_xlfn._xlws.FILTER(Positions!$C$2:$C$644,Positions!$O$2:$O$644 = tbl_report_manager[[#This Row],[CLO/ABS Debt]]))), COUNTA(_xlfn.UNIQUE(_xlfn._xlws.FILTER(Positions!$C$2:$C$644, (Positions!$O$2:$O$644 = tbl_report_manager[[#This Row],[CLO/ABS Debt]])*(Positions!$M$2:$M$644= $C$4)))) )} -> 1 | I45: =IF($C$4="All Portfolios", COUNTIFS(Positions!$O$2:$O$644, tbl_report_manager[[#This Row],[CLO/ABS Debt]]), COUNTIFS(Positions!$M$2:$M$644, $C$4,Positions!$O$2:$O$644, tbl_report_manager[[#This Row],[CLO/ABS Debt]]) ) -> 0
B46: Blackstone Private Credit Fund | C46: =IF($C$4="All Portfolios", SUMIFS(Positions!$D$2:$D$644,Positions!$O$2:$O$644, tbl_report_manager[[#This Row],[CLO/ABS Debt]]), SUMIFS(Positions!$D$2:$D$644, Positions!$M$2:$M$644, $C$4,Positions!$O$2:$O$644, tbl_report_manager[[#This Row],[CLO/ABS Debt]])) -> 0 | D46: =IF($C$4="All Portfolios", SUMIFS(Positions!$E$2:$E$644,Positions!$O$2:$O$644, tbl_report_manager[[#This Row],[CLO/ABS Debt]]), SUMIFS(Positions!$E$2:$E$644, Positions!$M$2:$M$644, $C$4,Positions!$O$2:$O$644, tbl_report_manager[[#This Row],[CLO/ABS Debt]])) -> 0 | E46: =IFERROR(tbl_report_manager[[#This Row],[Current Face]]/$C$37,0) -> 0 | F46: =IFERROR(tbl_report_manager[[#This Row],[Market Value]]/$D$37,0) -> 0 | G46: {=IF($C$4="All Portfolios", COUNTA(_xlfn.UNIQUE(_xlfn._xlws.FILTER(Positions!$G$2:$G$644,Positions!$O$2:$O$644= tbl_report_manager[[#This Row],[CLO/ABS Debt]]))), COUNTA(_xlfn.UNIQUE(_xlfn._xlws.FILTER(Positions!$G$2:$G$644, (Positions!$O$2:$O$644= tbl_report_manager[[#This Row],[CLO/ABS Debt]])*(Positions!$M$2:$M$644= $C$4)))) )} -> 1 | H46: {=IF($C$4="All Portfolios", COUNTA(_xlfn.UNIQUE(_xlfn._xlws.FILTER(Positions!$C$2:$C$644,Positions!$O$2:$O$644 = tbl_report_manager[[#This Row],[CLO/ABS Debt]]))), COUNTA(_xlfn.UNIQUE(_xlfn._xlws.FILTER(Positions!$C$2:$C$644, (Positions!$O$2:$O$644 = tbl_report_manager[[#This Row],[CLO/ABS Debt]])*(Positions!$M$2:$M$644= $C$4)))) )} -> 1 | I46: =IF($C$4="All Portfolios", COUNTIFS(Positions!$O$2:$O$644, tbl_report_manager[[#This Row],[CLO/ABS Debt]]), COUNTIFS(Positions!$M$2:$M$644, $C$4,Positions!$O$2:$O$644, tbl_report_manager[[#This Row],[CLO/ABS Debt]]) ) -> 0
B47: Bain Capital Credit U.S. CLO Manager II | C47: =IF($C$4="All Portfolios", SUMIFS(Positions!$D$2:$D$644,Positions!$O$2:$O$644, tbl_report_manager[[#This Row],[CLO/ABS Debt]]), SUMIFS(Positions!$D$2:$D$644, Positions!$M$2:$M$644, $C$4,Positions!$O$2:$O$644, tbl_report_manager[[#This Row],[CLO/ABS Debt]])) -> 11480000 | D47: =IF($C$4="All Portfolios", SUMIFS(Positions!$E$2:$E$644,Positions!$O$2:$O$644, tbl_report_manager[[#This Row],[CLO/ABS Debt]]), SUMIFS(Positions!$E$2:$E$644, Positions!$M$2:$M$644, $C$4,Positions!$O$2:$O$644, tbl_report_manager[[#This Row],[CLO/ABS Debt]])) -> 11489209 | E47: =IFERROR(tbl_report_manager[[#This Row],[Current Face]]/$C$37,0) -> 0.063213336 | F47: =IFERROR(tbl_report_manager[[#This Row],[Market Value]]/$D$37,0) -> 0.062905124 | G47: {=IF($C$4="All Portfolios", COUNTA(_xlfn.UNIQUE(_xlfn._xlws.FILTER(Positions!$G$2:$G$644,Positions!$O$2:$O$644= tbl_report_manager[[#This Row],[CLO/ABS Debt]]))), COUNTA(_xlfn.UNIQUE(_xlfn._xlws.FILTER(Positions!$G$2:$G$644, (Positions!$O$2:$O$644= tbl_report_manager[[#This Row],[CLO/ABS Debt]])*(Positions!$M$2:$M$644= $C$4)))) )} -> 1 | H47: {=IF($C$4="All Portfolios", COUNTA(_xlfn.UNIQUE(_xlfn._xlws.FILTER(Positions!$C$2:$C$644,Positions!$O$2:$O$644 = tbl_report_manager[[#This Row],[CLO/ABS Debt]]))), COUNTA(_xlfn.UNIQUE(_xlfn._xlws.FILTER(Positions!$C$2:$C$644, (Positions!$O$2:$O$644 = tbl_report_manager[[#This Row],[CLO/ABS Debt]])*(Positions!$M$2:$M$644= $C$4)))) )} -> 3 | I47: =IF($C$4="All Portfolios", COUNTIFS(Positions!$O$2:$O$644, tbl_report_manager[[#This Row],[CLO/ABS Debt]]), COUNTIFS(Positions!$M$2:$M$644, $C$4,Positions!$O$2:$O$644, tbl_report_manager[[#This Row],[CLO/ABS Debt]]) ) -> 3
B52: Type | C52: Issuer | D52: Security Description | E52: Cusip | F52: Settle Date | G52: Face Value | H52: Tranche Rating
B53: Call | C53: Golub Capital Partners CLO Ltd | D53: GOCAP 2015-24A CR 05-Nov-2029 | E53: 38174YAE5 | F53: 05-05-2025 | G53: =IF($C$4="All Portfolios",-SUMIFS(tbl_rawtran[Quantity],tbl_rawtran[Security ID],E53,tbl_rawtran[Type], "Paydown"),-SUMIFS(tbl_rawtran[Quantity],tbl_rawtran[Portfolio_Name],$C$4,tbl_rawtran[Security ID],E53,tbl_rawtran[Type], "Paydown")) -> 0 | H53: AA
B59: Issuer | C59: Security Description | D59: Cusip | E59: Trade Date | F59: Settle Date | G59: Face Value | H59: Sale Price | I59: Maturity Date | J59: Tranche Rating
B60: Atlas Senior Loan Fund LTD | C60: ATCLO 2019-14A D 20-Jul-2032 | D60: 04942CAL0 | E60: 05-12-2025 | F60: 05-13-2025 | G60: =IF($C$4="All Portfolios",SUMIFS(tbl_rawtran[Quantity],tbl_rawtran[Security ID],D60,tbl_rawtran[Type], "SELL"),SUMIFS(tbl_rawtran[Quantity],tbl_rawtran[Portfolio_Name],$C$4,tbl_rawtran[Security ID],D60,tbl_rawtran[Type], "SELL")) -> -5000000 | H60: 100.075 | I60: 07-20-2032 | J60: BBB
B67: Issuer | C67: Security Description | D67: Cusip | E67: Trade Date | F67: Settle Date | G67: Face Value | H67: Purchase Price | I67: Maturity Date | J67: Tranche Rating
B68: AGL CLO Ltd. | C68: AGL 2023-24A CR 31-Mar-2038 | D68: 00119AAS4 | E68: 05-09-2025 | F68: 05-23-2025 | G68: =IF($C$4="All Portfolios",SUMIFS(tbl_rawtran[Quantity],tbl_rawtran[Security ID],D68,tbl_rawtran[Type], "BUY"),SUMIFS(tbl_rawtran[Quantity],tbl_rawtran[Portfolio_Name],$C$4,tbl_rawtran[Security ID],D68,tbl_rawtran[Type], "BUY")) -> 927000 | H68: 100 | I68: 03-31-2038 | J68: A
B75: Cusip | C75: Issuer | D75: Security Description | E75: Issue Date | F75: Maturity Date | G75: Coupon | H75: Spread | I75: Current Face | J75: Factor | K75: Market Price | L75: Market Value | M75: NRSRO | N75: NRSRO Rating | O75: WAL | P75: Par Sub | Q75: Implied DM | R75: Next Payment Date | S75: Non-Call Date
I76: =IF($C$4="All Portfolios",SUMIFS(Positions!$D$2:$D$644,Positions!$C$2:$C$644,B76),SUMIFS(Positions!$D$2:$D$644,Positions!$M$2:$M$644,$C$4,Positions!$C$2:$C$644,B76)) -> 0 | L76: =IF($C$4="All Portfolios",SUMIFS(Positions!$E$2:$E$644,Positions!$C$2:$C$644,B76),SUMIFS(Positions!$E$2:$E$644,Positions!$M$2:$M$644,$C$4,Positions!$C$2:$C$644,B76)) -> 0
B83: Cusip | C83: Issuer | D83: Security Description | E83: Issue Date | F83: Maturity Date | G83: Coupon | H83: Spread | I83: Current Face | J83: Factor | K83: Market Price | L83: Market Value | M83: NRSRO | N83: NRSRO Rating | O83: WAL | P83: Par Sub | Q83: Implied DM | R83: Next Payment Date | S83: Non-Call Date
B84: 48250RBJ4 | C84: KKR 25 | D84: KKR 12 CR2 15-Oct-2030 | E84: 2018-10-03 | F84: 10-15-2030 | G84: 6.82916 | H84: 251.161 | I84: =IF($C$4="All Portfolios",SUMIFS(Positions!$D$2:$D$644,Positions!$C$2:$C$644,B84),SUMIFS(Positions!$D$2:$D$644,Positions!$M$2:$M$644,$C$4,Positions!$C$2:$C$644,B84)) -> 247037 | J84: 1 | K84: 100.2955 | L84: =IF($C$4="All Portfolios",SUMIFS(Positions!$E$2:$E$644,Positions!$C$2:$C$644,B84),SUMIFS(Positions!$E$2:$E$644,Positions!$M$2:$M$644,$C$4,Positions!$C$2:$C$644,B84)) -> 247766.99 | M84: Moody's | N84: Aa2 | O84: 2.6001601 | P84: 0.37616782 | Q84: 238.32201 | R84: 10-15-2025 | S84: 10-15-2020
B85: 542798AG8 | C85: Blackstone Inc | D85: LNGPT 2017-1A B 17-Jan-2030 | E85: 2017-12-28 | F85: 01-17-2030 | G85: 6.28401 | H85: 196.161 | I85: =IF($C$4="All Portfolios",SUMIFS(Positions!$D$2:$D$644,Positions!$C$2:$C$644,B85),SUMIFS(Positions!$D$2:$D$644,Positions!$M$2:$M$644,$C$4,Positions!$C$2:$C$644,B85)) -> 970000 | J85: 1 | K85: 100.4838 | L85: =IF($C$4="All Portfolios",SUMIFS(Positions!$E$2:$E$644,Positions!$C$2:$C$644,B85),SUMIFS(Positions!$E$2:$E$644,Positions!$M$2:$M$644,$C$4,Positions!$C$2:$C$644,B85)) -> 974692.86 | M85: Moody's | N85: Aa1 | O85: 2.3373505 | P85: 0.38541549 | Q85: 173.29035 | R85: 10-17-2025 | S85: 01-17-2020
B86: 92535VAF9 | C86: Vertical Bridge Holdings LLC | D86: VBTOW 2020-2A A 15-Sep-2050 | E86: 2020-09-24 | F86: 09-15-2050 | G86: 2.636 | I86: =IF($C$4="All Portfolios",SUMIFS(Positions!$D$2:$D$644,Positions!$C$2:$C$644,B86),SUMIFS(Positions!$D$2:$D$644,Positions!$M$2:$M$644,$C$4,Positions!$C$2:$C$644,B86)) -> 15000000 | J86: 1 | K86: 99.640785 | L86: =IF($C$4="All Portfolios",SUMIFS(Positions!$E$2:$E$644,Positions!$C$2:$C$644,B86),SUMIFS(Positions!$E$2:$E$644,Positions!$M$2:$M$644,$C$4,Positions!$C$2:$C$644,B86)) -> 14946118 | M86: DBRS | N86: AAL | O86: 0.12298742 | P86: 0.23715415 | Q86: 657.49227 | R86: 08-15-2025
B93: Cusip | C93: Issuer | D93: Security Description | E93: Issue Date | F93: Maturity Date | G93: Coupon | H93: Spread | I93: Current Face | J93: Factor | K93: Market Price | L93: Market Value | M93: NRSRO | N93: NRSRO Rating | O93: WAL | P93: Par Sub | Q93: Implied DM | R93: Next Payment Date | S93: Non-Call Date
B94: 00119AAS4 | C94: AGL CLO Ltd | D94: AGL 2023-24A CR 31-Mar-2038 | E94: 2025-05-23 | F94: 03-31-2038 | G94: 6.46899 | H94: 215 | I94: =IF($C$4="All Portfolios",SUMIFS(Positions!$D$2:$D$644,Positions!$C$2:$C$644,B94),SUMIFS(Positions!$D$2:$D$644,Positions!$M$2:$M$644,$C$4,Positions!$C$2:$C$644,B94)) -> 927000 | J94: 1 | K94: 100.9195 | L94: =IF($C$4="All Portfolios",SUMIFS(Positions!$E$2:$E$644,Positions!$C$2:$C$644,B94),SUMIFS(Positions!$E$2:$E$644,Positions!$M$2:$M$644,$C$4,Positions!$C$2:$C$644,B94)) -> 935523.77 | M94: Fitch | N94: A | O94: 9.1695377 | P94: 0.17880402 | Q94: 202.15609 | R94: 10-23-2025 | S94: 07-23-2027
B95: 00901AAW7 | C95: Aimco CDO | D95: AIMCO 2019-10A CRR 22-Jul-2037 | E95: 2024-06-12 | F95: 07-22-2037 | G95: 6.38199 | H95: 205 | I95: =IF($C$4="All Portfolios",SUMIFS(Positions!$D$2:$D$644,Positions!$C$2:$C$644,B95),SUMIFS(Positions!$D$2:$D$644,Positions!$M$2:$M$644,$C$4,Positions!$C$2:$C$644,B95)) -> 4050000 | J95: 1 | K95: 100.3793 | L95: =IF($C$4="All Portfolios",SUMIFS(Positions!$E$2:$E$644,Positions!$C$2:$C$644,B95),SUMIFS(Positions!$E$2:$E$644,Positions!$M$2:$M$644,$C$4,Positions!$C$2:$C$644,B95)) -> 4065361.6 | M95: SP | N95: A | O95: 8.2745266 | P95: 0.18026612 | Q95: 199.21467 | R95: 10-22-2025 | S95: 06-12-2026
B102: Cusip | C102: Issuer | D102: Security Description | E102: Issue Date | F102: Maturity Date | G102: Coupon | H102: Spread | I102: Current Face | J102: Factor | K102: Market Price | L102: Market Value | M102: NRSRO | N102: NRSRO Rating | O102: WAL | P102: Par Sub | Q102: Implied DM | R102: Next Payment Date | S102: Non-Call Date
B103: 001210AY9 | C103: AGL CLO Ltd | D103: AGL 2022-19A D1R 21-Jul-2038 | E103: 2025-07-11 | F103: 07-21-2038 | G103: 7.37046 | H103: 305 | I103: =IF($C$4="All Portfolios",SUMIFS(Positions!$D$2:$D$644,Positions!$C$2:$C$644,B103),SUMIFS(Positions!$D$2:$D$644,Positions!$M$2:$M$644,$C$4,Positions!$C$2:$C$644,B103)) -> 3500000 | J103: 1 | K103: 100.4057 | L103: =IF($C$4="All Portfolios",SUMIFS(Positions!$E$2:$E$644,Positions!$C$2:$C$644,B103),SUMIFS(Positions!$E$2:$E$644,Positions!$M$2:$M$644,$C$4,Positions!$C$2:$C$644,B103)) -> 3514199.5 | M103: Fitch | N103: BBB- | O103: 9.2339746 | P103: 0.11770896 | Q103: 299.10923 | R103: 10-21-2025 | S103: 07-21-2027
B110: Cusip | C110: Issuer | D110: Security Description | E110: Issue Date | F110: Maturity Date | G110: Coupon | H110: Spread | I110: Current Face | J110: Factor | K110: Market Price | L110: Market Value | M110: NRSRO | N110: NRSRO Rating | O110: WAL | P110: Par Sub | Q110: Implied DM | R110: Next Payment Date | S110: Non-Call Date
B111: 00119WAG2 | C111: AGL CLO Ltd | D111: AGL 2020-6A ER2 20-Apr-2038 | E111: 2025-04-08 | F111: 04-20-2038 | G111: 10.93549 | H111: 661 | I111: =IF($C$4="All Portfolios",SUMIFS(Positions!$D$2:$D$644,Positions!$C$2:$C$644,B111),SUMIFS(Positions!$D$2:$D$644,Positions!$M$2:$M$644,$C$4,Positions!$C$2:$C$644,B111)) -> 4500000 | J111: 1 | K111: 100.8477 | L111: =IF($C$4="All Portfolios",SUMIFS(Positions!$E$2:$E$644,Positions!$C$2:$C$644,B111),SUMIFS(Positions!$E$2:$E$644,Positions!$M$2:$M$644,$C$4,Positions!$C$2:$C$644,B111)) -> 4538146.5 | M111: Fitch | N111: BB- | O111: 10.114243 | P111: 0.075380415 | Q111: 647.40377 | R111: 10-20-2025 | S111: 04-20-2027
B118: Cusip | C118: Issuer | D118: Security Description | E118: Issue Date | F118: Maturity Date | G118: Coupon | H118: Spread | I118: Current Face | J118: Factor | K118: Market Price | L118: Market Value | M118: NRSRO | N118: NRSRO Rating | O118: WAL | P118: Par Sub | Q118: Implied DM | R118: Next Payment Date | S118: Non-Call Date
B119: 91734KAL1 | C119: Blackrock Baker CLO 2021-1, Ltd | D119: BLKMM 2021-8A E 15-Jan-2034 | E119: 2021-12-22 | F119: 01-15-2034 | G119: 12.57916 | H119: 826.161 | I119: =IF($C$4="All Portfolios",SUMIFS(Positions!$D$2:$D$644,Positions!$C$2:$C$644,B119),SUMIFS(Positions!$D$2:$D$644,Positions!$M$2:$M$644,$C$4,Positions!$C$2:$C$644,B119)) -> 5577177.1 | J119: 1.140257 | K119: 96.257 | L119: =IF($C$4="All Portfolios",SUMIFS(Positions!$E$2:$E$644,Positions!$C$2:$C$644,B119),SUMIFS(Positions!$E$2:$E$644,Positions!$M$2:$M$644,$C$4,Positions!$C$2:$C$644,B119)) -> 5368423.4 | M119: SP | N119: B- | O119: 5.347515 | P119: 0.045584748 | Q119: 917.90243 | R119: 10-15-2025 | S119: 01-15-2024
B120: 12482GAC0 | C120: CBAM Ltd | D120: CBAM 2018-7A E 20-Jul-2031 | E120: 2018-07-12 | F120: 07-20-2031 | G120: 10.0871 | H120: 576.161 | I120: =IF($C$4="All Portfolios",SUMIFS(Positions!$D$2:$D$644,Positions!$C$2:$C$644,B120),SUMIFS(Positions!$D$2:$D$644,Positions!$M$2:$M$644,$C$4,Positions!$C$2:$C$644,B120)) -> 33750000 | J120: 1 | K120: 99.4272 | L120: =IF($C$4="All Portfolios",SUMIFS(Positions!$E$2:$E$644,Positions!$C$2:$C$644,B120),SUMIFS(Positions!$E$2:$E$644,Positions!$M$2:$M$644,$C$4,Positions!$C$2:$C$644,B120)) -> 33556680 | M120: Moody's | N120: B1 | O120: 3.7449949 | P120: 0.083278187 | Q120: 594.17199 | R120: 10-20-2025 | S120: 07-20-2020
B121: 510803AA7 | C121: THL Credit Lake Shore MM CLO L | D121: THLLS 2019-1A ER 15-Apr-2033 | E121: 2021-05-26 | F121: 04-15-2033 | G121: 13.54916 | H121: 923.161 | I121: =IF($C$4="All Portfolios",SUMIFS(Positions!$D$2:$D$644,Positions!$C$2:$C$644,B121),SUMIFS(Positions!$D$2:$D$644,Positions!$M$2:$M$644,$C$4,Positions!$C$2:$C$644,B121)) -> 1305000 | J121: 1 | K121: 102.1258 | L121: =IF($C$4="All Portfolios",SUMIFS(Positions!$E$2:$E$644,Positions!$C$2:$C$644,B121),SUMIFS(Positions!$E$2:$E$644,Positions!$M$2:$M$644,$C$4,Positions!$C$2:$C$644,B121)) -> 1332741.7 | M121: Moody's | N121: B1 | O121: 4.2185234 | P121: 0.1012363 | Q121: 949.88685 | R121: 10-15-2025 | S121: 04-15-2023
B128: Cusip | C128: Issuer | D128: Security Description | E128: Issue Date | F128: Maturity Date | G128: Coupon | H128: Spread | I128: Current Face | J128: Factor | K128: Market Price | L128: Market Value | M128: NRSRO | N128: NRSRO Rating | O128: WAL | P128: Par Sub | Q128: Implied DM | R128: Next Payment Date | S128: Non-Call Date
B129: 87246LAJ3 | C129: Wind River CLO Ltd | D129: WINDR 2015-1A FR 20-Oct-2030 | E129: 2018-11-21 | F129: 10-20-2030 | G129: 13.0871 | H129: 876.161 | I129: =IF($C$4="All Portfolios",SUMIFS(Positions!$D$2:$D$644,Positions!$C$2:$C$644,B129),SUMIFS(Positions!$D$2:$D$644,Positions!$M$2:$M$644,$C$4,Positions!$C$2:$C$644,B129)) -> 10827000 | J129: 1 | K129: 66.6772 | L129: =IF($C$4="All Portfolios",SUMIFS(Positions!$E$2:$E$644,Positions!$C$2:$C$644,B129),SUMIFS(Positions!$E$2:$E$644,Positions!$M$2:$M$644,$C$4,Positions!$C$2:$C$644,B129)) -> 7219140.5 | M129: Moody's | N129: Caa2 | O129: 5.0227397 | P129: 0.036431031 | Q129: 1506.9467 | R129: 10-20-2025 | S129: 10-10-2024
B136: Cusip | C136: Issuer | D136: Security Description | E136: Issue Date | F136: Maturity Date | G136: Coupon | H136: Spread | I136: Current Face | J136: Factor | K136: Market Price | L136: Market Value | M136: NRSRO | N136: NRSRO Rating | O136: WAL | P136: Par Sub | Q136: Implied DM | R136: Next Payment Date | S136: Non-Call Date
B137: 33883PAY3 | C137: Flatiron CLO Ltd | D137: FLAT 2021-1A D1R 19-Oct-2037 | E137: 2024-09-12 | F137: 10-19-2037 | G137: 7.42549 | H137: 310 | I137: =IF($C$4="All Portfolios",SUMIFS(Positions!$D$2:$D$644,Positions!$C$2:$C$644,B137),SUMIFS(Positions!$D$2:$D$644,Positions!$M$2:$M$644,$C$4,Positions!$C$2:$C$644,B137)) -> 8790000 | J137: 1 | K137: 100.1667 | L137: =IF($C$4="All Portfolios",SUMIFS(Positions!$E$2:$E$644,Positions!$C$2:$C$644,B137),SUMIFS(Positions!$E$2:$E$644,Positions!$M$2:$M$644,$C$4,Positions!$C$2:$C$644,B137)) -> 8804652.9 | M137: Moody's | N137: WR | O137: 8.7084859 | P137: 0.11350431 | Q137: 307.36382 | R137: 10-19-2025 | S137: 10-19-2026

Sheet ValidationLists
A1: All Portfolios
A2: 44G8/813/IG CLO FWH
A3: 44G9/814/ABS FWH
A4: 44H1/815/Atypical FWH
A5: 44I4/816/HY CLOs FWH
A6: P44I5/817/HY CLOs OC
A7: 44J6/821/IG CLO OC
A8: 44J7/822/ABS OC
A9: 44J5/823/Atypical OC

Sheet Transactions
A1: Portfolio | B1: Security ID | C1: Security Description | D1: Trade Date | E1: Settle Date | F1: Maturity Date | G1: Quantity | H1: Price | I1: Cost Proceeds | J1: Coupon Rate | K1: Portfolio_Name | L1: Type
A2: SBL_813_813 | B2: 00119AAG0 | C2: AGL 2023-24A C 25-Jul-2036 | D2: 05-23-2025 | E2: 05-23-2025 | F2: 07-25-2036 | G2: -927000 | H2: 100 | I2: -927000 | J2: 7.78177 | K2: 44G8/813/IG CLO FWH | L2: Paydown
A3: SBL_813_813 | B3: 00119AAJ4 | C3: AGL 2023-24A D 25-Jul-2036 | D3: 05-23-2025 | E3: 05-23-2025 | F3: 07-25-2036 | G3: -1043000 | H3: 100 | I3: -1043000 | J3: 9.78177 | K3: 44G8/813/IG CLO FWH | L3: Paydown
A4: SBL_813_813 | B4: 00119AAS4 | C4: AGL 2023-24A CR 31-Mar-2038 | D4: 05-09-2025 | E4: 05-23-2025 | F4: 03-31-2038 | G4: 927000 | H4: 100 | I4: 927000 | J4: 6.46899 | K4: 44G8/813/IG CLO FWH | L4: BUY
A5: SBL_813_813 | B5: 00119AAU9 | C5: AGL 2023-24A D1R 31-Mar-2038 | D5: 05-09-2025 | E5: 05-23-2025 | F5: 03-31-2038 | G5: 1043000 | H5: 100 | I5: 1043000 | J5: 7.61899 | K5: 44G8/813/IG CLO FWH | L5: BUY
A6: SBL_813_813 | B6: 00120NAG9 | C6: AGL 2023-25A D 21-Jul-2036 | D6: 06-25-2025 | E6: 06-25-2025 | F6: 07-21-2036 | G6: -5951733 | H6: 100 | I6: -5951733 | J6: 9.57238 | K6: 44G8/813/IG CLO FWH | L6: Paydown
A7: SBL_813_813 | B7: 00120NAU8 | C7: AGL 2023-25A D1R 21-Jul-2038 | D7: 06-11-2025 | E7: 06-25-2025 | F7: 07-21-2038 | G7: 5951733 | H7: 100 | I7: 5951733 | J7: 7.22322 | K7: 44G8/813/IG CLO FWH | L7: BUY
A8: SBL_813_813 | B8: 001210AY9 | C8: AGL 2022-19A D1R 21-Jul-2038 | D8: 06-27-2025 | E8: 07-11-2025 | F8: 07-21-2038 | G8: 3500000 | H8: 100 | I8: 3500000 | J8: 7.37046 | K8: 44G8/813/IG CLO FWH | L8: BUY
A9: SBL_813_813 | B9: 01750WAJ8 | C9: ALLEG 2021-1A D 20-Jul-2034 | D9: 07-21-2025 | E9: 07-21-2025 | F9: 07-20-2034 | G9: -3500000 | H9: 100 | I9: -3500000 | J9: 7.73108 | K9: 44G8/813/IG CLO FWH | L9: Paydown
A10: SBL_813_813 | B10: 03328QCC3 | C10: ANCHC 2015-6A DR4 22-Jul-2038 | D10: 07-28-2025 | E10: 08-11-2025 | F10: 07-22-2038 | G10: 7160000 | H10: 100 | I10: 7160000 | J10: 7.32039 | K10: 44G8/813/IG CLO FWH | L10: BUY
A11: SBL_816_816 | B11: 03770JAA8 | C11: APID 2023-43A E 25-Apr-2035 | D11: 06-18-2025 | E11: 06-18-2025 | F11: 04-25-2035 | G11: -2700000 | H11: 100 | I11: -2700000 | J11: 36.09531 | K11: 44I4/816/HY CLOs FWH | L11: Paydown
A12: SBL_816_816 | B12: 03770JAG5 | C12: APID 2023-43A ER 25-Jul-2038 | D12: 05-28-2025 | E12: 06-18-2025 | F12: 07-25-2038 | G12: 2700000 | H12: 100 | I12: 2700000 | J12: 9.66447 | K12: 44I4/816/HY CLOs FWH | L12: BUY
A13: SBL_813_813 | B13: 03770MAG8 | C13: APID 2023-45A D 26-Apr-2036 | D13: 07-02-2025 | E13: 07-02-2025 | F13: 04-26-2036 | G13: -2343000 | H13: 100 | I13: -2343000 | J13: 9.48262 | K13: 44G8/813/IG CLO FWH | L13: Paydown
... A130: SBL_814_814 | B130: 97064FAB1 | C130: WESTF 2020-A B 15-Mar-2045 | D130: 06-15-2025 | E130: 06-15-2025 | F130: 03-15-2045 | G130: -5350.7252 | H130: 100 | I130: -5350.73 | J130: 4.212 | K130: 44G9/814/ABS FWH | L130: Paydown

Sheet Positions
A1: Portfolio Code | B1: Investment Type | C1: CUSIP | D1: Current Face | E1: BASEMarket Value | F1: BASEOriginal Cost | G1: Issuer Name | H1: Coupon Rate | I1: Security Description | J1: Maturity Date | K1: Spread | L1: Factor | M1: Portfolio_Name | N1: Row Labels | O1: Manager | P1: WAL | Q1: Tranche Rating | R1: WAL_Range | S1: coupon_Range
A2: SBL_816_816 | C2: 75887PAN4 | D2: 2200000 | E2: 2207075.2 | F2: 2200000 | G2: Regatta Funding Ltd | H2: 11.3371 | I2: REGT6 2016-1A ER2 20-Apr-2034 | J2: 49054 | K2: 701.161 | L2: 1 | M2: 44I4/816/HY CLOs FWH | N2: 75887PAN4 | O2: Regatta Loan Management | P2: 6.1273312 | Q2: BB | R2: 6<8 | S2: 7+
A3: SBL_816_816 | C3: 75887PAN4 | D3: 5000000 | E3: 5016080 | F3: 5019285 | G3: Regatta Funding Ltd | H3: 11.3371 | I3: REGT6 2016-1A ER2 20-Apr-2034 | J3: 49054 | K3: 701.161 | L3: 1 | M3: 44I4/816/HY CLOs FWH | N3: 75887PAN4 | O3: Regatta Loan Management | P3: 6.1273312 | Q3: BB | R3: 6<8 | S3: 7+
A4: SBL_816_816 | C4: 75888CAA0 | D4: 900000 | E4: 909132.3 | F4: 911065.5 | G4: Regatta Funding Ltd | H4: 11.20549 | I4: REG19 2022-1A E 20-Apr-2035 | J4: 49419 | K4: 688 | L4: 1 | M4: 44I4/816/HY CLOs FWH | N4: 75888CAA0 | O4: Napier Park Global Capital | P4: 6.8997015 | Q4: BB | R4: 6<8 | S4: 7+
A5: SBL_816_816 | C5: 75888CAA0 | D5: 1100000 | E5: 1111161.7 | F5: 1113295.7 | G5: Regatta Funding Ltd | H5: 11.20549 | I5: REG19 2022-1A E 20-Apr-2035 | J5: 49419 | K5: 688 | L5: 1 | M5: 44I4/816/HY CLOs FWH | N5: 75888CAA0 | O5: Napier Park Global Capital | P5: 6.8997015 | Q5: BB | R5: 6<8 | S5: 7+
A6: SBL_816_816 | C6: 75888CAA0 | D6: 2500000 | E6: 2525367.5 | F6: 2263250 | G6: Regatta Funding Ltd | H6: 11.20549 | I6: REG19 2022-1A E 20-Apr-2035 | J6: 49419 | K6: 688 | L6: 1 | M6: 44I4/816/HY CLOs FWH | N6: 75888CAA0 | O6: Napier Park Global Capital | P6: 6.8997015 | Q6: BB | R6: 6<8 | S6: 7+
A7: SBL_816_816 | C7: 77341JAA2 | D7: 198000 | E7: 194085.94 | F7: 195782.4 | G7: ROCKT 2017 1A | H7: 10.9471 | I7: ROCKT 2021-1A E 20-Jul-2034 | J7: 49145 | K7: 662.161 | L7: 1 | M7: 44I4/816/HY CLOs FWH | N7: 77341JAA2 | O7: Rockford Tower Capital Management | P7: 6.3904329 | Q7: BB | R7: 6<8 | S7: 7+
A8: SBL_816_816 | B8: CLO RATED | C8: 77341JAA2 | D8: 450000 | E8: 441104.4 | F8: 452782.35 | G8: ROCKT 2017 1A | H8: 10.9471 | I8: ROCKT 2021-1A E 20-Jul-2034 | J8: 49145 | K8: 662.161 | L8: 1 | M8: 44I4/816/HY CLOs FWH | N8: 77341JAA2 | O8: Rockford Tower Capital Management | P8: 6.3904329 | Q8: BB | R8: 6<8 | S8: 7+
A9: SBL_816_816 | C9: 83616LAA3 | D9: 1080000 | E9: 1000350 | F9: 1017637.6 | G9: Sound Point CLO Ltd | H9: 11.01846 | I9: SNDPT 2022-1A E 25-Apr-2035 | J9: 49424 | K9: 670 | L9: 1 | M9: 44I4/816/HY CLOs FWH | N9: 83616LAA3 | O9: Sound Point Capital Management | P9: 6.8167818 | Q9: BB | R9: 6<8 | S9: 7+
A10: SBL_816_816 | C10: 83616LAA3 | D10: 1320000 | E10: 1222650 | F10: 1306800 | G10: Sound Point CLO Ltd | H10: 11.01846 | I10: SNDPT 2022-1A E 25-Apr-2035 | J10: 49424 | K10: 670 | L10: 1 | M10: 44I4/816/HY CLOs FWH | N10: 83616LAA3 | O10: Sound Point Capital Management | P10: 6.8167818 | Q10: BB | R10: 6<8 | S10: 7+
A11: SBL_816_816 | C11: 83616LAA3 | D11: 3000000 | E11: 2778750 | F11: 2758938 | G11: Sound Point CLO Ltd | H11: 11.01846 | I11: SNDPT 2022-1A E 25-Apr-2035 | J11: 49424 | K11: 670 | L11: 1 | M11: 44I4/816/HY CLOs FWH | N11: 83616LAA3 | O11: Sound Point Capital Management | P11: 6.8167818 | Q11: BB | R11: 6<8 | S11: 7+
A12: SBL_816_816 | B12: CLO RATED | C12: 87167YAA9 | D12: 585000 | E12: 570930.17 | F12: 587583.95 | G12: Symphony CLO Ltd | H12: 11.0871 | I12: SYMP 2021-25A E 19-Apr-2034 | J12: 49053 | K12: 676.161 | L12: 1 | M12: 44I4/816/HY CLOs FWH | N12: 87167YAA9 | O12: Symphony Alternative Asset Management | P12: 6.3561494 | Q12: BB | R12: 6<8 | S12: 7+
A13: SBL_816_816 | B13: CLO RATED | C13: 87167YAA9 | D13: 750000 | E13: 731961.75 | F13: 672750 | G13: Symphony CLO Ltd | H13: 11.0871 | I13: SYMP 2021-25A E 19-Apr-2034 | J13: 49053 | K13: 676.161 | L13: 1 | M13: 44I4/816/HY CLOs FWH | N13: 87167YAA9 | O13: Symphony Alternative Asset Management | P13: 6.3561494 | Q13: BB | R13: 6<8 | S13: 7+
A14: SBL_816_816 | C14: 87167YAA9 | D14: 1590000 | E14: 1551758.9 | F14: 1498578.7 | G14: Symphony CLO Ltd | H14: 11.0871 | I14: SYMP 2021-25A E 19-Apr-2034 | J14: 49053 | K14: 676.161 | L14: 1 | M14: 44I4/816/HY CLOs FWH | N14: 87167YAA9 | O14: Symphony Alternative Asset Management | P14: 6.3561494 | Q14: BB | R14: 6<8 | S14: 7+
A15: SBL_816_816 | C15: 87240GAG6 | D15: 1391000 | E15: 1374346.9 | F15: 1407793.5 | G15: TCP Waterman Clo LLC | H15: 12.7436 | I15: TCP 2017-1A ER 20-Aug-2033 | J15: 48811 | K15: 842.161 | L15: 1 | M15: 44I4/816/HY CLOs FWH | N15: 87240GAG6 | O15: BlackRock Capital Investment Advisors | P15: 4.9032832 | Q15: BB | R15: 4<6 | S15: 7+
A16: SBL_816_816 | C16: 87240GAG6 | D16: 3170000 | E16: 3132048.8 | F16: 3191533.8 | G16: TCP Waterman Clo LLC | H16: 12.7436 | I16: TCP 2017-1A ER 20-Aug-2033 | J16: 48811 | K16: 842.161 | L16: 1 | M16: 44I4/816/HY CLOs FWH | N16: 87240GAG6 | O16: BlackRock Capital Investment Advisors | P16: 4.9032832 | Q16: BB | R16: 4<6 | S16: 7+
A17: SBL_816_816 | C17: 87240GAG6 | D17: 80000 | E17: 79042.24 | F17: 80258.64 | G17: TCP Waterman Clo LLC | H17: 12.7436 | I17: TCP 2017-1A ER 20-Aug-2033 | J17: 48811 | K17: 842.161 | L17: 1 | M17: 44I4/816/HY CLOs FWH | N17: 87240GAG6 | O17: BlackRock Capital Investment Advisors | P17: 4.9032832 | Q17: BB | R17: 4<6 | S17: 7+
A18: SBL_816_816 | C18: 87240GAG6 | D18: 600000 | E18: 592816.8 | F18: 603426.64 | G18: TCP Waterman Clo LLC | H18: 12.7436 | I18: TCP 2017-1A ER 20-Aug-2033 | J18: 48811 | K18: 842.161 | L18: 1 | M18: 44I4/816/HY CLOs FWH | N18: 87240GAG6 | O18: BlackRock Capital Investment Advisors | P18: 4.9032832 | Q18: BB | R18: 4<6 | S18: 7+
A19: SBL_816_816 | C19: 87240GAG6 | D19: 2004000 | E19: 1980008.1 | F19: 1970819.6 | G19: TCP Waterman Clo LLC | H19: 12.7436 | I19: TCP 2017-1A ER 20-Aug-2033 | J19: 48811 | K19: 842.161 | L19: 1 | M19: 44I4/816/HY CLOs FWH | N19: 87240GAG6 | O19: BlackRock Capital Investment Advisors | P19: 4.9032832 | Q19: BB | R19: 4<6 | S19: 7+
A20: SBL_816_816 | C20: 87246LAJ3 | D20: 2165400 | E20: 1443828.1 | F20: 1635574.3 | G20: Wind River CLO Ltd | H20: 13.0871 | I20: WINDR 2015-1A FR 20-Oct-2030 | J20: 47776 | K20: 876.161 | L20: 1 | M20: 44I4/816/HY CLOs FWH | N20: 87246LAJ3 | O20: First Eagle Alternative Credit | P20: 5.0227397 | Q20: CCC | R20: 4<6 | S20: 7+
A21: SBL_816_816 | C21: 87246LAJ3 | D21: 2646600 | E21: 1764678.8 | F21: 2646600 | G21: Wind River CLO Ltd | H21: 13.0871 | I21: WINDR 2015-1A FR 20-Oct-2030 | J21: 47776 | K21: 876.161 | L21: 1 | M21: 44I4/816/HY CLOs FWH | N21: 87246LAJ3 | O21: First Eagle Alternative Credit | P21: 5.0227397 | Q21: CCC | R21: 4<6 | S21: 7+
A22: SBL_816_816 | C22: 87246LAJ3 | D22: 6015000 | E22: 4010633.6 | F22: 4816968.4 | G22: Wind River CLO Ltd | H22: 13.0871 | I22: WINDR 2015-1A FR 20-Oct-2030 | J22: 47776 | K22: 876.161 | L22: 1 | M22: 44I4/816/HY CLOs FWH | N22: 87246LAJ3 | O22: First Eagle Alternative Credit | P22: 5.0227397 | Q22: CCC | R22: 4<6 | S22: 7+
A23: SBL_816_816 | C23: 91734KAL1 | D23: 4436919.9 | E23: 4270846 | F23: 4436919.9 | G23: Blackrock Baker CLO 2021-1, Ltd | H23: 12.57916 | I23: BLKMM 2021-8A E 15-Jan-2034 | J23: 48959 | K23: 826.161 | L23: 1.140257 | M23: 44I4/816/HY CLOs FWH | N23: 91734KAL1 | O23: BlackRock Capital Investment Advisors | P23: 5.347515 | Q23: B | R23: 4<6 | S23: 7+
A24: SBL_816_816 | B24: CLO RATED | C24: 94951KAC1 | D24: 1724000 | E24: 1681025.9 | F24: 1700708.8 | G24: Wellfleet CLO Ltd | H24: 11.67916 | I24: WELF 2021-3A E 15-Jan-2035 | J24: 49324 | K24: 736.161 | L24: 1 | M24: 44I4/816/HY CLOs FWH | N24: 94951KAC1 | O24: Blue Owl Liquid Credit Advisors | P24: 6.8478591 | Q24: BB | R24: 6<8 | S24: 7+
A25: SBL_816_816 | C25: 94951KAC1 | D25: 3935000 | E25: 3836912.3 | F25: 3770639 | G25: Wellfleet CLO Ltd | H25: 11.67916 | I25: WELF 2021-3A E 15-Jan-2035 | J25: 49324 | K25: 736.161 | L25: 1 | M25: 44I4/816/HY CLOs FWH | N25: 94951KAC1 | O25: Blue Owl Liquid Credit Advisors | P25: 6.8478591 | Q25: BB | R25: 6<8 | S25: 7+
A26: SBL_816_816 | C26: 94951KAC1 | D26: 90000 | E26: 87756.57 | F26: 84963.33 | G26: Wellfleet CLO Ltd | H26: 11.67916 | I26: WELF 2021-3A E 15-Jan-2035 | J26: 49324 | K26: 736.161 | L26: 1 | M26: 44I4/816/HY CLOs FWH | N26: 94951KAC1 | O26: Blue Owl Liquid Credit Advisors | P26: 6.8478591 | Q26: BB | R26: 6<8 | S26: 7+
A27: SBL_816_816 | C27: 94951KAC1 | D27: 770000 | E27: 750806.21 | F27: 738120.23 | G27: Wellfleet CLO Ltd | H27: 11.67916 | I27: WELF 2021-3A E 15-Jan-2035 | J27: 49324 | K27: 736.161 | L27: 1 | M27: 44I4/816/HY CLOs FWH | N27: 94951KAC1 | O27: Blue Owl Liquid Credit Advisors | P27: 6.8478591 | Q27: BB | R27: 6<8 | S27: 7+
A28: SBL_816_816 | B28: CLO RATED | C28: 94951KAC1 | D28: 2481000 | E28: 2419156.1 | F28: 2437451.7 | G28: Wellfleet CLO Ltd | H28: 11.67916 | I28: WELF 2021-3A E 15-Jan-2035 | J28: 49324 | K28: 736.161 | L28: 1 | M28: 44I4/816/HY CLOs FWH | N28: 94951KAC1 | O28: Blue Owl Liquid Credit Advisors | P28: 6.8478591 | Q28: BB | R28: 6<8 | S28: 7+
A29: SBL_816_816 | B29: CLO RATED | C29: 97315YAA9 | D29: 1260000 | E29: 1184590.3 | F29: 1193868.9 | G29: Wind River CLO Ltd | H29: 11.0171 | I29: WINDR 2021-2A E 20-Jul-2034 | J29: 49145 | K29: 669.161 | L29: 1 | M29: 44I4/816/HY CLOs FWH | N29: 97315YAA9 | O29: First Eagle Alternative Credit | P29: 6.6361027 | Q29: BB | R29: 6<8 | S29: 7+
A30: SBL_816_816 | B30: CLO RATED | C30: 97315YAA9 | D30: 1540000 | E30: 1447832.5 | F30: 1532300 | G30: Wind River CLO Ltd | H30: 11.0171 | I30: WINDR 2021-2A E 20-Jul-2034 | J30: 49145 | K30: 669.161 | L30: 1 | M30: 44I4/816/HY CLOs FWH | N30: 97315YAA9 | O30: First Eagle Alternative Credit | P30: 6.6361027 | Q30: BB | R30: 6<8 | S30: 7+
A31: SBL_816_816 | C31: 97315YAA9 | D31: 3500000 | E31: 3290528.5 | F31: 3255416.5 | G31: Wind River CLO Ltd | H31: 11.0171 | I31: WINDR 2021-2A E 20-Jul-2034 | J31: 49145 | K31: 669.161 | L31: 1 | M31: 44I4/816/HY CLOs FWH | N31: 97315YAA9 | O31: First Eagle Alternative Credit | P31: 6.6361027 | Q31: BB | R31: 6<8 | S31: 7+
A32: SBL_816_816 | C32: 97316VAA4 | D32: 990000 | E32: 965526.21 | F32: 992927.43 | G32: Wind River CLO Ltd | H32: 9.5871 | I32: WINDR 2021-4A E1 20-Jan-2035 | J32: 49329 | K32: 526.161 | L32: 1 | M32: 44I4/816/HY CLOs FWH | N32: 97316VAA4 | O32: First Eagle Alternative Credit | P32: 6.7222222 | Q32: BB | R32: 6<8 | S32: 7+
A33: SBL_816_816 | C33: 97316VAA4 | D33: 3960000 | E33: 3862104.8 | F33: 3966506.5 | G33: Wind River CLO Ltd | H33: 9.5871 | I33: WINDR 2021-4A E1 20-Jan-2035 | J33: 49329 | K33: 526.161 | L33: 1 | M33: 44I4/816/HY CLOs FWH | N33: 97316VAA4 | O33: First Eagle Alternative Credit | P33: 6.7222222 | Q33: BB | R33: 6<8 | S33: 7+
A34: SBL_813_813 | C34: 08186RAW9 | D34: 120000 | E34: 120431.16 | F34: 120340.08 | G34: Benefit Street Partners CLO Ltd | H34: 7.92916 | I34: BSP 2020-21A DR 15-Oct-2034 | J34: 49232 | K34: 361.161 | L34: 1 | M34: 44G8/813/IG CLO FWH | N34: 08186RAW9 | O34: BSP CLO Management | P34: 6.0971577 | Q34: BBB | R34: 6<8 | S34: 7+
A35: SBL_813_813 | B35: CLO RATED | C35: 08186RAW9 | D35: 120000 | E35: 120431.16 | F35: 120340.08 | G35: Benefit Street Partners CLO Ltd | H35: 7.92916 | I35: BSP 2020-21A DR 15-Oct-2034 | J35: 49232 | K35: 361.161 | L35: 1 | M35: 44G8/813/IG CLO FWH | N35: 08186RAW9 | O35: BSP CLO Management | P35: 6.0971577 | Q35: BBB | R35: 6<8 | S35: 7+
A36: SBL_813_813 | C36: 081917AG1 | D36: 6500000 | E36: 6532513 | F36: 6500000 | G36: Benefit Street Partners CLO Ltd | H36: 7.36755 | I36: BSP 2017-12BRA D1 15-Oct-2037 | J36: 50328 | K36: 305 | L36: 1 | M36: 44G8/813/IG CLO FWH | N36: 081917AG1 | O36: Benefit Street Partners | P36: 8.2262426 | Q36: BBB | R36: 8<10 | S36: 7+
A37: SBL_813_813 | C37: 081922AG1 | D37: 5600000 | E37: 5621784 | F37: 5600000 | G37: Benefit Street Partners CLO Ltd | H37: 6.21846 | I37: BSP 2024-36A C 25-Jan-2038 | J37: 50430 | K37: 190 | L37: 1 | M37: 44G8/813/IG CLO FWH | N37: 081922AG1 | O37: Benefit Street Partners | P37: 8.6746585 | Q37: A | R37: 8<10 | S37: 6<7
A38: SBL_813_813 | C38: 081922AJ5 | D38: 5600000 | E38: 5638684.8 | F38: 5600000 | G38: Benefit Street Partners CLO Ltd | H38: 7.26846 | I38: BSP 2024-36A D1 25-Jan-2038 | J38: 50430 | K38: 295 | L38: 1 | M38: 44G8/813/IG CLO FWH | N38: 081922AJ5 | O38: Benefit Street Partners | P38: 9.1957404 | Q38: BBB | R38: 8<10 | S38: 7+
A39: SBL_813_813 | C39: 09077CAY8 | D39: 6600000 | E39: 6618645 | F39: 6600000 | G39: Birch Grove CLO | H39: 7.51755 | I39: BGCLO 2022-4A D1R 15-Jul-2037 | J39: 50236 | K39: 320 | L39: 1 | M39: 44G8/813/IG CLO FWH | N39: 09077CAY8 | O39: Birch Grove Capital | P39: 8.8606201 | Q39: BBB | R39: 8<10 | S39: 7+
A40: SBL_813_813 | C40: 09077FAU9 | D40: 4070000 | E40: 4094623.5 | F40: 4070000 | G40: Birch Grove CLO | H40: 7.52087 | I40: BGCLO 2023-6A D1R 20-Jul-2038 | J40: 50606 | K40: 315 | M40: 44G8/813/IG CLO FWH | N40: 09077FAU9 | O40: Birch Grove Capital | P40: 9.6493194 | Q40: BBB | R40: 8<10 | S40: 7+
A41: SBL_813_813 | C41: 09077LAU6 | D41: 2000000 | E41: 2007346 | F41: 2000000 | G41: Birch Grove CLO | H41: 7.47549 | I41: BGCLO 2021-2A D1R 19-Oct-2037 | J41: 50332 | K41: 315 | L41: 1 | M41: 44G8/813/IG CLO FWH | N41: 09077LAU6 | O41: Birch Grove Capital | P41: 9.070457 | Q41: BBB | R41: 8<10 | S41: 7+
A42: SBL_813_813 | C42: 09261MAY2 | D42: 7182942 | E42: 7193450.6 | F42: 7182942 | G42: Blackrock CLO Ltd | H42: 7.27549 | I42: BLKMM 2021-6A CR 20-Apr-2037 | J42: 50150 | K42: 295 | L42: 1 | M42: 44G8/813/IG CLO FWH | N42: 09261MAY2 | O42: BlackRock Capital Investment Advisors | P42: 7.4787455 | Q42: A | R42: 6<8 | S42: 7+
A43: SBL_813_813 | C43: 09262WAE3 | D43: 3000000 | E43: 3008856 | F43: 3000000 | G43: BlackRock DLF IX-L CLO, LP | H43: 8.42549 | I43: BLKMM 2023-2A C 20-Oct-2033 | J43: 48872 | K43: 410 | L43: 1 | M43: 44G8/813/IG CLO FWH | N43: 09262WAE3 | O43: BlackRock Capital Investment Advisors | P43: 3.1294006 | Q43: A | R43: 2<4 | S43: 7+
A44: SBL_813_813 | C44: 09290EAL3 | D44: 5800000 | E44: 5727575.4 | F44: 5800000 | G44: Blackrock CLO Ltd | H44: 6.66755 | I44: BLKMM 2022-1A CR 15-Jan-2038 | J44: 50420 | K44: 235 | L44: 1 | M44: 44G8/813/IG CLO FWH | N44: 09290EAL3 | O44: BlackRock Capital Investment Advisors | P44: 8.2323538 | Q44: A | R44: 8<10 | S44: 6<7
A45: SBL_813_813 | C45: 09290EAN9 | D45: 6400000 | E45: 6307603.2 | F45: 6400000 | G45: Blackrock CLO Ltd | H45: 8.21755 | I45: BLKMM 2022-1A DR 15-Jan-2038 | J45: 50420 | K45: 390 | L45: 1 | M45: 44G8/813/IG CLO FWH | N45: 09290EAN9 | O45: BlackRock Capital Investment Advisors | P45: 8.7429403 | Q45: BBB | R45: 8<10 | S45: 7+
A46: SBL_813_813 | B46: CLO RATED | C46: 09631BAJ2 | D46: 4250000 | E46: 4243127.8 | F46: 4218125 | G46: BlueMountain CLO Ltd | H46: 7.5871 | I46: BLUEM 2021-31A D 19-Apr-2034 | J46: 49053 | K46: 326.161 | L46: 1 | M46: 44G8/813/IG CLO FWH | N46: 09631BAJ2 | O46: Sound Point Capital Management | P46: 6.0357852 | Q46: BBB | R46: 6<8 | S46: 7+
A47: SBL_813_813 | B47: CLO RATED | C47: 12481HAW5 | D47: 15359893 | E47: 15388831 | F47: 15359893 | G47: CBAM Ltd | H47: 8.08401 | I47: CBAM 2017-3A DR 17-Jul-2034 | J47: 49142 | K47: 376.161 | L47: 1 | M47: 44G8/813/IG CLO FWH | N47: 12481HAW5 | O47: CBAM Partners | P47: 6.1117026 | Q47: BBB | R47: 6<8 | S47: 7+
A48: SBL_813_813 | B48: CLO RATED | C48: 12481KAY4 | D48: 32772918 | E48: 32837808 | F48: 32772918 | G48: CBAM Ltd | H48: 7.93401 | I48: CBAM 2017-2A DR 17-Jul-2034 | J48: 49142 | K48: 361.161 | L48: 1 | M48: 44G8/813/IG CLO FWH | N48: 12481KAY4 | O48: CBAM Partners | P48: 5.9506013 | Q48: BBB | R48: 4<6 | S48: 7+
A49: SBL_813_813 | B49: CLO RATED | C49: 12482JAJ9 | D49: 25125000 | E49: 25175401 | F49: 25125000 | G49: CBAM Ltd | H49: 7.3871 | I49: CBAM 2018-7A D 20-Jul-2031 | J49: 48049 | K49: 306.161 | L49: 1 | M49: 44G8/813/IG CLO FWH | N49: 12482JAJ9 | O49: CBAM CLO Management | P49: 3.2730262 | Q49: BBB | R49: 2<4 | S49: 7+
A50: SBL_813_813 | C50: 12516EAL5 | D50: 10000000 | E50: 10010670 | F50: 10000000 | G50: CBAMR Ltd | H50: 7.28109 | I50: CBAMR 2017-4A D1R 31-Mar-2038 | J50: 50495 | K50: 300 | M50: 44G8/813/IG CLO FWH | N50: 12516EAL5 | O50: CBAM CLO Management | P50: 9.5236411 | Q50: BBB | R50: 8<10 | S50: 7+
A51: SBL_813_813 | C51: 12516EAN1 | D51: 10000000 | E51: 10080670 | F51: 10000000 | G51: CBAMR Ltd | H51: 8.78109 | I51: CBAMR 2017-4A D2R 31-Mar-2038 | J51: 50495 | K51: 450 | M51: 44G8/813/IG CLO FWH | N51: 12516EAN1 | O51: CBAM CLO Management | P51: 9.8113671 | Q51: BBB | R51: 8<10 | S51: 7+
A52: SBL_813_813 | C52: 12516GAJ5 | D52: 6200000 | E52: 6210626.8 | F52: 6200000 | G52: CBAMR Ltd | H52: 8.03997 | I52: CBAMR 2018-6A D1R2 31-Mar-2038 | J52: 50495 | K52: 375 | L52: 1 | M52: 44G8/813/IG CLO FWH | N52: 12516GAJ5 | O52: CBAM CLO Management | P52: 9.264825 | Q52: BBB | R52: 8<10 | S52: 7+
A53: SBL_813_813 | C53: 12516GAL0 | D53: 1860000 | E53: 1897923.5 | F53: 1860000 | G53: CBAMR Ltd | H53: 10.28997 | I53: CBAMR 2018-6A D2R2 31-Mar-2038 | J53: 50495 | K53: 600 | L53: 1 | M53: 44G8/813/IG CLO FWH | N53: 12516GAL0 | O53: CBAM CLO Management | P53: 9.5529454 | Q53: BBB | R53: 8<10 | S53: 7+
A54: SBL_813_813 | C54: 12529QAJ8 | D54: 575000 | E54: 570342.5 | F54: 572357.3 | G54: CFIP CLO Ltd | H54: 8.1271 | I54: CFIP 2021-1A D 20-Jan-2035 | J54: 49329 | K54: 380.161 | L54: 1 | M54: 44G8/813/IG CLO FWH | N54: 12529QAJ8 | O54: CFI Partners | P54: 6.4179559 | Q54: BBB | R54: 6<8 | S54: 7+
A55: SBL_813_813 | C55: 12529QAJ8 | D55: 5100000 | E55: 5058690 | F55: 5076080.8 | G55: CFIP CLO Ltd | H55: 8.1271 | I55: CFIP 2021-1A D 20-Jan-2035 | J55: 49329 | K55: 380.161 | L55: 1 | M55: 44G8/813/IG CLO FWH | N55: 12529QAJ8 | O55: CFI Partners | P55: 6.4179559 | Q55: BBB | R55: 6<8 | S55: 7+
A56: SBL_813_813 | C56: 12529QAJ8 | D56: 160000 | E56: 158704 | F56: 160276.32 | G56: CFIP CLO Ltd | H56: 8.1271 | I56: CFIP 2021-1A D 20-Jan-2035 | J56: 49329 | K56: 380.161 | L56: 1 | M56: 44G8/813/IG CLO FWH | N56: 12529QAJ8 | O56: CFI Partners | P56: 6.4179559 | Q56: BBB | R56: 6<8 | S56: 7+
A57: SBL_813_813 | C57: 12529QAJ8 | D57: 170000 | E57: 168623 | F57: 170040.97 | G57: CFIP CLO Ltd | H57: 8.1271 | I57: CFIP 2021-1A D 20-Jan-2035 | J57: 49329 | K57: 380.161 | L57: 1 | M57: 44G8/813/IG CLO FWH | N57: 12529QAJ8 | O57: CFI Partners | P57: 6.4179559 | Q57: BBB | R57: 6<8 | S57: 7+
A58: SBL_813_813 | C58: 12529QAJ8 | D58: 270000 | E58: 267813 | F58: 268451.04 | G58: CFIP CLO Ltd | H58: 8.1271 | I58: CFIP 2021-1A D 20-Jan-2035 | J58: 49329 | K58: 380.161 | L58: 1 | M58: 44G8/813/IG CLO FWH | N58: 12529QAJ8 | O58: CFI Partners | P58: 6.4179559 | Q58: BBB | R58: 6<8 | S58: 7+
A59: SBL_813_813 | C59: 12529QAJ8 | D59: 270000 | E59: 267813 | F59: 269619.95 | G59: CFIP CLO Ltd | H59: 8.1271 | I59: CFIP 2021-1A D 20-Jan-2035 | J59: 49329 | K59: 380.161 | L59: 1 | M59: 44G8/813/IG CLO FWH | N59: 12529QAJ8 | O59: CFI Partners | P59: 6.4179559 | Q59: BBB | R59: 6<8 | S59: 7+
A60: SBL_813_813 | C60: 12550ABM7 | D60: 3750000 | E60: 3773422.5 | F60: 3750000 | G60: CIFC Funding Ltd | H60: 7.5724 | I60: CIFC 2014-5A D1R3 17-Jul-2037 | J60: 50238 | K60: 325 | L60: 1 | M60: 44G8/813/IG CLO FWH | N60: 12550ABM7 | O60: CIFC Asset Management | P60: 8.1791669 | Q60: BBB | R60: 8<10 | S60: 7+
A61: SBL_813_813 | C61: 12550ABP0 | D61: 2700000 | E61: 2726103.6 | F61: 2740500 | G61: CIFC Funding Ltd | H61: 9.2224 | I61: CIFC 2014-5A D2R3 17-Jul-2037 | J61: 50238 | K61: 490 | L61: 1 | M61: 44G8/813/IG CLO FWH | N61: 12550ABP0 | O61: CIFC Asset Management | P61: 8.4638889 | Q61: BBB | R61: 8<10 | S61: 7+
A62: SBL_813_813 | C62: 12555XAY7 | D62: 9000000 | E62: 9076689 | F62: 9000000 | G62: CIFC Funding Ltd | H62: 7.61777 | I62: CIFC 2019-6A D1R 16-Jul-2037 | J62: 50237 | K62: 330 | L62: 1 | M62: 44G8/813/IG CLO FWH | N62: 12555XAY7 | O62: CIFC Asset Management | P62: 8.4375997 | Q62: BBB | R62: 8<10 | S62: 7+
A63: SBL_813_813 | B63: CLO RATED | C63: 12560EAU0 | D63: 5375000 | E63: 5401165.5 | F63: 5375000 | G63: CIFC Funding Ltd | H63: 7.6871 | I63: CIFC 2020-3A DR 20-Oct-2034 | J63: 49237 | K63: 336.161 | L63: 1 | M63: 44G8/813/IG CLO FWH | N63: 12560EAU0 | O63: CIFC Asset Management | P63: 6.253337 | Q63: BBB | R63: 6<8 | S63: 7+
A64: SBL_813_813 | C64: 12562RAS4 | D64: 4700000 | E64: 4717639.1 | F64: 4700000 | G64: CIFC Funding Ltd | H64: 7.11755 | I64: CIFC 2020-4A DR 15-Jan-2040 | J64: 51150 | K64: 280 | L64: 1 | M64: 44G8/813/IG CLO FWH | N64: 12562RAS4 | O64: CIFC Asset Management | P64: 9.1877874 | Q64: BBB | R64: 8<10 | S64: 7+
A65: SBL_817_817 | C65: 12481LAE6 | D65: 1300000 | E65: 1290679 | F65: 1287000 | G65: CBAM Ltd | H65: 11.68401 | I65: CBAM 2017-2A ER 17-Jul-2034 | J65: 49142 | K65: 736.161 | L65: 1 | M65: P44I5/817/HY CLOs OC | N65: 12481LAE6 | O65: CBAM Partners | P65: 6.3180232 | Q65: BB | R65: 6<8 | S65: 7+
A66: SBL_817_817 | B66: CLO RATED | C66: 449249AJ0 | D66: 1750000 | E66: 1730550.5 | F66: 1723750 | G66: ICG US CLO Ltd | H66: 12.0571 | I66: ICG 2021-3A E 20-Oct-2034 | J66: 49237 | K66: 773.161 | L66: 1 | M66: P44I5/817/HY CLOs OC | N66: 449249AJ0 | O66: ICG Debt Advisors | P66: 6.6054042 | Q66: BB | R66: 6<8 | S66: 7+
A67: SBL_817_817 | C67: 75885AAE9 | D67: 1500000 | E67: 1507455 | F67: 1500000 | G67: Regatta Funding Ltd | H67: 9.21755 | I67: REG20 2021-2A ER 15-Jan-2038 | J67: 50420 | K67: 490 | L67: 1 | M67: P44I5/817/HY CLOs OC | N67: 75885AAE9 | O67: Napier Park Global Capital | P67: 9.8226872 | Q67: BB | R67: 8<10 | S67: 7+
A68: SBL_823_823 | C68: 91734KAL1 | D68: 1140257.2 | E68: 1097577.4 | F68: 1140257.2 | G68: Blackrock Baker CLO 2021-1, Ltd | H68: 12.57916 | I68: BLKMM 2021-8A E 15-Jan-2034 | J68: 48959 | K68: 826.161 | L68: 1.140257 | M68: 44J5/823/Atypical OC | N68: 91734KAL1 | O68: BlackRock Capital Investment Advisors | P68: 5.347515 | Q68: B | R68: 4<6 | S68: 7+
A69: SBL_813_813 | C69: 12563EAU7 | D69: 9000000 | E69: 9048420 | F69: 9000000 | G69: CIFC Funding Ltd | H69: 7.46846 | I69: CIFC 2021-1A D1R 25-Jul-2037 | J69: 50246 | K69: 315 | L69: 1 | M69: 44G8/813/IG CLO FWH | N69: 12563EAU7 | O69: CIFC Asset Management | P69: 8.8329233 | Q69: BBB | R69: 8<10 | S69: 7+
A70: SBL_813_813 | C70: 12564DAG9 | D70: 2000000 | E70: 2009306 | F70: 1992500 | G70: CIFC Funding Ltd | H70: 7.57916 | I70: CIFC 2021-3A D 15-Jul-2036 | J70: 49871 | K70: 326.161 | L70: 1 | M70: 44G8/813/IG CLO FWH | N70: 12564DAG9 | O70: CIFC Asset Management | P70: 6.0957346 | Q70: BBB | R70: 6<8 | S70: 7+
A71: SBL_813_813 | C71: 12564DAG9 | D71: 2675000 | E71: 2687446.8 | F71: 2604781.2 | G71: CIFC Funding Ltd | H71: 7.57916 | I71: CIFC 2021-3A D 15-Jul-2036 | J71: 49871 | K71: 326.161 | L71: 1 | M71: 44G8/813/IG CLO FWH | N71: 12564DAG9 | O71: CIFC Asset Management | P71: 6.0957346 | Q71: BBB | R71: 6<8 | S71: 7+
A72: SBL_813_813 | B72: CLO RATED | C72: 12567HAJ1 | D72: 3825000 | E72: 3844086.8 | F72: 3825000 | G72: CIFC Funding Ltd | H72: 7.5806 | I72: CIFC 2021-7A D 23-Jan-2035 | J72: 49332 | K72: 326.161 | L72: 1 | M72: 44G8/813/IG CLO FWH | N72: 12567HAJ1 | O72: CIFC Asset Management | P72: 6.3854852 | Q72: BBB | R72: 6<8 | S72: 7+
A73: SBL_813_813 | C73: 12567HAJ1 | D73: 90000 | E73: 90449.1 | F73: 90244.62 | G73: CIFC Funding Ltd | H73: 7.5806 | I73: CIFC 2021-7A D 23-Jan-2035 | J73: 49332 | K73: 326.161 | L73: 1 | M73: 44G8/813/IG CLO FWH | N73: 12567HAJ1 | O73: CIFC Asset Management | P73: 6.3854852 | Q73: BBB | R73: 6<8 | S73: 7+
A74: SBL_813_813 | C74: 12567HAJ1 | D74: 110000 | E74: 110548.9 | F74: 110480.26 | G74: CIFC Funding Ltd | H74: 7.5806 | I74: CIFC 2021-7A D 23-Jan-2035 | J74: 49332 | K74: 326.161 | L74: 1 | M74: 44G8/813/IG CLO FWH | N74: 12567HAJ1 | O74: CIFC Asset Management | P74: 6.3854852 | Q74: BBB | R74: 6<8 | S74: 7+
A75: SBL_813_813 | C75: 12567HAJ1 | D75: 180000 | E75: 180898.2 | F75: 180575.96 | G75: CIFC Funding Ltd | H75: 7.5806 | I75: CIFC 2021-7A D 23-Jan-2035 | J75: 49332 | K75: 326.161 | L75: 1 | M75: 44G8/813/IG CLO FWH | N75: 12567HAJ1 | O75: CIFC Asset Management | P75: 6.3854852 | Q75: BBB | R75: 6<8 | S75: 7+
A76: SBL_813_813 | B76: CLO RATED | C76: 12567HAJ1 | D76: 180000 | E76: 180898.2 | F76: 180437.54 | G76: CIFC Funding Ltd | H76: 7.5806 | I76: CIFC 2021-7A D 23-Jan-2035 | J76: 49332 | K76: 326.161 | L76: 1 | M76: 44G8/813/IG CLO FWH | N76: 12567HAJ1 | O76: CIFC Asset Management | P76: 6.3854852 | Q76: BBB | R76: 6<8 | S76: 7+
A77: SBL_813_813 | C77: 12570XAG7 | D77: 7200000 | E77: 7267644 | F77: 7200000 | G77: CIFC Funding Ltd | H77: 8.029 | I77: CIFC 2024-1A D 18-Apr-2037 | J77: 50148 | K77: 370 | L77: 1 | M77: 44G8/813/IG CLO FWH | N77: 12570XAG7 | O77: CIFC Asset Management | P77: 8.5114692 | Q77: BBB | R77: 8<10 | S77: 7+
A78: SBL_813_813 | C78: 12572GAU1 | D78: 1750000 | E78: 1761753 | F78: 1750000 | G78: CIFC Funding Ltd | H78: 8.21777 | I78: CIFC 2022-5A DR 16-Jan-2037 | J78: 50056 | K78: 390 | L78: 1 | M78: 44G8/813/IG CLO FWH | N78: 12572GAU1 | O78: CIFC Asset Management | P78: 8.3143013 | Q78: BBB | R78: 8<10 | S78: 7+
A79: SBL_813_813 | C79: 13875MAG1 | D79: 1000000 | E79: 1001911 | F79: 971250 | G79: Canyon CLO | H79: 7.62916 | I79: CANYC 2021-3A D 15-Jul-2034 | J79: 49140 | K79: 331.161 | L79: 1 | M79: 44G8/813/IG CLO FWH | N79: 13875MAG1 | O79: Canyon CLO Advisors | P79: 6.0435283 | Q79: BBB | R79: 6<8 | S79: 7+
A80: SBL_813_813 | C80: 13876XAN1 | D80: 527000 | E80: 528028.18 | F80: 527000 | G80: CANYC 2018 1X | H80: 7.92916 | I80: CANYC 2021-2A D 15-Apr-2034 | J80: 49049 | K80: 361.161 | L80: 1 | M80: 44G8/813/IG CLO FWH | N80: 13876XAN1 | O80: Canyon CLO Advisors | P80: 5.7851951 | Q80: BBB | R80: 4<6 | S80: 7+
A81: SBL_813_813 | B81: CLO RATED | C81: 13876XAN1 | D81: 548072 | E81: 549141.29 | F81: 548072 | G81: CANYC 2018 1X | H81: 7.92916 | I81: CANYC 2021-2A D 15-Apr-2034 | J81: 49049 | K81: 361.161 | L81: 1 | M81: 44G8/813/IG CLO FWH | N81: 13876XAN1 | O81: Canyon CLO Advisors | P81: 5.7851951 | Q81: BBB | R81: 4<6 | S81: 7+
A82: SBL_813_813 | C82: 13876XAN1 | D82: 540000 | E82: 541053.54 | F82: 542119.72 | G82: CANYC 2018 1X | H82: 7.92916 | I82: CANYC 2021-2A D 15-Apr-2034 | J82: 49049 | K82: 361.161 | L82: 1 | M82: 44G8/813/IG CLO FWH | N82: 13876XAN1 | O82: Canyon CLO Advisors | P82: 5.7851951 | Q82: BBB | R82: 4<6 | S82: 7+
A83: SBL_813_813 | B83: CLO RATED | C83: 13876XAN1 | D83: 540001 | E83: 541054.54 | F83: 541067.14 | G83: CANYC 2018 1X | H83: 7.92916 | I83: CANYC 2021-2A D 15-Apr-2034 | J83: 49049 | K83: 361.161 | L83: 1 | M83: 44G8/813/IG CLO FWH | N83: 13876XAN1 | O83: Canyon CLO Advisors | P83: 5.7851951 | Q83: BBB | R83: 4<6 | S83: 7+
A84: SBL_813_813 | C84: 13877JAG6 | D84: 3000000 | E84: 3004575 | F84: 2791500 | G84: CANYC 2018 1X | H84: 7.51777 | I84: CANYC 2022-1A D 15-Apr-2035 | J84: 49414 | K84: 320 | L84: 1 | M84: 44G8/813/IG CLO FWH | N84: 13877JAG6 | O84: Canyon CLO Advisors | P84: 6.5239567 | Q84: BBB | R84: 6<8 | S84: 7+
A85: SBL_813_813 | C85: 13887TBA4 | D85: 3500000 | E85: 3531353 | F85: 3500000 | G85: CANYC 2018 1X | H85: 7.96755 | I85: CANYC 2019-1A D1RR 15-Jul-2037 | J85: 50236 | K85: 365 | L85: 1 | M85: 44G8/813/IG CLO FWH | N85: 13887TBA4 | O85: Canyon CLO Advisors | P85: 8.7783984 | Q85: BBB | R85: 8<10 | S85: 7+
A86: SBL_813_813 | C86: 13887TBC0 | D86: 4800000 | E86: 4844256 | F86: 4872000 | G86: CANYC 2018 1X | H86: 9.46755 | I86: CANYC 2019-1A D2RR 15-Jul-2037 | J86: 50236 | K86: 515 | L86: 1 | M86: 44G8/813/IG CLO FWH | N86: 13887TBC0 | O86: Canyon CLO Advisors | P86: 9.1088964 | Q86: BBB | R86: 8<10 | S86: 7+
A87: SBL_813_813 | C87: 14074EAJ0 | D87: 3000000 | E87: 3019323 | F87: 3000000 | G87: Captree Park CLO Ltd | H87: 6.62549 | I87: CPTPK 2024-1A C 20-Jul-2037 | J87: 50241 | K87: 230 | L87: 1 | M87: 44G8/813/IG CLO FWH | N87: 14074EAJ0 | O87: Blackstone CLO Management | P87: 8.2162903 | Q87: A | R87: 8<10 | S87: 6<7
A88: SBL_813_813 | C88: 14074EAL5 | D88: 3000000 | E88: 3022905 | F88: 3000000 | G88: Captree Park CLO Ltd | H88: 7.57549 | I88: CPTPK 2024-1A D 20-Jul-2037 | J88: 50241 | K88: 325 | L88: 1 | M88: 44G8/813/IG CLO FWH | N88: 14074EAL5 | O88: Blackstone CLO Management | P88: 8.8070333 | Q88: BBB | R88: 8<10 | S88: 7+
A89: SBL_813_813 | C89: 14311UBG2 | D89: 600000 | E89: 601180.8 | F89: 600000 | G89: Carlyle Global Market Strategies | H89: 7.17549 | I89: CGMS 2016-3A DRRR 20-Jul-2034 | J89: 49145 | K89: 285 | L89: 1 | M89: 44G8/813/IG CLO FWH | N89: 14311UBG2 | O89: Carlyle CLO Management | P89: 5.7513621 | Q89: BBB | R89: 4<6 | S89: 7+
A90: SBL_813_813 | B90: CLO RATED | C90: 143120AG8 | D90: 2000000 | E90: 2009296 | F90: 1994500 | G90: Carlyle Global Market Strategies | H90: 7.77916 | I90: CGMS 2021-8A D 15-Oct-2034 | J90: 49232 | K90: 346.161 | L90: 1 | M90: 44G8/813/IG CLO FWH | N90: 143120AG8 | O90: Carlyle CLO Management | P90: 6.2373314 | Q90: BBB | R90: 6<8 | S90: 7+
A91: SBL_813_813 | C91: 143120AG8 | D91: 779187 | E91: 782808.66 | F91: 779187 | G91: Carlyle Global Market Strategies | H91: 7.77916 | I91: CGMS 2021-8A D 15-Oct-2034 | J91: 49232 | K91: 346.161 | L91: 1 | M91: 44G8/813/IG CLO FWH | N91: 143120AG8 | O91: Carlyle CLO Management | P91: 6.2373314 | Q91: BBB | R91: 6<8 | S91: 7+
A92: SBL_813_813 | B92: CLO RATED | C92: 143120AG8 | D92: 779812 | E92: 783436.57 | F92: 779812 | G92: Carlyle Global Market Strategies | H92: 7.77916 | I92: CGMS 2021-8A D 15-Oct-2034 | J92: 49232 | K92: 346.161 | L92: 1 | M92: 44G8/813/IG CLO FWH | N92: 143120AG8 | O92: Carlyle CLO Management | P92: 6.2373314 | Q92: BBB | R92: 6<8 | S92: 7+
A93: SBL_813_813 | B93: CLO RATED | C93: 143120AG8 | D93: 350000 | E93: 351626.8 | F93: 351288.57 | G93: Carlyle Global Market Strategies | H93: 7.77916 | I93: CGMS 2021-8A D 15-Oct-2034 | J93: 49232 | K93: 346.161 | L93: 1 | M93: 44G8/813/IG CLO FWH | N93: 143120AG8 | O93: Carlyle CLO Management | P93: 6.2373314 | Q93: BBB | R93: 6<8 | S93: 7+
A94: SBL_813_813 | C94: 143120AG8 | D94: 350001 | E94: 351627.8 | F94: 351213.69 | G94: Carlyle Global Market Strategies | H94: 7.77916 | I94: CGMS 2021-8A D 15-Oct-2034 | J94: 49232 | K94: 346.161 | L94: 1 | M94: 44G8/813/IG CLO FWH | N94: 143120AG8 | O94: Carlyle CLO Management | P94: 6.2373314 | Q94: BBB | R94: 6<8 | S94: 7+
A95: SBL_813_813 | C95: 143133AW6 | D95: 5600000 | E95: 5609884 | F95: 5600000 | G95: Carlyle Global Market Strategies | H95: 7.11755 | I95: CGMS 2021-6A D1R 15-Jan-2038 | J95: 50420 | K95: 280 | L95: 1 | M95: 44G8/813/IG CLO FWH | N95: 143133AW6 | O95: Carlyle CLO Management | P95: 9.2116972 | Q95: BBB | R95: 8<10 | S95: 7+
A96: SBL_813_813 | C96: 14314FBG2 | D96: 5750000 | E96: 5767710 | F96: 5750000 | G96: Carlyle Global Market Strategies | H96: 7.52549 | I96: CGMS 2017-3A D1R2 21-Oct-2037 | J96: 50334 | K96: 320 | L96: 1 | M96: 44G8/813/IG CLO FWH | N96: 14314FBG2 | O96: Carlyle CLO Management | P96: 8.9596892 | Q96: BBB | R96: 8<10 | S96: 7+
A97: SBL_813_813 | C97: 14315GAU9 | D97: 2000000 | E97: 2009202 | F97: 1906500 | G97: Carlyle Global Market Strategies | H97: 7.78007 | I97: CGMS 2020-2A CR 25-Jan-2035 | J97: 49334 | K97: 346.161 | L97: 1 | M97: 44G8/813/IG CLO FWH | N97: 14315GAU9 | O97: Carlyle CLO Management | P97: 6.3997853 | Q97: BBB | R97: 6<8 | S97: 7+
A98: SBL_813_813 | C98: 14315RAW1 | D98: 4000000 | E98: 4013176 | F98: 4000000 | G98: Carlyle Global Market Strategies | H98: 7.4224 | I98: CGMS 2018-4A D1R 17-Oct-2037 | J98: 50330 | K98: 310 | L98: 1 | M98: 44G8/813/IG CLO FWH | N98: 14315RAW1 | O98: Carlyle CLO Management | P98: 9.0108155 | Q98: BBB | R98: 8<10 | S98: 7+
A99: SBL_813_813 | C99: 14316BAU9 | D99: 4250000 | E99: 4293452 | F99: 4262750 | G99: Carlyle Global Market Strategies | H99: 7.9371 | I99: CGMS 2019-1A CR 20-Apr-2031 | J99: 47958 | K99: 361.161 | L99: 1 | M99: 44G8/813/IG CLO FWH | N99: 14316BAU9 | O99: Carlyle CLO Management | P99: 3.9773387 | Q99: BBB | R99: 2<4 | S99: 7+
A100: SBL_813_813 | C100: 14316MAQ4 | D100: 4700000 | E100: 4722033.6 | F100: 4700000 | G100: Carlyle Global Market Strategies | H100: 6.31755 | I100: CGMS 2021-1A BR 15-Jan-2040 | J100: 51150 | K100: 200 | L100: 1 | M100: 44G8/813/IG CLO FWH | N100: 14316MAQ4 | O100: Carlyle CLO Management | P100: 8.6852709 | Q100: A | R100: 8<10 | S100: 6<7
...

Sheet Sec_Master
A1: cusip | B1: Row Labels | C1: WAL | D1: Next Payment Date | E1: Non-Call Date | F1: Par Sub | G1: Implied DM | H1: Market Price | I1: Manager | J1: Issue Date | K1: SP Rating | L1: Moody Rating | M1: Fitch Rating | N1: KBRA Rating | O1: DBRS Rating | P1: Issuer Name | Q1: NRSRO Rating | R1: NRSRO | S1: Tranche Rating
A2: 00119AAG0 | B2: 00119AAG0 | D2: 45953 | E2: 46591 | I2: AGL CLO Credit Management | J2: 20230511 | K2: NR | L2: NR | M2: A | N2: NR | O2: NR | P2: AGL CLO Ltd. | Q2: A | R2: Fitch | S2: A
A3: 00119AAJ4 | B3: 00119AAJ4 | D3: 45953 | E3: 46591 | I3: AGL CLO Credit Management | J3: 20230511 | K3: NR | L3: NR | M3: BBB- | N3: NR | O3: NR | P3: AGL CLO Ltd. | Q3: BBB- | R3: Fitch | S3: BBB
A4: 00119AAS4 | B4: 00119AAS4 | C4: 9.1695377 | D4: 45953 | E4: 46591 | F4: 17.880402 | G4: 202.15609 | H4: 100.9195 | I4: AGL CLO Credit Management | J4: 20250523 | K4: NR | L4: NR | M4: A | N4: NR | O4: NR | P4: AGL CLO Ltd. | Q4: A | R4: Fitch | S4: A
A5: 00119AAU9 | B5: 00119AAU9 | C5: 9.7045333 | D5: 45953 | E5: 46591 | F5: 11.871651 | G5: 337.95476 | H5: 99.4267 | I5: AGL CLO Credit Management | J5: 20250523 | K5: NR | L5: NR | M5: BBB- | N5: NR | O5: NR | P5: AGL CLO Ltd. | Q5: BBB- | R5: Fitch | S5: BBB
A6: 00120NAG9 | B6: 00120NAG9 | I6: AGL CLO Credit Management | J6: 20230613 | K6: NR | L6: NR | M6: BBB- | N6: NR | O6: NR | P6: AGL CLO Ltd. | Q6: BBB- | R6: Fitch | S6: BBB
A7: 00120NAU8 | B7: 00120NAU8 | C7: 9.6224766 | F7: 12.445965 | G7: 282.97731 | H7: 100.494 | I7: AGL CLO Credit Management | J7: 20250625 | K7: NR | L7: NR | M7: BBB | N7: NR | O7: NR | P7: AGL CLO Ltd. | Q7: BBB | R7: Fitch | S7: BBB
A8: 001210AY9 | B8: 001210AY9 | C8: 9.2339746 | D8: 45951 | E8: 46589 | F8: 11.770896 | G8: 299.10923 | H8: 100.4057 | I8: AGL CLO Credit Management | J8: 20250711 | K8: NR | L8: NR | M8: BBB- | N8: NR | O8: NR | P8: AGL CLO 19 Ltd | Q8: BBB- | R8: Fitch | S8: BBB
A9: 01750WAJ8 | B9: 01750WAJ8 | D9: 45950 | E9: 46588 | I9: AXA Investment Managers | J9: 20210628 | K9: NR | L9: Baa3 | M9: NR | N9: NR | O9: NR | P9: Allegro CLO Ltd | Q9: Baa3 | R9: Moody's | S9: BBB
A10: 03328QCC3 | B10: 03328QCC3 | C10: 0 | D10: 45952 | E10: 45769 | G10: 298.47644 | H10: 100.375 | I10: Anchorage Collateral Management | J10: 20250811 | K10: NR | L10: NR | M10: BBB- | N10: NR | O10: NR | P10: Anchorage Capital CLO LTD | Q10: BBB- | R10: Fitch | S10: BBB
A11: 03770JAA8 | B11: 03770JAA8 | I11: CVC Credit Partners | J11: 20230327 | K11: NR | L11: NR | M11: BB | N11: NR | O11: NR | P11: Apidos CLO Ltd | Q11: BB | R11: Fitch | S11: BB
A12: 03770JAG5 | B12: 03770JAG5 | C12: 10.359942 | F12: 8.1656529 | G12: 516.99473 | H12: 101.2028 | I12: CVC Credit Partners | J12: 20250618 | K12: NR | L12: NR | M12: BB+ | N12: NR | O12: NR | P12: Apidos CLO Ltd | Q12: BB+ | R12: Fitch | S12: BB
A13: 03770MAG8 | B13: 03770MAG8 | D13: 45956 | E13: 46594 | I13: CVC Credit Partners | J13: 20230525 | K13: NR | L13: NR | M13: BBB- | N13: NR | O13: NR | P13: Apidos CLO Ltd | Q13: BBB- | R13: Fitch | S13: BBB
A14: 03770MAU7 | B14: 03770MAU7 | C14: 9.7105044 | D14: 45956 | E14: 46594 | F14: 12.197847 | G14: 282.17599 | H14: 100.1923 | I14: CVC Credit Partners | J14: 20250702 | K14: NR | L14: NR | M14: BBB- | N14: NR | O14: NR | P14: Apidos CLO Ltd | Q14: BBB- | R14: Fitch | S14: BBB
A15: 039937BA4 | B15: 039937BA4 | C15: 0 | D15: 45950 | E15: 45402 | G15: 293.33317 | H15: 100.3889 | I15: Ares CLO Management | J15: 20250807 | K15: NR | L15: NR | M15: BBB- | N15: NR | O15: NR | P15: ARES CLO Ltd | Q15: BBB- | R15: Fitch | S15: BBB
A16: 04039BAG7 | B16: 04039BAG7 | C16: 9.6083371 | F16: 12 | G16: 318.24635 | H16: 100.3889 | I16: Arini Loan Management US | J16: 20250820 | K16: BBB- | L16: NR | M16: NR | N16: NR | O16: NR | P16: Arini US CLO Limited | Q16: BBB- | R16: SP | S16: BBB
A17: 04942CAL0 | B17: 04942CAL0 | D17: 45950 | E17: 44915 | F17: 13.115368 | I17: Crescent Capital Group | J17: 20190614 | K17: NR | L17: Baa3 | M17: NR | N17: NR | O17: NR | P17: Atlas Senior Loan Fund LTD | Q17: Baa3 | R17: Moody's | S17: BBB
A18: 05553MAE1 | B18: 05553MAE1 | I18: Blackstone Private Credit Fund | J18: 20210629 | K18: NR | L18: A2 | M18: NR | N18: NR | O18: NR | P18: BCRED BSL Static CLO Ltd | Q18: A2 | R18: Moody's | S18: A
A19: 05553MAG6 | B19: 05553MAG6 | I19: Blackstone Private Credit Fund | J19: 20210629 | K19: NR | L19: Baa3 | M19: NR | N19: NR | O19: NR | P19: BCRED BSL Static CLO Ltd | Q19: Baa3 | R19: Moody's | S19: BBB
A20: 05684GAJ5 | B20: 05684GAJ5 | C20: 7.6345538 | D20: 45948 | E20: 45856 | F20: 12.146295 | H20: 100.005 | I20: Bain Capital Credit U.S. CLO Manager II | J20: 20230621 | K20: NR | L20: NR | M20: BBB- | N20: NR | O20: NR | P20: Bain Capital Credit CLO, Limit | Q20: BBB- | R20: Fitch | S20: BBB
A21: 05875AAQ1 | B21: 05875AAQ1 | C21: 9.7609555 | D21: 45945 | E21: 46583 | F21: 11.965117 | G21: 292.44529 | H21: 100.1764 | I21: Ballyrock Investment Advisors | J21: 20250711 | K21: BBB- | L21: NR | M21: NR | N21: NR | O21: NR | P21: Ballyrock Ltd | Q21: BBB- | R21: SP | S21: BBB
A22: 05876GAJ3 | B22: 05876GAJ3 | C22: 9.712812 | D22: 46047 | E22: 46585 | F22: 12 | G22: 286.84214 | H22: 100.1116 | I22: Ballyrock Investment Advisors | J22: 20250717 | K22: BBB- | L22: NR | M22: NR | N22: NR | O22: NR | P22: Ballyrock Ltd | Q22: BBB- | R22: SP | S22: BBB
A23: 05876UAE3 | B23: 05876UAE3 | H23: 100.2639 | I23: Ballyrock Ltd | J23: 20250904 | K23: BBB | L23: NR | M23: NR | N23: NR | O23: NR | P23: Ballyrock Ltd | Q23: BBB | R23: SP | S23: BBB
A24: 09077FAU9 | B24: 09077FAU9 | C24: 9.6493194 | D24: 46042 | E24: 46575 | F24: 12.439622 | G24: 304.51114 | H24: 100.605 | I24: Birch Grove Capital | J24: 20250707 | K24: NR | L24: NR | M24: BBB- | N24: NR | O24: NR | P24: Birch Grove CLO Ltd. | Q24: BBB- | R24: Fitch | S24: BBB
A25: 12481PAA5 | B25: 12481PAA5 | D25: 46037 | E25: 46583 | I25: CBAM CLO Management | J25: 20171206 | K25: NR | L25: Ba3 | M25: NR | N25: NR | O25: NR | P25: CBAMR Ltd | Q25: Ba3 | R25: Moody's | S25: BB
A26: 12516EAL5 | B26: 12516EAL5 | C26: 9.5236411 | D26: 46037 | E26: 46583 | F26: 13.427808 | G26: 296.80929 | H26: 100.1067 | I26: CBAM CLO Management | J26: 20250627 | K26: NR | L26: NR | M26: BBB+ | N26: NR | O26: NR | P26: CBAMR Ltd | Q26: BBB+ | R26: Fitch | S26: BBB
A27: 12516EAN1 | B27: 12516EAN1 | C27: 9.8113671 | D27: 46037 | E27: 46583 | F27: 12.432726 | G27: 436.23287 | H27: 100.8067 | I27: CBAM CLO Management | J27: 20250627 | K27: NR | L27: NR | M27: BBB- | N27: NR | O27: NR | P27: CBAMR Ltd | Q27: BBB- | R27: Fitch | S27: BBB
A28: 12516JAA8 | B28: 12516JAA8 | C28: 10.153624 | D28: 46037 | E28: 46583 | F28: 8.4523949 | G28: 579.82288 | H28: 101.1726 | I28: CBAM CLO Management | J28: 20250627 | K28: NR | L28: NR | M28: BB- | N28: NR | O28: NR | P28: CBAMR Ltd | Q28: BB- | R28: Fitch | S28: BB
A29: 14315BAG1 | B29: 14315BAG1 | D29: 45945 | E29: 43845 | I29: Carlyle CLO Management | J29: 20171130 | K29: NR | L29: A3 | M29: NR | N29: NR | O29: NR | P29: Carlyle Global Market Strategi | Q29: A3 | R29: Moody's | S29: A
A30: 26243EAC5 | B30: 26243EAC5 | D30: 45945 | E30: 46030 | I30: PGIM | J30: 20180111 | K30: NR | L30: A1 | M30: NR | N30: NR | O30: NR | P30: Dryden Senior Loan Fund | Q30: A1 | R30: Moody's | S30: A
A31: 26246GAW3 | B31: 26246GAW3 | C31: 0 | G31: 309.69888 | H31: 100.375 | I31: PGIM | J31: 20250808 | K31: NR | L31: NR | M31: BBB- | N31: NR | O31: NR | P31: Dryden Senior Loan Fund | Q31: BBB- | R31: Fitch | S31: BBB
A32: 26253QAG6 | B32: 26253QAG6 | D32: 45945 | E32: 46492 | I32: PGIM | J32: 20230328 | K32: BBB- | L32: NR | M32: NR | N32: NR | O32: NR | P32: Dryden Senior Loan Fund | Q32: BBB- | R32: SP | S32: BBB
A33: 26253QAS0 | B33: 26253QAS0 | C33: 9.4551501 | D33: 45945 | E33: 46492 | F33: 12.059184 | G33: 373.2646 | H33: 100.4377 | I33: PGIM | J33: 20250522 | K33: BBB- | L33: NR | M33: NR | N33: NR | O33: NR | P33: Dryden Senior Loan Fund | Q33: BBB- | R33: SP | S33: BBB
A34: 29002HBE8 | B34: 29002HBE8 | D34: 45948 | E34: 46193 | F34: 10.447594 | I34: Elmwood Asset Management | J34: 20240620 | K34: NR | L34: NR | M34: BBB- | N34: NR | O34: NR | P34: Elmwood CLO III Ltd | Q34: BBB- | R34: Fitch | S34: BBB
A35: 29003KAA9 | B35: 29003KAA9 | D35: 45952 | E35: 46213 | I35: Elmwood RR CLO | J35: 20220330 | K35: BB- | L35: NR | M35: NR | N35: NR | O35: NR | P35: Elmwood CLO 15 Ltd | Q35: BB- | R35: SP | S35: BB
A36: 29004KAJ9 | B36: 29004KAJ9 | C36: 9.68211 | D36: 46042 | E36: 46585 | F36: 12 | G36: 272.36225 | H36: 100.4378 | I36: Elmwood Asset Management | J36: 20250717 | K36: NR | L36: NR | M36: BBB- | N36: NR | O36: NR | P36: Elmwood CLO 43 Ltd | Q36: BBB- | R36: Fitch | S36: BBB
A37: 30605YAB7 | B37: 30605YAB7 | C37: 0.041666667 | D37: 45884 | F37: 91.081592 | G37: -12848.936 | H37: 99.43349 | I37: Falcon Aerospace Ltd | J37: 20170214 | K37: A | L37: NR | M37: NR | N37: A- | O37: NR | P37: Falcon Aerospace Ltd | Q37: A | R37: SP | S37: A
A38: 33883DAE4 | B38: 33883DAE4 | D38: 45947 | E38: 46183 | I38: NYL Investors | J38: 20230509 | K38: NR | L38: NR | M38: A | N38: NR | O38: NR | P38: Flatiron CLO Ltd | Q38: A | R38: Fitch | S38: A
A39: 33883DAG9 | B39: 33883DAG9 | D39: 45947 | E39: 46183 | I39: NYL Investors | J39: 20230509 | K39: NR | L39: NR | M39: BBB- | N39: NR | O39: NR | P39: Flatiron CLO Ltd | Q39: BBB- | R39: Fitch | S39: BBB
A40: 33883DAU8 | B40: 33883DAU8 | C40: 6.8201395 | D40: 45947 | E40: 46183 | F40: 18.039227 | G40: 170.27213 | H40: 100.5538 | I40: NYL Investors | J40: 20250610 | K40: NR | L40: NR | M40: A+ | N40: NR | O40: NR | P40: Flatiron CLO Ltd | Q40: A+ | R40: Fitch | S40: A
A41: 36626AAD7 | B41: 36626AAD7 | C41: 8.1636231 | F41: 18 | G41: 215.11399 | H41: 100.5387 | I41: Garnet Credit Management | J41: 20250703 | K41: A | L41: NR | M41: NR | N41: NR | O41: NR | P41: Garnet CLO Ltd | Q41: A | R41: SP | S41: A
A42: 38139FAG5 | B42: 38139FAG5 | D42: 45950 | E42: 46562 | I42: GLM II | J42: 20230622 | K42: NR | L42: NR | M42: A | N42: NR | O42: NR | P42: GoldenTree Loan Management US | Q42: A | R42: Fitch | S42: A
A43: 38139FAJ9 | B43: 38139FAJ9 | D43: 45950 | E43: 46562 | I43: GLM II | J43: 20230622 | K43: NR | L43: NR | M43: BBB- | N43: NR | O43: NR | P43: GoldenTree Loan Management US | Q43: BBB- | R43: Fitch | S43: BBB
A44: 38139FAW0 | B44: 38139FAW0 | C44: 9.6833798 | D44: 45950 | E44: 46562 | F44: 12.042431 | G44: 273.0174 | H44: 100.501 | I44: GLM II | J44: 20250624 | K44: NR | L44: NR | M44: BBB- | N44: NR | O44: NR | P44: GoldenTree Loan Management US | Q44: BBB- | R44: Fitch | S44: BBB
A45: 38139QAL0 | B45: 38139QAL0 | C45: 9.6333088 | F45: 12 | G45: 268.34362 | H45: 100.3889 | I45: GLM III | J45: 20250807 | K45: NR | L45: NR | M45: BBB- | N45: NR | O45: NR | P45: GoldenTree Loan Management US | Q45: BBB- | R45: Fitch | S45: BBB
A46: 38174YAE5 | B46: 38174YAE5 | I46: GC Investment Management | J46: 20171109 | K46: AA | L46: NR | M46: NR | N46: NR | O46: NR | P46: Golub Capital Partners CLO Ltd | Q46: AA | R46: SP | S46: AA
A47: 38174YAG0 | B47: 38174YAG0 | I47: GC Investment Management | J47: 20171109 | K47: BBB+ | L47: NR | M47: NR | N47: NR | O47: NR | P47: Golub Capital Partners CLO Ltd | Q47: BBB+ | R47: SP | S47: BBB
A48: 38181PAG0 | B48: 38181PAG0 | C48: 0 | D48: 45955 | E48: 45863 | G48: 190.34991 | H48: 100.25 | I48: OPAL BSL | J48: 20250815 | K48: NR | L48: NR | M48: A | N48: NR | O48: NR | P48: Golub Capital Partners CLO, LT | Q48: A | R48: Fitch | S48: A
A49: 40169CAJ5 | B49: 40169CAJ5 | C49: 2.0965508 | D49: 45945 | E49: 45282 | F49: 13.816869 | G49: 460.1772 | H49: 93.1954 | I49: Guggenheim Corporate Funding | J49: 20211222 | K49: NR | L49: NR | M49: NR | N49: BBB- | O49: NR | P49: Guggenheim CLO Ltd | Q49: BBB- | R49: KBRA | S49: BBB
A50: 41757PAJ2 | B50: 41757PAJ2 | C50: 9.6645992 | D50: 46039 | E50: 46585 | F50: 12 | G50: 338.07629 | H50: 100.3888 | I50: Investcorp Credit Management US | J50: 20250730 | K50: NR | L50: NR | M50: BBB- | N50: NR | O50: NR | P50: Harvest US CLO Ltd | Q50: BBB- | R50: Fitch | S50: BBB
A51: 43128QAL3 | B51: 43128QAL3 | C51: 9.6223237 | F51: 12 | G51: 268.4338 | H51: 100.3889 | I51: Blackstone CLO Management | J51: 20250821 | K51: NR | L51: NR | M51: BBB- | N51: NR | O51: NR | P51: Higley Park Clo Ltd | Q51: BBB- | R51: Fitch | S51: BBB
A52: 442911AG8 | B52: 442911AG8 | D52: 45950 | E52: 46588 | I52: HPS Investment Partners | J52: 20230627 | K52: A | L52: NR | M52: NR | N52: NR | O52: NR | P52: HPS Loan Management Ltd | Q52: A | R52: SP | S52: A
A53: 442911AJ2 | B53: 442911AJ2 | D53: 45950 | E53: 46588 | I53: HPS Investment Partners | J53: 20230627 | K53: BBB- | L53: NR | M53: NR | N53: NR | O53: NR | P53: HPS Loan Management Ltd | Q53: BBB- | R53: SP | S53: BBB
A54: 442911AS2 | B54: 442911AS2 | C54: 9.1879788 | D54: 45950 | E54: 46588 | F54: 18.156844 | G54: 198.69778 | H54: 100.0881 | I54: HPS Investment Partners | J54: 20250721 | K54: NR | L54: NR | M54: A | N54: NR | O54: NR | P54: HPS Loan Management Ltd | Q54: A | R54: Fitch | S54: A
A55: 442911AU7 | B55: 442911AU7 | C55: 9.7230354 | D55: 45950 | E55: 46588 | F55: 12.168321 | G55: 303.31823 | H55: 100.1129 | I55: HPS Investment Partners | J55: 20250721 | K55: NR | L55: NR | M55: BBB- | N55: NR | O55: NR | P55: HPS Loan Management Ltd | Q55: BBB- | R55: Fitch | S55: BBB
A56: 442921AJ1 | B56: 442921AJ1 | C56: 10.331832 | D56: 45950 | E56: 46588 | F56: 8.1759715 | G56: 595.77877 | H56: 100.262 | I56: HPS Investment Partners | J56: 20250721 | K56: NR | L56: NR | M56: BB- | N56: NR | O56: NR | P56: HPS Loan Management Ltd | Q56: BB- | R56: Fitch | S56: BB
A57: 449278AG5 | B57: 449278AG5 | D57: 45948 | E57: 46586 | I57: ICG Debt Advisors | J57: 20230906 | K57: BBB- | L57: NR | M57: NR | N57: NR | O57: NR | P57: ICG US CLO Ltd | Q57: BBB- | R57: SP | S57: BBB
A58: 44931NAW1 | B58: 44931NAW1 | C58: 5.258316 | D58: 45959 | E58: 45045 | F58: 8.8787906 | G58: 384.3399 | H58: 100.2865 | I58: ICG Debt Advisors | J58: 20210528 | K58: BBB- | L58: NR | M58: NR | N58: NR | O58: NR | P58: ICG US CLO Ltd | Q58: BBB- | R58: SP | S58: BBB
A59: 46091RAE3 | B59: 46091RAE3 | D59: 45945 | E59: 46583 | I59: Invesco CLO Equity Fund 3 | J59: 20230817 | K59: A | L59: NR | M59: NR | N59: NR | O59: NR | P59: Invesco U.S. CLO 2025-2, Ltd. | Q59: A | R59: SP | S59: A
A60: 46091RAG8 | B60: 46091RAG8 | D60: 45945 | E60: 46583 | I60: Invesco CLO Equity Fund 3 | J60: 20230817 | K60: BBB- | L60: NR | M60: NR | N60: NR | O60: NR | P60: Invesco U.S. CLO 2025-2, Ltd. | Q60: BBB- | R60: SP | S60: BBB
A61: 46147KAD4 | B61: 46147KAD4 | D61: 45951 | E61: 46498 | I61: Invesco CLO Equity Fund 3 | J61: 20230328 | K61: NR | L61: NR | M61: BBB- | N61: NR | O61: NR | P61: Invesco U.S. CLO 2025-2, Ltd. | Q61: BBB- | R61: Fitch | S61: BBB
A62: 481954AG0 | B62: 481954AG0 | C62: 9.7071233 | D62: 46037 | E62: 46583 | F62: 12 | G62: 339.92339 | H62: 100.2393 | I62: KKR Financial Advisors II | J62: 20250703 | K62: NR | L62: NR | M62: BBB- | N62: NR | O62: NR | P62: KKR Financial CLO Ltd | Q62: BBB- | R62: Fitch | S62: BBB
A63: 48255XAW8 | B63: 48255XAW8 | C63: 9.6372363 | D63: 45946 | E63: 46584 | F63: 12.970114 | G63: 299.11142 | H63: 100.7623 | I63: KKR Financial Advisors II | J63: 20250707 | K63: NR | L63: NR | M63: BBB | N63: NR | O63: NR | P63: KKR Financial CLO Ltd | Q63: BBB | R63: Fitch | S63: BBB
A64: 48257CAJ1 | B64: 48257CAJ1 | C64: 7.6881911 | D64: 46037 | E64: 46189 | F64: 11.572145 | G64: 371.04705 | H64: 100.6784 | I64: KKR Financial Advisors II | J64: 20250616 | K64: NR | L64: NR | M64: BBB- | N64: NR | O64: NR | P64: KKR Financial CLO Ltd | Q64: BBB- | R64: Fitch | S64: BBB
A65: 542798AG8 | B65: 542798AG8 | C65: 2.3373505 | D65: 45947 | E65: 43847 | F65: 38.541549 | G65: 173.29035 | H65: 100.4838 | I65: Blackstone Liquid Credit Strategies | J65: 20171228 | K65: NR | L65: Aa1 | M65: NR | N65: NR | O65: NR | P65: Long Point Park CLO Ltd | Q65: Aa1 | R65: Moody's | S65: AA
A66: 55817GAW1 | B66: 55817GAW1 | C66: 9.6369096 | D66: 45951 | E66: 46543 | F66: 13.229202 | G66: 307.19499 | H66: 100.5496 | I66: UBS Asset Management (Americas) | J66: 20250605 | K66: NR | L66: NR | M66: BBB | N66: NR | O66: NR | P66: Madison Park Funding Ltd | Q66: BBB | R66: Fitch | S66: BBB
A67: 55817HAU3 | B67: 55817HAU3 | D67: 45947 | E67: 45855 | F67: 11.061923 | I67: UBS Asset Management (Americas) | J67: 20230717 | K67: NR | L67: NR | M67: BBB- | N67: NR | O67: NR | P67: Madison Park Funding Ltd | Q67: BBB- | R67: Fitch | S67: BBB
A68: 55821MAA0 | B68: 55821MAA0 | C68: 6.4471528 | D68: 45947 | E68: 45094 | F68: 7.8203246 | G68: 607.81424 | H68: 100.8671 | I68: Credit Suisse Asset Management | J68: 20210617 | K68: BB- | L68: NR | M68: NR | N68: NR | O68: NR | P68: Madison Park Funding Ltd | Q68: BB- | R68: SP | S68: BB
A69: 559922AG4 | B69: 559922AG4 | D69: 45955 | E69: 46549 | I69: Blackrock Financial Management | J69: 20230608 | K69: BBB- | L69: NR | M69: NR | N69: NR | O69: NR | P69: Magnetite CLO Ltd | Q69: BBB- | R69: SP | S69: BBB
A70: 56577GAJ8 | B70: 56577GAJ8 | C70: 1.1724087 | D70: 45945 | E70: 44576 | F70: 34.628597 | G70: 380.14373 | H70: 96.9857 | I70: Maranon Capital | J70: 20201208 | K70: NR | L70: NR | M70: NR | N70: BBB+ | O70: NR | P70: Maranon Loan Funding Ltd | Q70: BBB+ | R70: KBRA | S70: BBB
A71: 56577JAG8 | B71: 56577JAG8 | C71: 0.38137399 | D71: 45945 | E71: 45122 | F71: 19.48584 | G71: 487.78704 | H71: 98.7781 | I71: Maranon Management | J71: 20210623 | K71: NR | L71: NR | M71: NR | N71: BBB | O71: NR | P71: Maranon Loan Funding Ltd | Q71: BBB | R71: KBRA | S71: BBB
A72: 56577LAN8 | B72: 56577LAN8 | C72: 0.29289842 | D72: 45945 | E72: 45031 | F72: 20.125623 | G72: 455.54444 | H72: 99.1429 | I72: Maranon Capital | J72: 20210519 | K72: NR | L72: NR | M72: NR | N72: BBB | O72: NR | P72: Maranon Loan Funding Ltd | Q72: BBB | R72: KBRA | S72: BBB
A73: 59803TAY7 | B73: 59803TAY7 | D73: 45948 | E73: 46586 | I73: MidOcean Credit RR Manager | J73: 20240418 | K73: NR | L73: NR | M73: BBB- | N73: NR | O73: NR | P73: MidOcean Credit CLO | Q73: BBB- | R73: Fitch | S73: BBB
A74: 64133JAQ7 | B74: 64133JAQ7 | C74: 5.4661879 | D74: 45950 | E74: 45677 | F74: 7.2437066 | G74: 703.4057 | H74: 101.0785 | I74: Neuberger Berman Loan Advisers | J74: 20240311 | K74: BB- | L74: NR | M74: NR | N74: NR | O74: NR | P74: Neuberger Berman CLO Ltd | Q74: BB- | R74: SP | S74: BB
A75: 67116TAM8 | B75: 67116TAM8 | I75: Oak Hill Advisors | J75: 20230524 | K75: BBB- | L75: NR | M75: NR | N75: NR | O75: NR | P75: Oak Hill Credit | Q75: BBB- | R75: SP | S75: BBB
A76: 67181DAE1 | B76: 67181DAE1 | C76: 0.30534781 | D76: 45889 | F76: 27.4503 | G76: 1220.0108 | H76: 97.17864 | I76: Oak Street Investment Grade Ne | J76: 20201113 | K76: BBB+ | L76: NR | M76: NR | N76: NR | O76: NR | P76: Oak Street Investment Grade Ne | Q76: BBB+ | R76: SP | S76: BBB
A77: 67190AAC0 | B77: 67190AAC0 | C77: 0.47170212 | D77: 45889 | F77: 27.4503 | G77: 464.5625 | H77: 97.78384 | I77: Oak Street Investment Grade Ne | J77: 20210127 | K77: BBB+ | L77: NR | M77: NR | N77: NR | O77: NR | P77: Oak Street Investment Grade Ne | Q77: BBB+ | R77: SP | S77: BBB
A78: 67190AAD8 | B78: 67190AAD8 | C78: 2.4303684 | D78: 45889 | F78: 27.4503 | G78: 585.29407 | H78: 87.626225 | I78: Oak Street Investment Grade Ne | J78: 20210127 | K78: BBB+ | L78: NR | M78: NR | N78: NR | O78: NR | P78: Oak Street Investment Grade Ne | Q78: BBB+ | R78: SP | S78: BBB
A79: 67571LAW1 | B79: 67571LAW1 | C79: 9.7381478 | D79: 45955 | E79: 46527 | F79: 11.89095 | G79: 377.50389 | H79: 100.8619 | I79: Octagon Credit Investors | J79: 20250520 | K79: NR | L79: NR | M79: BBB- | N79: NR | O79: NR | P79: Octagon 67 Ltd | Q79: BBB- | R79: Fitch | S79: BBB
A80: 67577YAA5 | B80: 67577YAA5 | D80: 45955 | E80: 46527 | I80: Octagon Credit Investors | J80: 20230329 | K80: NR | L80: NR | M80: BB- | N80: NR | O80: NR | P80: Octagon 67 Ltd | Q80: BB- | R80: Fitch | S80: BB
A81: 67590EBN3 | B81: 67590EBN3 | D81: 45949 | E81: 44589 | I81: Octagon Credit Investors | J81: 20210728 | K81: BBB- | L81: NR | M81: NR | N81: NR | O81: NR | P81: Octagon Investment Partners XV | Q81: BBB- | R81: SP | S81: BBB
A82: 67707LAE8 | B82: 67707LAE8 | C82: 6.4722222 | D82: 45948 | E82: 45277 | F82: 10.863803 | H82: 100.45 | I82: Oak Hill Advisors | J82: 20211217 | K82: NR | L82: NR | M82: BBB- | N82: NR | O82: NR | P82: Oak Hill Credit | Q82: BBB- | R82: Fitch | S82: BBB
A83: 69688FAW0 | B83: 69688FAW0 | C83: 0 | D83: 45945 | E83: 45269 | G83: 274.85899 | H83: 100.375 | I83: Palmer Square Capital Management | J83: 20250814 | K83: NR | L83: NR | M83: BBB- | N83: NR | O83: NR | P83: Palmer Square CLO Ltd | Q83: BBB- | R83: Fitch | S83: BBB
A84: 69703AAG7 | B84: 69703AAG7 | D84: 45950 | E84: 46588 | I84: Palmer Square Capital Management | J84: 20230601 | K84: A | L84: NR | M84: NR | N84: NR | O84: NR | P84: Palmer Square CLO Ltd | Q84: A | R84: SP | S84: A
A85: 69703AAJ1 | B85: 69703AAJ1 | D85: 45950 | E85: 46588 | I85: Palmer Square Capital Management | J85: 20230601 | K85: BBB- | L85: NR | M85: NR | N85: NR | O85: NR | P85: Palmer Square CLO Ltd | Q85: BBB- | R85: SP | S85: BBB
A86: 69703AAU6 | B86: 69703AAU6 | C86: 9.6737587 | D86: 45950 | E86: 46588 | F86: 12.50252 | G86: 337.84601 | H86: 100.1432 | I86: Palmer Square Capital Management | J86: 20250522 | K86: BBB- | L86: NR | M86: NR | N86: NR | O86: NR | P86: Palmer Square CLO Ltd | Q86: BBB- | R86: SP | S86: BBB
A87: 69704GAJ7 | B87: 69704GAJ7 | C87: 9.6362707 | F87: 12 | G87: 273.43681 | H87: 100.3889 | I87: Palmer Square Capital Management | J87: 20250820 | K87: BBB- | L87: NR | M87: NR | N87: NR | O87: NR | P87: Palmer Square CLO Ltd | Q87: BBB- | R87: SP | S87: BBB
A88: 69915NAQ1 | B88: 69915NAQ1 | C88: 7.6524448 | D88: 45950 | E88: 46203 | F88: 12.035856 | G88: 353.4631 | H88: 100.3772 | I88: DoubleLine Capital | J88: 20250630 | K88: BBB- | L88: NR | M88: NR | N88: NR | O88: NR | P88: Parallel Ltd | Q88: BBB- | R88: SP | S88: BBB
A89: 70019UAJ4 | B89: 70019UAJ4 | H89: 100.375 | I89: Park Blue CLO Ltd | J89: 20250904 | K89: BBB- | L89: NR | M89: NR | N89: NR | O89: NR | P89: Park Blue CLO Ltd | Q89: BBB- | R89: SP | S89: BBB
A90: 750104AJ0 | B90: 750104AJ0 | D90: 45950 | E90: 46497 | I90: Redding Ridge Asset Management | J90: 20230504 | K90: NR | L90: NR | M90: BBB- | N90: NR | O90: NR | P90: Rad CLO Ltd | Q90: BBB- | R90: Fitch | S90: BBB
A91: 75884FAA7 | B91: 75884FAA7 | C91: 10.35653 | F91: 8 | G91: 566.91233 | H91: 100.4707 | I91: Napier Park Global Capital (US) | J91: 20250625 | K91: NR | L91: NR | M91: BB- | N91: NR | O91: NR | P91: Regatta 32 Funding Ltd. | Q91: BB- | R91: Fitch | S91: BB
A92: 758978AE0 | B92: 758978AE0 | D92: 45945 | E92: 46579 | I92: Napier Park Global Capital (US) | J92: 20230629 | K92: NR | L92: NR | M92: A | N92: NR | O92: NR | P92: Regatta XXV Funding Ltd. | Q92: A | R92: Fitch | S92: A
A93: 758978AG5 | B93: 758978AG5 | D93: 45945 | E93: 46579 | I93: Napier Park Global Capital (US) | J93: 20230629 | K93: NR | L93: NR | M93: BBB- | N93: NR | O93: NR | P93: Regatta XXV Funding Ltd. | Q93: BBB- | R93: Fitch | S93: BBB
A94: 758978AS9 | B94: 758978AS9 | C94: 9.1238882 | D94: 45945 | E94: 46579 | F94: 18.043504 | G94: 193.19763 | H94: 100.1232 | I94: Napier Park Global Capital (US) | J94: 20250711 | K94: NR | L94: NR | M94: A | N94: NR | O94: NR | P94: Regatta XXV Funding Ltd. | Q94: A | R94: Fitch | S94: A
A95: 758978AU4 | B95: 758978AU4 | C95: 9.6561344 | D95: 45945 | E95: 46579 | F95: 12.046687 | G95: 292.13216 | H95: 100.1976 | I95: Napier Park Global Capital (US) | J95: 20250711 | K95: NR | L95: NR | M95: BBB- | N95: NR | O95: NR | P95: Regatta XXV Funding Ltd. | Q95: BBB- | R95: Fitch | S95: BBB
A96: 78396YAA1 | B96: 78396YAA1 | D96: 45955 | I96: SESAC Finance, LLC | J96: 20190809 | K96: NR | L96: NR | M96: NR | N96: BBB- | O96: BBB | P96: SESAC Finance, LLC | Q96: BBB- | R96: KBRA | S96: BBB
A97: 826525AC1 | B97: 826525AC1 | I97: Sierra Receivables Funding Co | J97: 20200813 | K97: BBB | L97: NR | M97: BBB | N97: NR | O97: NR | P97: Sierra Receivables Funding Co | Q97: BBB | R97: SP | S97: BBB
A98: 827920AJ8 | B98: 827920AJ8 | C98: 9.6619287 | D98: 46037 | E98: 46569 | F98: 12.105848 | G98: 305.00916 | H98: 100.2419 | I98: Silver Point Select C CLO Manager | J98: 20250701 | K98: NR | L98: NR | M98: BBB- | N98: NR | O98: NR | P98: Silver Point CLO, Ltd | Q98: BBB- | R98: Fitch | S98: BBB
A99: 82809VAJ1 | B99: 82809VAJ1 | C99: 9.60531 | F99: 13 | G99: 340.87998 | H99: 101.2026 | I99: Silver Point Select C CLO Manager | J99: 20250606 | K99: NR | L99: NR | M99: BBB- | N99: NR | O99: NR | P99: Silver Point CLO, Ltd | Q99: BBB- | R99: Fitch | S99: BBB
A100: 83013LAG9 | B100: 83013LAG9 | C100: 9.6180592 | F100: 12 | G100: 283.24786 | H100: 100.3888 | I100: Sixth Street CLO Management | J100: 20250813 | K100: BBB- | L100: NR | M100: NR | N100: NR | O100: NR | P100: Sixth Street CLO LTD. | Q100: BBB- | R100: SP | S100: BBB
...
